[
  {
    "Type": "KeyUp",
    "Time": 61,
    "X": null,
    "Y": null,
    "Delta": null,
    "KeyCode": 35
  },
  {
    "Type": "MouseMove",
    "Time": 266,
    "X": 570,
    "Y": 597,
    "Delta": null,
    "KeyCode": null
  },
  {
    "Type": "MouseMove",
    "Time": 292,
    "X": 555,
    "Y": 588,
    "Delta": null,
    "KeyCode": null
  },
  {
    "Type": "MouseMove",
    "Time": 312,
    "X": 543,
    "Y": 576,
    "Delta": null,
    "KeyCode": null
  },
  {
    "Type": "MouseMove",
    "Time": 332,
    "X": 528,
    "Y": 558,
    "Delta": null,
    "KeyCode": null
  },
  {
    "Type": "MouseMove",
    "Time": 341,
    "X": 522,
    "Y": 549,
    "Delta": null,
    "KeyCode": null
  },
  {
    "Type": "MouseMove",
    "Time": 345,
    "X": 519,
    "Y": 540,
    "Delta": null,
    "KeyCode": null
  },
  {
    "Type": "MouseMove",
    "Time": 353,
    "X": 513,
    "Y": 525,
    "Delta": null,
    "KeyCode": null
  },
  {
    "Type": "MouseMove",
    "Time": 361,
    "X": 507,
    "Y": 510,
    "Delta": null,
    "KeyCode": null
  },
  {
    "Type": "MouseMove",
    "Time": 383,
    "X": 495,
    "Y": 480,
    "Delta": null,
    "KeyCode": null
  },
  {
    "Type": "MouseMove",
    "Time": 385,
    "X": 489,
    "Y": 462,
    "Delta": null,
    "KeyCode": null
  },
  {
    "Type": "MouseMove",
    "Time": 393,
    "X": 483,
    "Y": 444,
    "Delta": null,
    "KeyCode": null
  },
  {
    "Type": "MouseMove",
    "Time": 417,
    "X": 474,
    "Y": 417,
    "Delta": null,
    "KeyCode": null
  },
  {
    "Type": "MouseMove",
    "Time": 418,
    "X": 471,
    "Y": 411,
    "Delta": null,
    "KeyCode": null
  },
  {
    "Type": "MouseMove",
    "Time": 447,
    "X": 462,
    "Y": 378,
    "Delta": null,
    "KeyCode": null
  },
  {
    "Type": "MouseMove",
    "Time": 469,
    "X": 456,
    "Y": 348,
    "Delta": null,
    "KeyCode": null
  },
  {
    "Type": "MouseMove",
    "Time": 490,
    "X": 456,
    "Y": 336,
    "Delta": null,
    "KeyCode": null
  },
  {
    "Type": "MouseMove",
    "Time": 491,
    "X": 453,
    "Y": 330,
    "Delta": null,
    "KeyCode": null
  },
  {
    "Type": "MouseMove",
    "Time": 497,
    "X": 453,
    "Y": 324,
    "Delta": null,
    "KeyCode": null
  },
  {
    "Type": "MouseMove",
    "Time": 526,
    "X": 453,
    "Y": 312,
    "Delta": null,
    "KeyCode": null
  },
  {
    "Type": "MouseMove",
    "Time": 531,
    "X": 453,
    "Y": 309,
    "Delta": null,
    "KeyCode": null
  },
  {
    "Type": "MouseMove",
    "Time": 559,
    "X": 450,
    "Y": 300,
    "Delta": null,
    "KeyCode": null
  },
  {
    "Type": "MouseMove",
    "Time": 582,
    "X": 447,
    "Y": 288,
    "Delta": null,
    "KeyCode": null
  },
  {
    "Type": "MouseMove",
    "Time": 603,
    "X": 444,
    "Y": 282,
    "Delta": null,
    "KeyCode": null
  },
  {
    "Type": "MouseMove",
    "Time": 604,
    "X": 444,
    "Y": 276,
    "Delta": null,
    "KeyCode": null
  },
  {
    "Type": "MouseMove",
    "Time": 611,
    "X": 444,
    "Y": 273,
    "Delta": null,
    "KeyCode": null
  },
  {
    "Type": "MouseMove",
    "Time": 619,
    "X": 444,
    "Y": 270,
    "Delta": null,
    "KeyCode": null
  },
  {
    "Type": "MouseMove",
    "Time": 627,
    "X": 441,
    "Y": 264,
    "Delta": null,
    "KeyCode": null
  },
  {
    "Type": "MouseMove",
    "Time": 652,
    "X": 441,
    "Y": 252,
    "Delta": null,
    "KeyCode": null
  },
  {
    "Type": "MouseMove",
    "Time": 659,
    "X": 441,
    "Y": 246,
    "Delta": null,
    "KeyCode": null
  },
  {
    "Type": "MouseMove",
    "Time": 686,
    "X": 438,
    "Y": 228,
    "Delta": null,
    "KeyCode": null
  },
  {
    "Type": "MouseMove",
    "Time": 691,
    "X": 435,
    "Y": 225,
    "Delta": null,
    "KeyCode": null
  },
  {
    "Type": "MouseMove",
    "Time": 715,
    "X": 435,
    "Y": 216,
    "Delta": null,
    "KeyCode": null
  },
  {
    "Type": "MouseMove",
    "Time": 738,
    "X": 432,
    "Y": 204,
    "Delta": null,
    "KeyCode": null
  },
  {
    "Type": "MouseMove",
    "Time": 760,
    "X": 432,
    "Y": 198,
    "Delta": null,
    "KeyCode": null
  },
  {
    "Type": "MouseMove",
    "Time": 771,
    "X": 432,
    "Y": 195,
    "Delta": null,
    "KeyCode": null
  },
  {
    "Type": "MouseMove",
    "Time": 779,
    "X": 432,
    "Y": 192,
    "Delta": null,
    "KeyCode": null
  },
  {
    "Type": "MouseMove",
    "Time": 805,
    "X": 429,
    "Y": 189,
    "Delta": null,
    "KeyCode": null
  },
  {
    "Type": "MouseMove",
    "Time": 806,
    "X": 429,
    "Y": 186,
    "Delta": null,
    "KeyCode": null
  },
  {
    "Type": "MouseMove",
    "Time": 813,
    "X": 429,
    "Y": 183,
    "Delta": null,
    "KeyCode": null
  },
  {
    "Type": "MouseMove",
    "Time": 839,
    "X": 426,
    "Y": 180,
    "Delta": null,
    "KeyCode": null
  },
  {
    "Type": "MouseMove",
    "Time": 845,
    "X": 426,
    "Y": 177,
    "Delta": null,
    "KeyCode": null
  },
  {
    "Type": "MouseMove",
    "Time": 869,
    "X": 426,
    "Y": 174,
    "Delta": null,
    "KeyCode": null
  },
  {
    "Type": "MouseMove",
    "Time": 899,
    "X": 423,
    "Y": 171,
    "Delta": null,
    "KeyCode": null
  },
  {
    "Type": "MouseMove",
    "Time": 909,
    "X": 423,
    "Y": 168,
    "Delta": null,
    "KeyCode": null
  },
  {
    "Type": "MouseMove",
    "Time": 931,
    "X": 420,
    "Y": 165,
    "Delta": null,
    "KeyCode": null
  },
  {
    "Type": "MouseMove",
    "Time": 953,
    "X": 420,
    "Y": 159,
    "Delta": null,
    "KeyCode": null
  },
  {
    "Type": "MouseMove",
    "Time": 978,
    "X": 420,
    "Y": 156,
    "Delta": null,
    "KeyCode": null
  },
  {
    "Type": "MouseMove",
    "Time": 978,
    "X": 417,
    "Y": 156,
    "Delta": null,
    "KeyCode": null
  },
  {
    "Type": "MouseMove",
    "Time": 1000,
    "X": 417,
    "Y": 150,
    "Delta": null,
    "KeyCode": null
  },
  {
    "Type": "MouseMove",
    "Time": 1020,
    "X": 414,
    "Y": 147,
    "Delta": null,
    "KeyCode": null
  },
  {
    "Type": "MouseMove",
    "Time": 1043,
    "X": 411,
    "Y": 144,
    "Delta": null,
    "KeyCode": null
  },
  {
    "Type": "MouseMove",
    "Time": 1045,
    "X": 411,
    "Y": 141,
    "Delta": null,
    "KeyCode": null
  },
  {
    "Type": "MouseMove",
    "Time": 1075,
    "X": 411,
    "Y": 138,
    "Delta": null,
    "KeyCode": null
  },
  {
    "Type": "MouseMove",
    "Time": 1111,
    "X": 408,
    "Y": 135,
    "Delta": null,
    "KeyCode": null
  },
  {
    "Type": "MouseMove",
    "Time": 1211,
    "X": 408,
    "Y": 132,
    "Delta": null,
    "KeyCode": null
  },
  {
    "Type": "MouseMove",
    "Time": 1239,
    "X": 405,
    "Y": 132,
    "Delta": null,
    "KeyCode": null
  },
  {
    "Type": "MouseMove",
    "Time": 1290,
    "X": 405,
    "Y": 129,
    "Delta": null,
    "KeyCode": null
  },
  {
    "Type": "MouseMove",
    "Time": 1310,
    "X": 402,
    "Y": 129,
    "Delta": null,
    "KeyCode": null
  },
  {
    "Type": "MouseMove",
    "Time": 1439,
    "X": 399,
    "Y": 126,
    "Delta": null,
    "KeyCode": null
  },
  {
    "Type": "MouseMove",
    "Time": 1931,
    "X": 396,
    "Y": 123,
    "Delta": null,
    "KeyCode": null
  },
  {
    "Type": "MouseMove",
    "Time": 2338,
    "X": 393,
    "Y": 120,
    "Delta": null,
    "KeyCode": null
  },
  {
    "Type": "DragStart",
    "Time": 2645,
    "X": 393,
    "Y": 120,
    "Delta": null,
    "KeyCode": null
  },
  {
    "Type": "DragEnd",
    "Time": 2698,
    "X": 393,
    "Y": 120,
    "Delta": null,
    "KeyCode": null
  },
  {
    "Type": "MouseMove",
    "Time": 3045,
    "X": 390,
    "Y": 120,
    "Delta": null,
    "KeyCode": null
  },
  {
    "Type": "MouseMove",
    "Time": 3066,
    "X": 387,
    "Y": 120,
    "Delta": null,
    "KeyCode": null
  },
  {
    "Type": "MouseMove",
    "Time": 3069,
    "X": 384,
    "Y": 120,
    "Delta": null,
    "KeyCode": null
  },
  {
    "Type": "MouseMove",
    "Time": 3111,
    "X": 381,
    "Y": 120,
    "Delta": null,
    "KeyCode": null
  },
  {
    "Type": "MouseMove",
    "Time": 3143,
    "X": 378,
    "Y": 120,
    "Delta": null,
    "KeyCode": null
  },
  {
    "Type": "MouseMove",
    "Time": 3175,
    "X": 375,
    "Y": 120,
    "Delta": null,
    "KeyCode": null
  },
  {
    "Type": "MouseMove",
    "Time": 3195,
    "X": 372,
    "Y": 120,
    "Delta": null,
    "KeyCode": null
  },
  {
    "Type": "MouseMove",
    "Time": 3214,
    "X": 366,
    "Y": 120,
    "Delta": null,
    "KeyCode": null
  },
  {
    "Type": "MouseMove",
    "Time": 3245,
    "X": 363,
    "Y": 120,
    "Delta": null,
    "KeyCode": null
  },
  {
    "Type": "MouseMove",
    "Time": 3333,
    "X": 360,
    "Y": 120,
    "Delta": null,
    "KeyCode": null
  },
  {
    "Type": "MouseMove",
    "Time": 3367,
    "X": 357,
    "Y": 120,
    "Delta": null,
    "KeyCode": null
  },
  {
    "Type": "MouseMove",
    "Time": 3391,
    "X": 354,
    "Y": 120,
    "Delta": null,
    "KeyCode": null
  },
  {
    "Type": "MouseMove",
    "Time": 3442,
    "X": 351,
    "Y": 117,
    "Delta": null,
    "KeyCode": null
  },
  {
    "Type": "MouseMove",
    "Time": 3711,
    "X": 348,
    "Y": 117,
    "Delta": null,
    "KeyCode": null
  },
  {
    "Type": "DragStart",
    "Time": 4083,
    "X": 348,
    "Y": 117,
    "Delta": null,
    "KeyCode": null
  },
  {
    "Type": "DragEnd",
    "Time": 4143,
    "X": 348,
    "Y": 117,
    "Delta": null,
    "KeyCode": null
  },
  {
    "Type": "MouseMove",
    "Time": 4381,
    "X": 345,
    "Y": 120,
    "Delta": null,
    "KeyCode": null
  },
  {
    "Type": "MouseMove",
    "Time": 4410,
    "X": 342,
    "Y": 129,
    "Delta": null,
    "KeyCode": null
  },
  {
    "Type": "MouseMove",
    "Time": 4429,
    "X": 333,
    "Y": 147,
    "Delta": null,
    "KeyCode": null
  },
  {
    "Type": "MouseMove",
    "Time": 4459,
    "X": 327,
    "Y": 165,
    "Delta": null,
    "KeyCode": null
  },
  {
    "Type": "MouseMove",
    "Time": 4461,
    "X": 327,
    "Y": 171,
    "Delta": null,
    "KeyCode": null
  },
  {
    "Type": "MouseMove",
    "Time": 4469,
    "X": 324,
    "Y": 174,
    "Delta": null,
    "KeyCode": null
  },
  {
    "Type": "MouseMove",
    "Time": 4493,
    "X": 318,
    "Y": 183,
    "Delta": null,
    "KeyCode": null
  },
  {
    "Type": "MouseMove",
    "Time": 4513,
    "X": 312,
    "Y": 198,
    "Delta": null,
    "KeyCode": null
  },
  {
    "Type": "MouseMove",
    "Time": 4533,
    "X": 306,
    "Y": 207,
    "Delta": null,
    "KeyCode": null
  },
  {
    "Type": "MouseMove",
    "Time": 4535,
    "X": 300,
    "Y": 213,
    "Delta": null,
    "KeyCode": null
  },
  {
    "Type": "MouseMove",
    "Time": 4558,
    "X": 291,
    "Y": 225,
    "Delta": null,
    "KeyCode": null
  },
  {
    "Type": "MouseMove",
    "Time": 4559,
    "X": 285,
    "Y": 231,
    "Delta": null,
    "KeyCode": null
  },
  {
    "Type": "MouseMove",
    "Time": 4567,
    "X": 276,
    "Y": 243,
    "Delta": null,
    "KeyCode": null
  },
  {
    "Type": "MouseMove",
    "Time": 4575,
    "X": 273,
    "Y": 249,
    "Delta": null,
    "KeyCode": null
  },
  {
    "Type": "MouseMove",
    "Time": 4583,
    "X": 264,
    "Y": 258,
    "Delta": null,
    "KeyCode": null
  },
  {
    "Type": "MouseMove",
    "Time": 4605,
    "X": 252,
    "Y": 270,
    "Delta": null,
    "KeyCode": null
  },
  {
    "Type": "MouseMove",
    "Time": 4607,
    "X": 246,
    "Y": 282,
    "Delta": null,
    "KeyCode": null
  },
  {
    "Type": "MouseMove",
    "Time": 4615,
    "X": 240,
    "Y": 288,
    "Delta": null,
    "KeyCode": null
  },
  {
    "Type": "MouseMove",
    "Time": 4636,
    "X": 228,
    "Y": 300,
    "Delta": null,
    "KeyCode": null
  },
  {
    "Type": "MouseMove",
    "Time": 4639,
    "X": 219,
    "Y": 306,
    "Delta": null,
    "KeyCode": null
  },
  {
    "Type": "MouseMove",
    "Time": 4666,
    "X": 189,
    "Y": 336,
    "Delta": null,
    "KeyCode": null
  },
  {
    "Type": "MouseMove",
    "Time": 4671,
    "X": 180,
    "Y": 348,
    "Delta": null,
    "KeyCode": null
  },
  {
    "Type": "MouseMove",
    "Time": 4696,
    "X": 156,
    "Y": 372,
    "Delta": null,
    "KeyCode": null
  },
  {
    "Type": "MouseMove",
    "Time": 4703,
    "X": 150,
    "Y": 378,
    "Delta": null,
    "KeyCode": null
  },
  {
    "Type": "MouseMove",
    "Time": 4727,
    "X": 138,
    "Y": 390,
    "Delta": null,
    "KeyCode": null
  },
  {
    "Type": "MouseMove",
    "Time": 4728,
    "X": 135,
    "Y": 396,
    "Delta": null,
    "KeyCode": null
  },
  {
    "Type": "MouseMove",
    "Time": 4735,
    "X": 132,
    "Y": 399,
    "Delta": null,
    "KeyCode": null
  },
  {
    "Type": "MouseMove",
    "Time": 4758,
    "X": 126,
    "Y": 405,
    "Delta": null,
    "KeyCode": null
  },
  {
    "Type": "MouseMove",
    "Time": 4778,
    "X": 120,
    "Y": 411,
    "Delta": null,
    "KeyCode": null
  },
  {
    "Type": "MouseMove",
    "Time": 4783,
    "X": 117,
    "Y": 414,
    "Delta": null,
    "KeyCode": null
  },
  {
    "Type": "MouseMove",
    "Time": 4805,
    "X": 114,
    "Y": 417,
    "Delta": null,
    "KeyCode": null
  },
  {
    "Type": "MouseMove",
    "Time": 4825,
    "X": 111,
    "Y": 426,
    "Delta": null,
    "KeyCode": null
  },
  {
    "Type": "MouseMove",
    "Time": 4847,
    "X": 111,
    "Y": 429,
    "Delta": null,
    "KeyCode": null
  },
  {
    "Type": "MouseMove",
    "Time": 4870,
    "X": 105,
    "Y": 432,
    "Delta": null,
    "KeyCode": null
  },
  {
    "Type": "MouseMove",
    "Time": 4891,
    "X": 105,
    "Y": 435,
    "Delta": null,
    "KeyCode": null
  },
  {
    "Type": "MouseMove",
    "Time": 4897,
    "X": 102,
    "Y": 435,
    "Delta": null,
    "KeyCode": null
  },
  {
    "Type": "MouseMove",
    "Time": 5220,
    "X": 105,
    "Y": 432,
    "Delta": null,
    "KeyCode": null
  },
  {
    "Type": "MouseMove",
    "Time": 5241,
    "X": 105,
    "Y": 429,
    "Delta": null,
    "KeyCode": null
  },
  {
    "Type": "MouseMove",
    "Time": 5263,
    "X": 105,
    "Y": 426,
    "Delta": null,
    "KeyCode": null
  },
  {
    "Type": "MouseMove",
    "Time": 5301,
    "X": 108,
    "Y": 423,
    "Delta": null,
    "KeyCode": null
  },
  {
    "Type": "MouseMove",
    "Time": 5307,
    "X": 108,
    "Y": 420,
    "Delta": null,
    "KeyCode": null
  },
  {
    "Type": "MouseMove",
    "Time": 5330,
    "X": 108,
    "Y": 417,
    "Delta": null,
    "KeyCode": null
  },
  {
    "Type": "MouseMove",
    "Time": 5331,
    "X": 111,
    "Y": 417,
    "Delta": null,
    "KeyCode": null
  },
  {
    "Type": "MouseMove",
    "Time": 5339,
    "X": 111,
    "Y": 414,
    "Delta": null,
    "KeyCode": null
  },
  {
    "Type": "MouseMove",
    "Time": 5580,
    "X": 108,
    "Y": 417,
    "Delta": null,
    "KeyCode": null
  },
  {
    "Type": "MouseMove",
    "Time": 5603,
    "X": 105,
    "Y": 423,
    "Delta": null,
    "KeyCode": null
  },
  {
    "Type": "MouseMove",
    "Time": 5613,
    "X": 105,
    "Y": 426,
    "Delta": null,
    "KeyCode": null
  },
  {
    "Type": "MouseMove",
    "Time": 5657,
    "X": 102,
    "Y": 426,
    "Delta": null,
    "KeyCode": null
  },
  {
    "Type": "MouseMove",
    "Time": 6185,
    "X": 99,
    "Y": 426,
    "Delta": null,
    "KeyCode": null
  },
  {
    "Type": "DragStart",
    "Time": 6698,
    "X": 99,
    "Y": 426,
    "Delta": null,
    "KeyCode": null
  },
  {
    "Type": "DragEnd",
    "Time": 6778,
    "X": 99,
    "Y": 426,
    "Delta": null,
    "KeyCode": null
  },
  {
    "Type": "MouseMove",
    "Time": 12023,
    "X": 99,
    "Y": 423,
    "Delta": null,
    "KeyCode": null
  },
  {
    "Type": "MouseMove",
    "Time": 12070,
    "X": 102,
    "Y": 420,
    "Delta": null,
    "KeyCode": null
  },
  {
    "Type": "MouseMove",
    "Time": 12071,
    "X": 102,
    "Y": 417,
    "Delta": null,
    "KeyCode": null
  },
  {
    "Type": "MouseMove",
    "Time": 12079,
    "X": 102,
    "Y": 414,
    "Delta": null,
    "KeyCode": null
  },
  {
    "Type": "MouseMove",
    "Time": 12087,
    "X": 105,
    "Y": 414,
    "Delta": null,
    "KeyCode": null
  },
  {
    "Type": "MouseMove",
    "Time": 12111,
    "X": 111,
    "Y": 408,
    "Delta": null,
    "KeyCode": null
  },
  {
    "Type": "MouseMove",
    "Time": 12131,
    "X": 117,
    "Y": 405,
    "Delta": null,
    "KeyCode": null
  },
  {
    "Type": "MouseMove",
    "Time": 12135,
    "X": 120,
    "Y": 402,
    "Delta": null,
    "KeyCode": null
  },
  {
    "Type": "MouseMove",
    "Time": 12143,
    "X": 120,
    "Y": 399,
    "Delta": null,
    "KeyCode": null
  },
  {
    "Type": "MouseMove",
    "Time": 12151,
    "X": 123,
    "Y": 396,
    "Delta": null,
    "KeyCode": null
  },
  {
    "Type": "MouseMove",
    "Time": 12175,
    "X": 141,
    "Y": 387,
    "Delta": null,
    "KeyCode": null
  },
  {
    "Type": "MouseMove",
    "Time": 12183,
    "X": 144,
    "Y": 384,
    "Delta": null,
    "KeyCode": null
  },
  {
    "Type": "MouseMove",
    "Time": 12207,
    "X": 171,
    "Y": 372,
    "Delta": null,
    "KeyCode": null
  },
  {
    "Type": "MouseMove",
    "Time": 12230,
    "X": 186,
    "Y": 366,
    "Delta": null,
    "KeyCode": null
  },
  {
    "Type": "MouseMove",
    "Time": 12254,
    "X": 198,
    "Y": 363,
    "Delta": null,
    "KeyCode": null
  },
  {
    "Type": "MouseMove",
    "Time": 12275,
    "X": 201,
    "Y": 363,
    "Delta": null,
    "KeyCode": null
  },
  {
    "Type": "MouseMove",
    "Time": 12275,
    "X": 201,
    "Y": 360,
    "Delta": null,
    "KeyCode": null
  },
  {
    "Type": "RightDown",
    "Time": 12277,
    "X": 201,
    "Y": 360,
    "Delta": null,
    "KeyCode": null
  },
  {
    "Type": "MouseMove",
    "Time": 12296,
    "X": 204,
    "Y": 360,
    "Delta": null,
    "KeyCode": null
  },
  {
    "Type": "MouseMove",
    "Time": 12319,
    "X": 207,
    "Y": 357,
    "Delta": null,
    "KeyCode": null
  },
  {
    "Type": "MouseMove",
    "Time": 12321,
    "X": 210,
    "Y": 357,
    "Delta": null,
    "KeyCode": null
  },
  {
    "Type": "MouseMove",
    "Time": 12350,
    "X": 216,
    "Y": 354,
    "Delta": null,
    "KeyCode": null
  },
  {
    "Type": "MouseMove",
    "Time": 12382,
    "X": 222,
    "Y": 351,
    "Delta": null,
    "KeyCode": null
  },
  {
    "Type": "MouseMove",
    "Time": 12404,
    "X": 228,
    "Y": 348,
    "Delta": null,
    "KeyCode": null
  },
  {
    "Type": "MouseMove",
    "Time": 12405,
    "X": 240,
    "Y": 342,
    "Delta": null,
    "KeyCode": null
  },
  {
    "Type": "RightUp",
    "Time": 12407,
    "X": 240,
    "Y": 342,
    "Delta": null,
    "KeyCode": null
  },
  {
    "Type": "MouseMove",
    "Time": 12430,
    "X": 255,
    "Y": 333,
    "Delta": null,
    "KeyCode": null
  },
  {
    "Type": "MouseMove",
    "Time": 12433,
    "X": 258,
    "Y": 330,
    "Delta": null,
    "KeyCode": null
  },
  {
    "Type": "MouseMove",
    "Time": 12460,
    "X": 273,
    "Y": 324,
    "Delta": null,
    "KeyCode": null
  },
  {
    "Type": "MouseMove",
    "Time": 12480,
    "X": 279,
    "Y": 321,
    "Delta": null,
    "KeyCode": null
  },
  {
    "Type": "MouseMove",
    "Time": 12504,
    "X": 291,
    "Y": 318,
    "Delta": null,
    "KeyCode": null
  },
  {
    "Type": "MouseMove",
    "Time": 12525,
    "X": 306,
    "Y": 309,
    "Delta": null,
    "KeyCode": null
  },
  {
    "Type": "MouseMove",
    "Time": 12544,
    "X": 318,
    "Y": 303,
    "Delta": null,
    "KeyCode": null
  },
  {
    "Type": "MouseMove",
    "Time": 12547,
    "X": 324,
    "Y": 300,
    "Delta": null,
    "KeyCode": null
  },
  {
    "Type": "MouseMove",
    "Time": 12555,
    "X": 330,
    "Y": 297,
    "Delta": null,
    "KeyCode": null
  },
  {
    "Type": "MouseMove",
    "Time": 12564,
    "X": 336,
    "Y": 294,
    "Delta": null,
    "KeyCode": null
  },
  {
    "Type": "MouseMove",
    "Time": 12589,
    "X": 345,
    "Y": 288,
    "Delta": null,
    "KeyCode": null
  },
  {
    "Type": "MouseMove",
    "Time": 12612,
    "X": 360,
    "Y": 276,
    "Delta": null,
    "KeyCode": null
  },
  {
    "Type": "MouseMove",
    "Time": 12638,
    "X": 378,
    "Y": 264,
    "Delta": null,
    "KeyCode": null
  },
  {
    "Type": "MouseMove",
    "Time": 12658,
    "X": 390,
    "Y": 255,
    "Delta": null,
    "KeyCode": null
  },
  {
    "Type": "MouseMove",
    "Time": 12679,
    "X": 402,
    "Y": 246,
    "Delta": null,
    "KeyCode": null
  },
  {
    "Type": "MouseMove",
    "Time": 12701,
    "X": 408,
    "Y": 240,
    "Delta": null,
    "KeyCode": null
  },
  {
    "Type": "MouseMove",
    "Time": 12741,
    "X": 408,
    "Y": 237,
    "Delta": null,
    "KeyCode": null
  },
  {
    "Type": "MouseMove",
    "Time": 12755,
    "X": 411,
    "Y": 237,
    "Delta": null,
    "KeyCode": null
  },
  {
    "Type": "MouseMove",
    "Time": 12781,
    "X": 414,
    "Y": 234,
    "Delta": null,
    "KeyCode": null
  },
  {
    "Type": "MouseMove",
    "Time": 12804,
    "X": 417,
    "Y": 228,
    "Delta": null,
    "KeyCode": null
  },
  {
    "Type": "MouseMove",
    "Time": 12826,
    "X": 420,
    "Y": 225,
    "Delta": null,
    "KeyCode": null
  },
  {
    "Type": "MouseMove",
    "Time": 12870,
    "X": 420,
    "Y": 222,
    "Delta": null,
    "KeyCode": null
  },
  {
    "Type": "MouseMove",
    "Time": 12877,
    "X": 420,
    "Y": 219,
    "Delta": null,
    "KeyCode": null
  },
  {
    "Type": "MouseMove",
    "Time": 12885,
    "X": 423,
    "Y": 219,
    "Delta": null,
    "KeyCode": null
  },
  {
    "Type": "MouseMove",
    "Time": 12911,
    "X": 426,
    "Y": 213,
    "Delta": null,
    "KeyCode": null
  },
  {
    "Type": "MouseMove",
    "Time": 12917,
    "X": 429,
    "Y": 210,
    "Delta": null,
    "KeyCode": null
  },
  {
    "Type": "MouseMove",
    "Time": 12938,
    "X": 432,
    "Y": 207,
    "Delta": null,
    "KeyCode": null
  },
  {
    "Type": "MouseMove",
    "Time": 13032,
    "X": 435,
    "Y": 201,
    "Delta": null,
    "KeyCode": null
  },
  {
    "Type": "MouseMove",
    "Time": 13053,
    "X": 438,
    "Y": 198,
    "Delta": null,
    "KeyCode": null
  },
  {
    "Type": "MouseMove",
    "Time": 13809,
    "X": 435,
    "Y": 198,
    "Delta": null,
    "KeyCode": null
  },
  {
    "Type": "MouseMove",
    "Time": 13925,
    "X": 432,
    "Y": 198,
    "Delta": null,
    "KeyCode": null
  },
  {
    "Type": "MouseMove",
    "Time": 14037,
    "X": 432,
    "Y": 201,
    "Delta": null,
    "KeyCode": null
  },
  {
    "Type": "DragStart",
    "Time": 14151,
    "X": 432,
    "Y": 201,
    "Delta": null,
    "KeyCode": null
  },
  {
    "Type": "DragEnd",
    "Time": 14222,
    "X": 432,
    "Y": 201,
    "Delta": null,
    "KeyCode": null
  },
  {
    "Type": "MouseMove",
    "Time": 14350,
    "X": 426,
    "Y": 210,
    "Delta": null,
    "KeyCode": null
  },
  {
    "Type": "MouseMove",
    "Time": 14351,
    "X": 426,
    "Y": 213,
    "Delta": null,
    "KeyCode": null
  },
  {
    "Type": "MouseMove",
    "Time": 14379,
    "X": 420,
    "Y": 225,
    "Delta": null,
    "KeyCode": null
  },
  {
    "Type": "MouseMove",
    "Time": 14383,
    "X": 420,
    "Y": 228,
    "Delta": null,
    "KeyCode": null
  },
  {
    "Type": "MouseMove",
    "Time": 14412,
    "X": 414,
    "Y": 237,
    "Delta": null,
    "KeyCode": null
  },
  {
    "Type": "MouseMove",
    "Time": 14415,
    "X": 414,
    "Y": 240,
    "Delta": null,
    "KeyCode": null
  },
  {
    "Type": "MouseMove",
    "Time": 14439,
    "X": 411,
    "Y": 243,
    "Delta": null,
    "KeyCode": null
  },
  {
    "Type": "MouseMove",
    "Time": 14447,
    "X": 411,
    "Y": 246,
    "Delta": null,
    "KeyCode": null
  },
  {
    "Type": "MouseMove",
    "Time": 14471,
    "X": 408,
    "Y": 249,
    "Delta": null,
    "KeyCode": null
  },
  {
    "Type": "MouseMove",
    "Time": 14506,
    "X": 405,
    "Y": 252,
    "Delta": null,
    "KeyCode": null
  },
  {
    "Type": "MouseMove",
    "Time": 14535,
    "X": 402,
    "Y": 255,
    "Delta": null,
    "KeyCode": null
  },
  {
    "Type": "MouseMove",
    "Time": 14612,
    "X": 402,
    "Y": 258,
    "Delta": null,
    "KeyCode": null
  },
  {
    "Type": "MouseMove",
    "Time": 30979,
    "X": 408,
    "Y": 258,
    "Delta": null,
    "KeyCode": null
  },
  {
    "Type": "MouseMove",
    "Time": 30998,
    "X": 417,
    "Y": 258,
    "Delta": null,
    "KeyCode": null
  },
  {
    "Type": "MouseMove",
    "Time": 31022,
    "X": 429,
    "Y": 255,
    "Delta": null,
    "KeyCode": null
  },
  {
    "Type": "MouseMove",
    "Time": 31045,
    "X": 444,
    "Y": 252,
    "Delta": null,
    "KeyCode": null
  },
  {
    "Type": "MouseMove",
    "Time": 31073,
    "X": 456,
    "Y": 252,
    "Delta": null,
    "KeyCode": null
  },
  {
    "Type": "MouseMove",
    "Time": 31077,
    "X": 459,
    "Y": 252,
    "Delta": null,
    "KeyCode": null
  },
  {
    "Type": "MouseMove",
    "Time": 31105,
    "X": 468,
    "Y": 252,
    "Delta": null,
    "KeyCode": null
  },
  {
    "Type": "MouseMove",
    "Time": 31128,
    "X": 480,
    "Y": 252,
    "Delta": null,
    "KeyCode": null
  },
  {
    "Type": "MouseMove",
    "Time": 31149,
    "X": 498,
    "Y": 252,
    "Delta": null,
    "KeyCode": null
  },
  {
    "Type": "MouseMove",
    "Time": 31160,
    "X": 507,
    "Y": 252,
    "Delta": null,
    "KeyCode": null
  },
  {
    "Type": "MouseMove",
    "Time": 31171,
    "X": 519,
    "Y": 249,
    "Delta": null,
    "KeyCode": null
  },
  {
    "Type": "MouseMove",
    "Time": 31173,
    "X": 528,
    "Y": 249,
    "Delta": null,
    "KeyCode": null
  },
  {
    "Type": "MouseMove",
    "Time": 31181,
    "X": 531,
    "Y": 249,
    "Delta": null,
    "KeyCode": null
  },
  {
    "Type": "MouseMove",
    "Time": 31189,
    "X": 540,
    "Y": 249,
    "Delta": null,
    "KeyCode": null
  },
  {
    "Type": "MouseMove",
    "Time": 31197,
    "X": 552,
    "Y": 246,
    "Delta": null,
    "KeyCode": null
  },
  {
    "Type": "MouseMove",
    "Time": 31205,
    "X": 561,
    "Y": 246,
    "Delta": null,
    "KeyCode": null
  },
  {
    "Type": "MouseMove",
    "Time": 31230,
    "X": 591,
    "Y": 243,
    "Delta": null,
    "KeyCode": null
  },
  {
    "Type": "MouseMove",
    "Time": 31250,
    "X": 621,
    "Y": 240,
    "Delta": null,
    "KeyCode": null
  },
  {
    "Type": "MouseMove",
    "Time": 31253,
    "X": 630,
    "Y": 237,
    "Delta": null,
    "KeyCode": null
  },
  {
    "Type": "MouseMove",
    "Time": 31276,
    "X": 657,
    "Y": 237,
    "Delta": null,
    "KeyCode": null
  },
  {
    "Type": "MouseMove",
    "Time": 31299,
    "X": 684,
    "Y": 234,
    "Delta": null,
    "KeyCode": null
  },
  {
    "Type": "MouseMove",
    "Time": 31322,
    "X": 711,
    "Y": 228,
    "Delta": null,
    "KeyCode": null
  },
  {
    "Type": "MouseMove",
    "Time": 31345,
    "X": 732,
    "Y": 228,
    "Delta": null,
    "KeyCode": null
  },
  {
    "Type": "MouseMove",
    "Time": 31349,
    "X": 738,
    "Y": 225,
    "Delta": null,
    "KeyCode": null
  },
  {
    "Type": "MouseMove",
    "Time": 31359,
    "X": 744,
    "Y": 225,
    "Delta": null,
    "KeyCode": null
  },
  {
    "Type": "MouseMove",
    "Time": 31389,
    "X": 753,
    "Y": 222,
    "Delta": null,
    "KeyCode": null
  },
  {
    "Type": "MouseMove",
    "Time": 31410,
    "X": 756,
    "Y": 222,
    "Delta": null,
    "KeyCode": null
  },
  {
    "Type": "MouseMove",
    "Time": 31545,
    "X": 765,
    "Y": 216,
    "Delta": null,
    "KeyCode": null
  },
  {
    "Type": "MouseMove",
    "Time": 31551,
    "X": 768,
    "Y": 213,
    "Delta": null,
    "KeyCode": null
  },
  {
    "Type": "MouseMove",
    "Time": 31559,
    "X": 774,
    "Y": 210,
    "Delta": null,
    "KeyCode": null
  },
  {
    "Type": "MouseMove",
    "Time": 31582,
    "X": 780,
    "Y": 207,
    "Delta": null,
    "KeyCode": null
  },
  {
    "Type": "MouseMove",
    "Time": 31591,
    "X": 783,
    "Y": 204,
    "Delta": null,
    "KeyCode": null
  },
  {
    "Type": "MouseMove",
    "Time": 31615,
    "X": 786,
    "Y": 204,
    "Delta": null,
    "KeyCode": null
  },
  {
    "Type": "MouseMove",
    "Time": 31646,
    "X": 786,
    "Y": 201,
    "Delta": null,
    "KeyCode": null
  },
  {
    "Type": "MouseMove",
    "Time": 31666,
    "X": 792,
    "Y": 198,
    "Delta": null,
    "KeyCode": null
  },
  {
    "Type": "MouseMove",
    "Time": 31694,
    "X": 798,
    "Y": 195,
    "Delta": null,
    "KeyCode": null
  },
  {
    "Type": "MouseMove",
    "Time": 31723,
    "X": 798,
    "Y": 192,
    "Delta": null,
    "KeyCode": null
  },
  {
    "Type": "MouseMove",
    "Time": 31745,
    "X": 801,
    "Y": 192,
    "Delta": null,
    "KeyCode": null
  },
  {
    "Type": "MouseMove",
    "Time": 31761,
    "X": 804,
    "Y": 189,
    "Delta": null,
    "KeyCode": null
  },
  {
    "Type": "MouseMove",
    "Time": 31808,
    "X": 807,
    "Y": 186,
    "Delta": null,
    "KeyCode": null
  },
  {
    "Type": "MouseMove",
    "Time": 31863,
    "X": 813,
    "Y": 180,
    "Delta": null,
    "KeyCode": null
  },
  {
    "Type": "MouseMove",
    "Time": 31865,
    "X": 816,
    "Y": 180,
    "Delta": null,
    "KeyCode": null
  },
  {
    "Type": "MouseMove",
    "Time": 31895,
    "X": 819,
    "Y": 177,
    "Delta": null,
    "KeyCode": null
  },
  {
    "Type": "MouseMove",
    "Time": 32921,
    "X": 822,
    "Y": 177,
    "Delta": null,
    "KeyCode": null
  },
  {
    "Type": "MouseMove",
    "Time": 32945,
    "X": 822,
    "Y": 174,
    "Delta": null,
    "KeyCode": null
  },
  {
    "Type": "MouseMove",
    "Time": 32953,
    "X": 822,
    "Y": 171,
    "Delta": null,
    "KeyCode": null
  },
  {
    "Type": "MouseMove",
    "Time": 32978,
    "X": 825,
    "Y": 168,
    "Delta": null,
    "KeyCode": null
  },
  {
    "Type": "MouseMove",
    "Time": 33428,
    "X": 822,
    "Y": 165,
    "Delta": null,
    "KeyCode": null
  },
  {
    "Type": "MouseMove",
    "Time": 33709,
    "X": 819,
    "Y": 165,
    "Delta": null,
    "KeyCode": null
  },
  {
    "Type": "MouseMove",
    "Time": 34621,
    "X": 822,
    "Y": 165,
    "Delta": null,
    "KeyCode": null
  },
  {
    "Type": "MouseMove",
    "Time": 34654,
    "X": 822,
    "Y": 168,
    "Delta": null,
    "KeyCode": null
  },
  {
    "Type": "MouseMove",
    "Time": 35055,
    "X": 822,
    "Y": 171,
    "Delta": null,
    "KeyCode": null
  },
  {
    "Type": "MouseMove",
    "Time": 35105,
    "X": 819,
    "Y": 171,
    "Delta": null,
    "KeyCode": null
  },
  {
    "Type": "MouseMove",
    "Time": 37793,
    "X": 822,
    "Y": 171,
    "Delta": null,
    "KeyCode": null
  },
  {
    "Type": "DragStart",
    "Time": 39423,
    "X": 822,
    "Y": 171,
    "Delta": null,
    "KeyCode": null
  },
  {
    "Type": "DragEnd",
    "Time": 39519,
    "X": 822,
    "Y": 171,
    "Delta": null,
    "KeyCode": null
  },
  {
    "Type": "MouseMove",
    "Time": 42274,
    "X": 825,
    "Y": 180,
    "Delta": null,
    "KeyCode": null
  },
  {
    "Type": "MouseMove",
    "Time": 42294,
    "X": 828,
    "Y": 183,
    "Delta": null,
    "KeyCode": null
  },
  {
    "Type": "MouseMove",
    "Time": 42297,
    "X": 831,
    "Y": 186,
    "Delta": null,
    "KeyCode": null
  },
  {
    "Type": "MouseMove",
    "Time": 42305,
    "X": 831,
    "Y": 189,
    "Delta": null,
    "KeyCode": null
  },
  {
    "Type": "MouseMove",
    "Time": 42313,
    "X": 834,
    "Y": 189,
    "Delta": null,
    "KeyCode": null
  },
  {
    "Type": "MouseMove",
    "Time": 42321,
    "X": 834,
    "Y": 192,
    "Delta": null,
    "KeyCode": null
  },
  {
    "Type": "MouseMove",
    "Time": 42353,
    "X": 837,
    "Y": 195,
    "Delta": null,
    "KeyCode": null
  },
  {
    "Type": "MouseMove",
    "Time": 42373,
    "X": 840,
    "Y": 198,
    "Delta": null,
    "KeyCode": null
  },
  {
    "Type": "MouseMove",
    "Time": 42387,
    "X": 843,
    "Y": 201,
    "Delta": null,
    "KeyCode": null
  },
  {
    "Type": "MouseMove",
    "Time": 42393,
    "X": 846,
    "Y": 201,
    "Delta": null,
    "KeyCode": null
  },
  {
    "Type": "MouseMove",
    "Time": 42403,
    "X": 846,
    "Y": 204,
    "Delta": null,
    "KeyCode": null
  },
  {
    "Type": "MouseMove",
    "Time": 42411,
    "X": 849,
    "Y": 207,
    "Delta": null,
    "KeyCode": null
  },
  {
    "Type": "MouseMove",
    "Time": 42433,
    "X": 852,
    "Y": 210,
    "Delta": null,
    "KeyCode": null
  },
  {
    "Type": "MouseMove",
    "Time": 42456,
    "X": 858,
    "Y": 213,
    "Delta": null,
    "KeyCode": null
  },
  {
    "Type": "MouseMove",
    "Time": 42496,
    "X": 858,
    "Y": 216,
    "Delta": null,
    "KeyCode": null
  },
  {
    "Type": "MouseMove",
    "Time": 42518,
    "X": 864,
    "Y": 219,
    "Delta": null,
    "KeyCode": null
  },
  {
    "Type": "MouseMove",
    "Time": 42544,
    "X": 870,
    "Y": 228,
    "Delta": null,
    "KeyCode": null
  },
  {
    "Type": "MouseMove",
    "Time": 42566,
    "X": 876,
    "Y": 231,
    "Delta": null,
    "KeyCode": null
  },
  {
    "Type": "MouseMove",
    "Time": 42579,
    "X": 876,
    "Y": 234,
    "Delta": null,
    "KeyCode": null
  },
  {
    "Type": "MouseMove",
    "Time": 42587,
    "X": 879,
    "Y": 234,
    "Delta": null,
    "KeyCode": null
  },
  {
    "Type": "MouseMove",
    "Time": 42603,
    "X": 879,
    "Y": 237,
    "Delta": null,
    "KeyCode": null
  },
  {
    "Type": "MouseMove",
    "Time": 42624,
    "X": 882,
    "Y": 240,
    "Delta": null,
    "KeyCode": null
  },
  {
    "Type": "MouseMove",
    "Time": 42644,
    "X": 885,
    "Y": 243,
    "Delta": null,
    "KeyCode": null
  },
  {
    "Type": "MouseMove",
    "Time": 42672,
    "X": 888,
    "Y": 246,
    "Delta": null,
    "KeyCode": null
  },
  {
    "Type": "MouseMove",
    "Time": 42719,
    "X": 891,
    "Y": 249,
    "Delta": null,
    "KeyCode": null
  },
  {
    "Type": "MouseMove",
    "Time": 42725,
    "X": 891,
    "Y": 252,
    "Delta": null,
    "KeyCode": null
  },
  {
    "Type": "MouseMove",
    "Time": 42750,
    "X": 894,
    "Y": 252,
    "Delta": null,
    "KeyCode": null
  },
  {
    "Type": "MouseMove",
    "Time": 42757,
    "X": 894,
    "Y": 255,
    "Delta": null,
    "KeyCode": null
  },
  {
    "Type": "MouseMove",
    "Time": 42784,
    "X": 894,
    "Y": 258,
    "Delta": null,
    "KeyCode": null
  },
  {
    "Type": "MouseMove",
    "Time": 42805,
    "X": 897,
    "Y": 258,
    "Delta": null,
    "KeyCode": null
  },
  {
    "Type": "MouseMove",
    "Time": 42880,
    "X": 900,
    "Y": 261,
    "Delta": null,
    "KeyCode": null
  },
  {
    "Type": "MouseMove",
    "Time": 42901,
    "X": 900,
    "Y": 264,
    "Delta": null,
    "KeyCode": null
  },
  {
    "Type": "MouseMove",
    "Time": 42909,
    "X": 903,
    "Y": 264,
    "Delta": null,
    "KeyCode": null
  },
  {
    "Type": "MouseMove",
    "Time": 42943,
    "X": 906,
    "Y": 270,
    "Delta": null,
    "KeyCode": null
  },
  {
    "Type": "MouseMove",
    "Time": 42974,
    "X": 906,
    "Y": 273,
    "Delta": null,
    "KeyCode": null
  },
  {
    "Type": "MouseMove",
    "Time": 42975,
    "X": 909,
    "Y": 273,
    "Delta": null,
    "KeyCode": null
  },
  {
    "Type": "MouseMove",
    "Time": 42983,
    "X": 909,
    "Y": 276,
    "Delta": null,
    "KeyCode": null
  },
  {
    "Type": "MouseMove",
    "Time": 43027,
    "X": 912,
    "Y": 279,
    "Delta": null,
    "KeyCode": null
  },
  {
    "Type": "MouseMove",
    "Time": 43047,
    "X": 912,
    "Y": 282,
    "Delta": null,
    "KeyCode": null
  },
  {
    "Type": "MouseMove",
    "Time": 43069,
    "X": 912,
    "Y": 285,
    "Delta": null,
    "KeyCode": null
  },
  {
    "Type": "MouseMove",
    "Time": 43089,
    "X": 915,
    "Y": 288,
    "Delta": null,
    "KeyCode": null
  },
  {
    "Type": "MouseMove",
    "Time": 43111,
    "X": 918,
    "Y": 288,
    "Delta": null,
    "KeyCode": null
  },
  {
    "Type": "MouseMove",
    "Time": 43135,
    "X": 918,
    "Y": 291,
    "Delta": null,
    "KeyCode": null
  },
  {
    "Type": "MouseMove",
    "Time": 43167,
    "X": 921,
    "Y": 294,
    "Delta": null,
    "KeyCode": null
  },
  {
    "Type": "MouseMove",
    "Time": 43193,
    "X": 921,
    "Y": 297,
    "Delta": null,
    "KeyCode": null
  },
  {
    "Type": "MouseMove",
    "Time": 43225,
    "X": 921,
    "Y": 300,
    "Delta": null,
    "KeyCode": null
  },
  {
    "Type": "MouseMove",
    "Time": 43247,
    "X": 924,
    "Y": 300,
    "Delta": null,
    "KeyCode": null
  },
  {
    "Type": "MouseMove",
    "Time": 43268,
    "X": 924,
    "Y": 303,
    "Delta": null,
    "KeyCode": null
  },
  {
    "Type": "MouseMove",
    "Time": 43289,
    "X": 924,
    "Y": 306,
    "Delta": null,
    "KeyCode": null
  },
  {
    "Type": "MouseMove",
    "Time": 43320,
    "X": 927,
    "Y": 309,
    "Delta": null,
    "KeyCode": null
  },
  {
    "Type": "MouseMove",
    "Time": 43349,
    "X": 927,
    "Y": 315,
    "Delta": null,
    "KeyCode": null
  },
  {
    "Type": "MouseMove",
    "Time": 43372,
    "X": 930,
    "Y": 318,
    "Delta": null,
    "KeyCode": null
  },
  {
    "Type": "MouseMove",
    "Time": 43412,
    "X": 930,
    "Y": 324,
    "Delta": null,
    "KeyCode": null
  },
  {
    "Type": "MouseMove",
    "Time": 43456,
    "X": 930,
    "Y": 327,
    "Delta": null,
    "KeyCode": null
  },
  {
    "Type": "MouseMove",
    "Time": 43476,
    "X": 933,
    "Y": 333,
    "Delta": null,
    "KeyCode": null
  },
  {
    "Type": "MouseMove",
    "Time": 43508,
    "X": 933,
    "Y": 336,
    "Delta": null,
    "KeyCode": null
  },
  {
    "Type": "MouseMove",
    "Time": 43538,
    "X": 933,
    "Y": 342,
    "Delta": null,
    "KeyCode": null
  },
  {
    "Type": "MouseMove",
    "Time": 43563,
    "X": 933,
    "Y": 345,
    "Delta": null,
    "KeyCode": null
  },
  {
    "Type": "MouseMove",
    "Time": 43587,
    "X": 936,
    "Y": 351,
    "Delta": null,
    "KeyCode": null
  },
  {
    "Type": "MouseMove",
    "Time": 43619,
    "X": 936,
    "Y": 354,
    "Delta": null,
    "KeyCode": null
  },
  {
    "Type": "MouseMove",
    "Time": 43651,
    "X": 936,
    "Y": 357,
    "Delta": null,
    "KeyCode": null
  },
  {
    "Type": "MouseMove",
    "Time": 43676,
    "X": 936,
    "Y": 360,
    "Delta": null,
    "KeyCode": null
  },
  {
    "Type": "MouseMove",
    "Time": 43747,
    "X": 936,
    "Y": 363,
    "Delta": null,
    "KeyCode": null
  },
  {
    "Type": "MouseMove",
    "Time": 43772,
    "X": 939,
    "Y": 363,
    "Delta": null,
    "KeyCode": null
  },
  {
    "Type": "MouseMove",
    "Time": 43797,
    "X": 939,
    "Y": 366,
    "Delta": null,
    "KeyCode": null
  },
  {
    "Type": "MouseMove",
    "Time": 43872,
    "X": 939,
    "Y": 369,
    "Delta": null,
    "KeyCode": null
  },
  {
    "Type": "MouseMove",
    "Time": 45123,
    "X": 939,
    "Y": 372,
    "Delta": null,
    "KeyCode": null
  },
  {
    "Type": "MouseMove",
    "Time": 45143,
    "X": 939,
    "Y": 378,
    "Delta": null,
    "KeyCode": null
  },
  {
    "Type": "MouseMove",
    "Time": 45157,
    "X": 936,
    "Y": 381,
    "Delta": null,
    "KeyCode": null
  },
  {
    "Type": "MouseMove",
    "Time": 45173,
    "X": 936,
    "Y": 384,
    "Delta": null,
    "KeyCode": null
  },
  {
    "Type": "MouseMove",
    "Time": 45205,
    "X": 936,
    "Y": 387,
    "Delta": null,
    "KeyCode": null
  },
  {
    "Type": "MouseMove",
    "Time": 46017,
    "X": 933,
    "Y": 387,
    "Delta": null,
    "KeyCode": null
  },
  {
    "Type": "MouseMove",
    "Time": 46059,
    "X": 930,
    "Y": 387,
    "Delta": null,
    "KeyCode": null
  },
  {
    "Type": "MouseMove",
    "Time": 46383,
    "X": 933,
    "Y": 387,
    "Delta": null,
    "KeyCode": null
  },
  {
    "Type": "MouseMove",
    "Time": 46442,
    "X": 933,
    "Y": 390,
    "Delta": null,
    "KeyCode": null
  },
  {
    "Type": "MouseMove",
    "Time": 46536,
    "X": 936,
    "Y": 390,
    "Delta": null,
    "KeyCode": null
  },
  {
    "Type": "DragStart",
    "Time": 47101,
    "X": 936,
    "Y": 390,
    "Delta": null,
    "KeyCode": null
  },
  {
    "Type": "DragEnd",
    "Time": 47194,
    "X": 936,
    "Y": 390,
    "Delta": null,
    "KeyCode": null
  },
  {
    "Type": "MouseMove",
    "Time": 47816,
    "X": 933,
    "Y": 390,
    "Delta": null,
    "KeyCode": null
  },
  {
    "Type": "MouseMove",
    "Time": 47835,
    "X": 933,
    "Y": 393,
    "Delta": null,
    "KeyCode": null
  },
  {
    "Type": "MouseMove",
    "Time": 47869,
    "X": 930,
    "Y": 396,
    "Delta": null,
    "KeyCode": null
  },
  {
    "Type": "MouseMove",
    "Time": 47944,
    "X": 924,
    "Y": 399,
    "Delta": null,
    "KeyCode": null
  },
  {
    "Type": "MouseMove",
    "Time": 47965,
    "X": 924,
    "Y": 402,
    "Delta": null,
    "KeyCode": null
  },
  {
    "Type": "MouseMove",
    "Time": 47969,
    "X": 921,
    "Y": 402,
    "Delta": null,
    "KeyCode": null
  },
  {
    "Type": "MouseMove",
    "Time": 47993,
    "X": 921,
    "Y": 405,
    "Delta": null,
    "KeyCode": null
  },
  {
    "Type": "MouseMove",
    "Time": 48024,
    "X": 918,
    "Y": 408,
    "Delta": null,
    "KeyCode": null
  },
  {
    "Type": "MouseMove",
    "Time": 48045,
    "X": 906,
    "Y": 411,
    "Delta": null,
    "KeyCode": null
  },
  {
    "Type": "MouseMove",
    "Time": 48066,
    "X": 894,
    "Y": 414,
    "Delta": null,
    "KeyCode": null
  },
  {
    "Type": "MouseMove",
    "Time": 48089,
    "X": 885,
    "Y": 420,
    "Delta": null,
    "KeyCode": null
  },
  {
    "Type": "MouseMove",
    "Time": 48097,
    "X": 882,
    "Y": 420,
    "Delta": null,
    "KeyCode": null
  },
  {
    "Type": "MouseMove",
    "Time": 48105,
    "X": 876,
    "Y": 423,
    "Delta": null,
    "KeyCode": null
  },
  {
    "Type": "MouseMove",
    "Time": 48113,
    "X": 873,
    "Y": 423,
    "Delta": null,
    "KeyCode": null
  },
  {
    "Type": "MouseMove",
    "Time": 48121,
    "X": 870,
    "Y": 426,
    "Delta": null,
    "KeyCode": null
  },
  {
    "Type": "MouseMove",
    "Time": 48147,
    "X": 852,
    "Y": 432,
    "Delta": null,
    "KeyCode": null
  },
  {
    "Type": "MouseMove",
    "Time": 48153,
    "X": 846,
    "Y": 432,
    "Delta": null,
    "KeyCode": null
  },
  {
    "Type": "MouseMove",
    "Time": 48182,
    "X": 828,
    "Y": 438,
    "Delta": null,
    "KeyCode": null
  },
  {
    "Type": "MouseMove",
    "Time": 48203,
    "X": 813,
    "Y": 444,
    "Delta": null,
    "KeyCode": null
  },
  {
    "Type": "MouseMove",
    "Time": 48225,
    "X": 804,
    "Y": 447,
    "Delta": null,
    "KeyCode": null
  },
  {
    "Type": "MouseMove",
    "Time": 48227,
    "X": 798,
    "Y": 447,
    "Delta": null,
    "KeyCode": null
  },
  {
    "Type": "MouseMove",
    "Time": 48235,
    "X": 792,
    "Y": 450,
    "Delta": null,
    "KeyCode": null
  },
  {
    "Type": "MouseMove",
    "Time": 48257,
    "X": 777,
    "Y": 453,
    "Delta": null,
    "KeyCode": null
  },
  {
    "Type": "MouseMove",
    "Time": 48259,
    "X": 768,
    "Y": 459,
    "Delta": null,
    "KeyCode": null
  },
  {
    "Type": "MouseMove",
    "Time": 48267,
    "X": 762,
    "Y": 462,
    "Delta": null,
    "KeyCode": null
  },
  {
    "Type": "MouseMove",
    "Time": 48290,
    "X": 741,
    "Y": 468,
    "Delta": null,
    "KeyCode": null
  },
  {
    "Type": "MouseMove",
    "Time": 48291,
    "X": 732,
    "Y": 468,
    "Delta": null,
    "KeyCode": null
  },
  {
    "Type": "MouseMove",
    "Time": 48320,
    "X": 711,
    "Y": 477,
    "Delta": null,
    "KeyCode": null
  },
  {
    "Type": "MouseMove",
    "Time": 48341,
    "X": 690,
    "Y": 483,
    "Delta": null,
    "KeyCode": null
  },
  {
    "Type": "MouseMove",
    "Time": 48363,
    "X": 672,
    "Y": 486,
    "Delta": null,
    "KeyCode": null
  },
  {
    "Type": "MouseMove",
    "Time": 48383,
    "X": 660,
    "Y": 492,
    "Delta": null,
    "KeyCode": null
  },
  {
    "Type": "MouseMove",
    "Time": 48414,
    "X": 645,
    "Y": 498,
    "Delta": null,
    "KeyCode": null
  },
  {
    "Type": "MouseMove",
    "Time": 48419,
    "X": 642,
    "Y": 498,
    "Delta": null,
    "KeyCode": null
  },
  {
    "Type": "MouseMove",
    "Time": 48447,
    "X": 639,
    "Y": 501,
    "Delta": null,
    "KeyCode": null
  },
  {
    "Type": "MouseMove",
    "Time": 48478,
    "X": 633,
    "Y": 507,
    "Delta": null,
    "KeyCode": null
  },
  {
    "Type": "MouseMove",
    "Time": 48485,
    "X": 630,
    "Y": 507,
    "Delta": null,
    "KeyCode": null
  },
  {
    "Type": "MouseMove",
    "Time": 48508,
    "X": 624,
    "Y": 513,
    "Delta": null,
    "KeyCode": null
  },
  {
    "Type": "MouseMove",
    "Time": 48531,
    "X": 618,
    "Y": 519,
    "Delta": null,
    "KeyCode": null
  },
  {
    "Type": "MouseMove",
    "Time": 48533,
    "X": 615,
    "Y": 519,
    "Delta": null,
    "KeyCode": null
  },
  {
    "Type": "MouseMove",
    "Time": 48555,
    "X": 615,
    "Y": 522,
    "Delta": null,
    "KeyCode": null
  },
  {
    "Type": "MouseMove",
    "Time": 48577,
    "X": 606,
    "Y": 528,
    "Delta": null,
    "KeyCode": null
  },
  {
    "Type": "MouseMove",
    "Time": 48597,
    "X": 600,
    "Y": 537,
    "Delta": null,
    "KeyCode": null
  },
  {
    "Type": "MouseMove",
    "Time": 48605,
    "X": 597,
    "Y": 540,
    "Delta": null,
    "KeyCode": null
  },
  {
    "Type": "MouseMove",
    "Time": 48613,
    "X": 594,
    "Y": 540,
    "Delta": null,
    "KeyCode": null
  },
  {
    "Type": "MouseMove",
    "Time": 48634,
    "X": 591,
    "Y": 546,
    "Delta": null,
    "KeyCode": null
  },
  {
    "Type": "MouseMove",
    "Time": 48656,
    "X": 588,
    "Y": 549,
    "Delta": null,
    "KeyCode": null
  },
  {
    "Type": "MouseMove",
    "Time": 48697,
    "X": 588,
    "Y": 552,
    "Delta": null,
    "KeyCode": null
  },
  {
    "Type": "MouseMove",
    "Time": 48701,
    "X": 585,
    "Y": 552,
    "Delta": null,
    "KeyCode": null
  },
  {
    "Type": "MouseMove",
    "Time": 48709,
    "X": 585,
    "Y": 555,
    "Delta": null,
    "KeyCode": null
  },
  {
    "Type": "MouseMove",
    "Time": 48734,
    "X": 582,
    "Y": 558,
    "Delta": null,
    "KeyCode": null
  },
  {
    "Type": "MouseMove",
    "Time": 48756,
    "X": 579,
    "Y": 561,
    "Delta": null,
    "KeyCode": null
  },
  {
    "Type": "MouseMove",
    "Time": 48777,
    "X": 576,
    "Y": 567,
    "Delta": null,
    "KeyCode": null
  },
  {
    "Type": "MouseMove",
    "Time": 48798,
    "X": 573,
    "Y": 570,
    "Delta": null,
    "KeyCode": null
  },
  {
    "Type": "MouseMove",
    "Time": 48807,
    "X": 573,
    "Y": 573,
    "Delta": null,
    "KeyCode": null
  },
  {
    "Type": "MouseMove",
    "Time": 48815,
    "X": 570,
    "Y": 576,
    "Delta": null,
    "KeyCode": null
  },
  {
    "Type": "MouseMove",
    "Time": 48831,
    "X": 570,
    "Y": 579,
    "Delta": null,
    "KeyCode": null
  },
  {
    "Type": "MouseMove",
    "Time": 48857,
    "X": 564,
    "Y": 585,
    "Delta": null,
    "KeyCode": null
  },
  {
    "Type": "MouseMove",
    "Time": 48863,
    "X": 564,
    "Y": 588,
    "Delta": null,
    "KeyCode": null
  },
  {
    "Type": "MouseMove",
    "Time": 48887,
    "X": 564,
    "Y": 591,
    "Delta": null,
    "KeyCode": null
  },
  {
    "Type": "MouseMove",
    "Time": 48888,
    "X": 561,
    "Y": 591,
    "Delta": null,
    "KeyCode": null
  },
  {
    "Type": "MouseMove",
    "Time": 48895,
    "X": 561,
    "Y": 594,
    "Delta": null,
    "KeyCode": null
  },
  {
    "Type": "MouseMove",
    "Time": 48917,
    "X": 558,
    "Y": 594,
    "Delta": null,
    "KeyCode": null
  },
  {
    "Type": "MouseMove",
    "Time": 48919,
    "X": 558,
    "Y": 597,
    "Delta": null,
    "KeyCode": null
  },
  {
    "Type": "MouseMove",
    "Time": 48948,
    "X": 555,
    "Y": 600,
    "Delta": null,
    "KeyCode": null
  },
  {
    "Type": "MouseMove",
    "Time": 48959,
    "X": 555,
    "Y": 603,
    "Delta": null,
    "KeyCode": null
  },
  {
    "Type": "MouseMove",
    "Time": 49002,
    "X": 552,
    "Y": 603,
    "Delta": null,
    "KeyCode": null
  },
  {
    "Type": "MouseMove",
    "Time": 49028,
    "X": 552,
    "Y": 606,
    "Delta": null,
    "KeyCode": null
  }
]