[
  {
    "Type": "KeyUp",
    "Time": 46,
    "X": null,
    "Y": null,
    "Delta": null,
    "KeyCode": 35
  },
  {
    "Type": "MouseMove",
    "Time": 203,
    "X": 1092,
    "Y": 174,
    "Delta": null,
    "KeyCode": null
  },
  {
    "Type": "MouseMove",
    "Time": 223,
    "X": 1092,
    "Y": 180,
    "Delta": null,
    "KeyCode": null
  },
  {
    "Type": "MouseMove",
    "Time": 230,
    "X": 1089,
    "Y": 183,
    "Delta": null,
    "KeyCode": null
  },
  {
    "Type": "MouseMove",
    "Time": 236,
    "X": 1089,
    "Y": 186,
    "Delta": null,
    "KeyCode": null
  },
  {
    "Type": "MouseMove",
    "Time": 257,
    "X": 1086,
    "Y": 192,
    "Delta": null,
    "KeyCode": null
  },
  {
    "Type": "MouseMove",
    "Time": 258,
    "X": 1086,
    "Y": 195,
    "Delta": null,
    "KeyCode": null
  },
  {
    "Type": "MouseMove",
    "Time": 277,
    "X": 1083,
    "Y": 204,
    "Delta": null,
    "KeyCode": null
  },
  {
    "Type": "MouseMove",
    "Time": 298,
    "X": 1074,
    "Y": 216,
    "Delta": null,
    "KeyCode": null
  },
  {
    "Type": "MouseMove",
    "Time": 321,
    "X": 1068,
    "Y": 231,
    "Delta": null,
    "KeyCode": null
  },
  {
    "Type": "MouseMove",
    "Time": 343,
    "X": 1053,
    "Y": 249,
    "Delta": null,
    "KeyCode": null
  },
  {
    "Type": "MouseMove",
    "Time": 362,
    "X": 1044,
    "Y": 264,
    "Delta": null,
    "KeyCode": null
  },
  {
    "Type": "MouseMove",
    "Time": 378,
    "X": 1038,
    "Y": 270,
    "Delta": null,
    "KeyCode": null
  },
  {
    "Type": "MouseMove",
    "Time": 399,
    "X": 1029,
    "Y": 282,
    "Delta": null,
    "KeyCode": null
  },
  {
    "Type": "MouseMove",
    "Time": 400,
    "X": 1026,
    "Y": 285,
    "Delta": null,
    "KeyCode": null
  },
  {
    "Type": "MouseMove",
    "Time": 422,
    "X": 1020,
    "Y": 291,
    "Delta": null,
    "KeyCode": null
  },
  {
    "Type": "MouseMove",
    "Time": 435,
    "X": 1017,
    "Y": 294,
    "Delta": null,
    "KeyCode": null
  },
  {
    "Type": "MouseMove",
    "Time": 445,
    "X": 1017,
    "Y": 297,
    "Delta": null,
    "KeyCode": null
  },
  {
    "Type": "MouseMove",
    "Time": 464,
    "X": 1014,
    "Y": 300,
    "Delta": null,
    "KeyCode": null
  },
  {
    "Type": "MouseMove",
    "Time": 483,
    "X": 1014,
    "Y": 303,
    "Delta": null,
    "KeyCode": null
  },
  {
    "Type": "MouseMove",
    "Time": 505,
    "X": 1011,
    "Y": 303,
    "Delta": null,
    "KeyCode": null
  },
  {
    "Type": "MouseMove",
    "Time": 510,
    "X": 1011,
    "Y": 306,
    "Delta": null,
    "KeyCode": null
  },
  {
    "Type": "MouseMove",
    "Time": 557,
    "X": 1008,
    "Y": 306,
    "Delta": null,
    "KeyCode": null
  },
  {
    "Type": "MouseMove",
    "Time": 577,
    "X": 1005,
    "Y": 309,
    "Delta": null,
    "KeyCode": null
  },
  {
    "Type": "MouseMove",
    "Time": 618,
    "X": 1002,
    "Y": 309,
    "Delta": null,
    "KeyCode": null
  },
  {
    "Type": "MouseMove",
    "Time": 636,
    "X": 1002,
    "Y": 312,
    "Delta": null,
    "KeyCode": null
  },
  {
    "Type": "MouseMove",
    "Time": 657,
    "X": 999,
    "Y": 312,
    "Delta": null,
    "KeyCode": null
  },
  {
    "Type": "MouseMove",
    "Time": 670,
    "X": 996,
    "Y": 312,
    "Delta": null,
    "KeyCode": null
  },
  {
    "Type": "MouseMove",
    "Time": 680,
    "X": 990,
    "Y": 312,
    "Delta": null,
    "KeyCode": null
  },
  {
    "Type": "MouseMove",
    "Time": 702,
    "X": 984,
    "Y": 312,
    "Delta": null,
    "KeyCode": null
  },
  {
    "Type": "MouseMove",
    "Time": 722,
    "X": 978,
    "Y": 312,
    "Delta": null,
    "KeyCode": null
  },
  {
    "Type": "MouseMove",
    "Time": 743,
    "X": 975,
    "Y": 312,
    "Delta": null,
    "KeyCode": null
  },
  {
    "Type": "MouseMove",
    "Time": 763,
    "X": 969,
    "Y": 312,
    "Delta": null,
    "KeyCode": null
  },
  {
    "Type": "MouseMove",
    "Time": 768,
    "X": 966,
    "Y": 312,
    "Delta": null,
    "KeyCode": null
  },
  {
    "Type": "MouseMove",
    "Time": 810,
    "X": 963,
    "Y": 312,
    "Delta": null,
    "KeyCode": null
  },
  {
    "Type": "MouseMove",
    "Time": 830,
    "X": 960,
    "Y": 309,
    "Delta": null,
    "KeyCode": null
  },
  {
    "Type": "MouseMove",
    "Time": 851,
    "X": 957,
    "Y": 309,
    "Delta": null,
    "KeyCode": null
  },
  {
    "Type": "MouseMove",
    "Time": 870,
    "X": 954,
    "Y": 309,
    "Delta": null,
    "KeyCode": null
  },
  {
    "Type": "MouseMove",
    "Time": 890,
    "X": 951,
    "Y": 306,
    "Delta": null,
    "KeyCode": null
  },
  {
    "Type": "MouseMove",
    "Time": 909,
    "X": 948,
    "Y": 306,
    "Delta": null,
    "KeyCode": null
  },
  {
    "Type": "MouseMove",
    "Time": 970,
    "X": 945,
    "Y": 303,
    "Delta": null,
    "KeyCode": null
  },
  {
    "Type": "MouseMove",
    "Time": 1047,
    "X": 942,
    "Y": 300,
    "Delta": null,
    "KeyCode": null
  },
  {
    "Type": "MouseMove",
    "Time": 1164,
    "X": 942,
    "Y": 297,
    "Delta": null,
    "KeyCode": null
  },
  {
    "Type": "MouseMove",
    "Time": 1254,
    "X": 942,
    "Y": 294,
    "Delta": null,
    "KeyCode": null
  },
  {
    "Type": "MouseMove",
    "Time": 1268,
    "X": 942,
    "Y": 291,
    "Delta": null,
    "KeyCode": null
  },
  {
    "Type": "MouseMove",
    "Time": 1327,
    "X": 942,
    "Y": 288,
    "Delta": null,
    "KeyCode": null
  },
  {
    "Type": "MouseMove",
    "Time": 1575,
    "X": 942,
    "Y": 285,
    "Delta": null,
    "KeyCode": null
  },
  {
    "Type": "MouseMove",
    "Time": 1924,
    "X": 939,
    "Y": 285,
    "Delta": null,
    "KeyCode": null
  },
  {
    "Type": "MouseMove",
    "Time": 2232,
    "X": 939,
    "Y": 282,
    "Delta": null,
    "KeyCode": null
  },
  {
    "Type": "DragStart",
    "Time": 2568,
    "X": 939,
    "Y": 282,
    "Delta": null,
    "KeyCode": null
  },
  {
    "Type": "DragEnd",
    "Time": 2648,
    "X": 939,
    "Y": 282,
    "Delta": null,
    "KeyCode": null
  },
  {
    "Type": "MouseMove",
    "Time": 3144,
    "X": 936,
    "Y": 282,
    "Delta": null,
    "KeyCode": null
  },
  {
    "Type": "MouseMove",
    "Time": 3156,
    "X": 933,
    "Y": 282,
    "Delta": null,
    "KeyCode": null
  },
  {
    "Type": "MouseMove",
    "Time": 3172,
    "X": 930,
    "Y": 282,
    "Delta": null,
    "KeyCode": null
  },
  {
    "Type": "MouseMove",
    "Time": 3392,
    "X": 924,
    "Y": 279,
    "Delta": null,
    "KeyCode": null
  },
  {
    "Type": "MouseMove",
    "Time": 3413,
    "X": 915,
    "Y": 276,
    "Delta": null,
    "KeyCode": null
  },
  {
    "Type": "MouseMove",
    "Time": 3427,
    "X": 909,
    "Y": 276,
    "Delta": null,
    "KeyCode": null
  },
  {
    "Type": "MouseMove",
    "Time": 3437,
    "X": 906,
    "Y": 276,
    "Delta": null,
    "KeyCode": null
  },
  {
    "Type": "MouseMove",
    "Time": 3458,
    "X": 900,
    "Y": 276,
    "Delta": null,
    "KeyCode": null
  },
  {
    "Type": "MouseMove",
    "Time": 3481,
    "X": 888,
    "Y": 276,
    "Delta": null,
    "KeyCode": null
  },
  {
    "Type": "MouseMove",
    "Time": 3496,
    "X": 879,
    "Y": 273,
    "Delta": null,
    "KeyCode": null
  },
  {
    "Type": "MouseMove",
    "Time": 3516,
    "X": 852,
    "Y": 273,
    "Delta": null,
    "KeyCode": null
  },
  {
    "Type": "MouseMove",
    "Time": 3536,
    "X": 834,
    "Y": 273,
    "Delta": null,
    "KeyCode": null
  },
  {
    "Type": "MouseMove",
    "Time": 3560,
    "X": 804,
    "Y": 270,
    "Delta": null,
    "KeyCode": null
  },
  {
    "Type": "MouseMove",
    "Time": 3581,
    "X": 777,
    "Y": 270,
    "Delta": null,
    "KeyCode": null
  },
  {
    "Type": "MouseMove",
    "Time": 3599,
    "X": 756,
    "Y": 270,
    "Delta": null,
    "KeyCode": null
  },
  {
    "Type": "MouseMove",
    "Time": 3613,
    "X": 738,
    "Y": 267,
    "Delta": null,
    "KeyCode": null
  },
  {
    "Type": "MouseMove",
    "Time": 3630,
    "X": 708,
    "Y": 267,
    "Delta": null,
    "KeyCode": null
  },
  {
    "Type": "MouseMove",
    "Time": 3650,
    "X": 684,
    "Y": 264,
    "Delta": null,
    "KeyCode": null
  },
  {
    "Type": "MouseMove",
    "Time": 3672,
    "X": 645,
    "Y": 264,
    "Delta": null,
    "KeyCode": null
  },
  {
    "Type": "MouseMove",
    "Time": 3676,
    "X": 636,
    "Y": 264,
    "Delta": null,
    "KeyCode": null
  },
  {
    "Type": "MouseMove",
    "Time": 3695,
    "X": 621,
    "Y": 261,
    "Delta": null,
    "KeyCode": null
  },
  {
    "Type": "MouseMove",
    "Time": 3706,
    "X": 612,
    "Y": 261,
    "Delta": null,
    "KeyCode": null
  },
  {
    "Type": "MouseMove",
    "Time": 3727,
    "X": 588,
    "Y": 258,
    "Delta": null,
    "KeyCode": null
  },
  {
    "Type": "MouseMove",
    "Time": 3748,
    "X": 573,
    "Y": 258,
    "Delta": null,
    "KeyCode": null
  },
  {
    "Type": "MouseMove",
    "Time": 3770,
    "X": 552,
    "Y": 255,
    "Delta": null,
    "KeyCode": null
  },
  {
    "Type": "MouseMove",
    "Time": 3774,
    "X": 546,
    "Y": 255,
    "Delta": null,
    "KeyCode": null
  },
  {
    "Type": "MouseMove",
    "Time": 3790,
    "X": 543,
    "Y": 252,
    "Delta": null,
    "KeyCode": null
  },
  {
    "Type": "MouseMove",
    "Time": 3800,
    "X": 537,
    "Y": 252,
    "Delta": null,
    "KeyCode": null
  },
  {
    "Type": "MouseMove",
    "Time": 3818,
    "X": 534,
    "Y": 252,
    "Delta": null,
    "KeyCode": null
  },
  {
    "Type": "MouseMove",
    "Time": 3835,
    "X": 528,
    "Y": 252,
    "Delta": null,
    "KeyCode": null
  },
  {
    "Type": "MouseMove",
    "Time": 3852,
    "X": 525,
    "Y": 249,
    "Delta": null,
    "KeyCode": null
  },
  {
    "Type": "MouseMove",
    "Time": 3869,
    "X": 522,
    "Y": 249,
    "Delta": null,
    "KeyCode": null
  },
  {
    "Type": "MouseMove",
    "Time": 3885,
    "X": 519,
    "Y": 249,
    "Delta": null,
    "KeyCode": null
  },
  {
    "Type": "MouseMove",
    "Time": 3903,
    "X": 516,
    "Y": 249,
    "Delta": null,
    "KeyCode": null
  },
  {
    "Type": "MouseMove",
    "Time": 3945,
    "X": 513,
    "Y": 246,
    "Delta": null,
    "KeyCode": null
  },
  {
    "Type": "MouseMove",
    "Time": 3966,
    "X": 510,
    "Y": 246,
    "Delta": null,
    "KeyCode": null
  },
  {
    "Type": "MouseMove",
    "Time": 3974,
    "X": 507,
    "Y": 246,
    "Delta": null,
    "KeyCode": null
  },
  {
    "Type": "MouseMove",
    "Time": 3982,
    "X": 504,
    "Y": 246,
    "Delta": null,
    "KeyCode": null
  },
  {
    "Type": "MouseMove",
    "Time": 3990,
    "X": 501,
    "Y": 246,
    "Delta": null,
    "KeyCode": null
  },
  {
    "Type": "MouseMove",
    "Time": 4006,
    "X": 498,
    "Y": 246,
    "Delta": null,
    "KeyCode": null
  },
  {
    "Type": "MouseMove",
    "Time": 4051,
    "X": 495,
    "Y": 246,
    "Delta": null,
    "KeyCode": null
  },
  {
    "Type": "MouseMove",
    "Time": 4072,
    "X": 492,
    "Y": 246,
    "Delta": null,
    "KeyCode": null
  },
  {
    "Type": "MouseMove",
    "Time": 4124,
    "X": 489,
    "Y": 246,
    "Delta": null,
    "KeyCode": null
  },
  {
    "Type": "MouseMove",
    "Time": 4146,
    "X": 486,
    "Y": 246,
    "Delta": null,
    "KeyCode": null
  },
  {
    "Type": "MouseMove",
    "Time": 4188,
    "X": 483,
    "Y": 246,
    "Delta": null,
    "KeyCode": null
  },
  {
    "Type": "MouseMove",
    "Time": 4286,
    "X": 480,
    "Y": 243,
    "Delta": null,
    "KeyCode": null
  },
  {
    "Type": "MouseMove",
    "Time": 4403,
    "X": 480,
    "Y": 240,
    "Delta": null,
    "KeyCode": null
  },
  {
    "Type": "MouseMove",
    "Time": 4443,
    "X": 480,
    "Y": 237,
    "Delta": null,
    "KeyCode": null
  },
  {
    "Type": "MouseMove",
    "Time": 4474,
    "X": 477,
    "Y": 234,
    "Delta": null,
    "KeyCode": null
  },
  {
    "Type": "MouseMove",
    "Time": 4511,
    "X": 477,
    "Y": 231,
    "Delta": null,
    "KeyCode": null
  },
  {
    "Type": "MouseMove",
    "Time": 4546,
    "X": 477,
    "Y": 228,
    "Delta": null,
    "KeyCode": null
  },
  {
    "Type": "MouseMove",
    "Time": 4609,
    "X": 477,
    "Y": 225,
    "Delta": null,
    "KeyCode": null
  },
  {
    "Type": "DragStart",
    "Time": 4786,
    "X": 477,
    "Y": 225,
    "Delta": null,
    "KeyCode": null
  },
  {
    "Type": "DragEnd",
    "Time": 4867,
    "X": 477,
    "Y": 225,
    "Delta": null,
    "KeyCode": null
  },
  {
    "Type": "MouseMove",
    "Time": 6354,
    "X": 480,
    "Y": 225,
    "Delta": null,
    "KeyCode": null
  },
  {
    "Type": "MouseMove",
    "Time": 6371,
    "X": 483,
    "Y": 222,
    "Delta": null,
    "KeyCode": null
  },
  {
    "Type": "MouseMove",
    "Time": 6382,
    "X": 486,
    "Y": 222,
    "Delta": null,
    "KeyCode": null
  },
  {
    "Type": "MouseMove",
    "Time": 6404,
    "X": 495,
    "Y": 219,
    "Delta": null,
    "KeyCode": null
  },
  {
    "Type": "MouseMove",
    "Time": 6422,
    "X": 501,
    "Y": 216,
    "Delta": null,
    "KeyCode": null
  },
  {
    "Type": "MouseMove",
    "Time": 6446,
    "X": 507,
    "Y": 216,
    "Delta": null,
    "KeyCode": null
  },
  {
    "Type": "MouseMove",
    "Time": 6490,
    "X": 510,
    "Y": 216,
    "Delta": null,
    "KeyCode": null
  },
  {
    "Type": "MouseMove",
    "Time": 6525,
    "X": 510,
    "Y": 213,
    "Delta": null,
    "KeyCode": null
  },
  {
    "Type": "MouseMove",
    "Time": 6556,
    "X": 516,
    "Y": 213,
    "Delta": null,
    "KeyCode": null
  },
  {
    "Type": "MouseMove",
    "Time": 6575,
    "X": 519,
    "Y": 213,
    "Delta": null,
    "KeyCode": null
  },
  {
    "Type": "MouseMove",
    "Time": 6576,
    "X": 522,
    "Y": 213,
    "Delta": null,
    "KeyCode": null
  },
  {
    "Type": "MouseMove",
    "Time": 6602,
    "X": 522,
    "Y": 210,
    "Delta": null,
    "KeyCode": null
  },
  {
    "Type": "MouseMove",
    "Time": 6918,
    "X": 519,
    "Y": 228,
    "Delta": null,
    "KeyCode": null
  },
  {
    "Type": "MouseMove",
    "Time": 6939,
    "X": 504,
    "Y": 255,
    "Delta": null,
    "KeyCode": null
  },
  {
    "Type": "MouseMove",
    "Time": 6951,
    "X": 495,
    "Y": 264,
    "Delta": null,
    "KeyCode": null
  },
  {
    "Type": "MouseMove",
    "Time": 6961,
    "X": 492,
    "Y": 273,
    "Delta": null,
    "KeyCode": null
  },
  {
    "Type": "MouseMove",
    "Time": 6978,
    "X": 471,
    "Y": 297,
    "Delta": null,
    "KeyCode": null
  },
  {
    "Type": "MouseMove",
    "Time": 6991,
    "X": 456,
    "Y": 312,
    "Delta": null,
    "KeyCode": null
  },
  {
    "Type": "MouseMove",
    "Time": 7008,
    "X": 438,
    "Y": 327,
    "Delta": null,
    "KeyCode": null
  },
  {
    "Type": "MouseMove",
    "Time": 7021,
    "X": 423,
    "Y": 339,
    "Delta": null,
    "KeyCode": null
  },
  {
    "Type": "MouseMove",
    "Time": 7042,
    "X": 414,
    "Y": 345,
    "Delta": null,
    "KeyCode": null
  },
  {
    "Type": "MouseMove",
    "Time": 7059,
    "X": 411,
    "Y": 348,
    "Delta": null,
    "KeyCode": null
  },
  {
    "Type": "MouseMove",
    "Time": 7080,
    "X": 408,
    "Y": 348,
    "Delta": null,
    "KeyCode": null
  },
  {
    "Type": "MouseMove",
    "Time": 7246,
    "X": 414,
    "Y": 345,
    "Delta": null,
    "KeyCode": null
  },
  {
    "Type": "MouseMove",
    "Time": 7268,
    "X": 423,
    "Y": 336,
    "Delta": null,
    "KeyCode": null
  },
  {
    "Type": "MouseMove",
    "Time": 7291,
    "X": 450,
    "Y": 309,
    "Delta": null,
    "KeyCode": null
  },
  {
    "Type": "MouseMove",
    "Time": 7294,
    "X": 456,
    "Y": 303,
    "Delta": null,
    "KeyCode": null
  },
  {
    "Type": "MouseMove",
    "Time": 7313,
    "X": 483,
    "Y": 279,
    "Delta": null,
    "KeyCode": null
  },
  {
    "Type": "MouseMove",
    "Time": 7324,
    "X": 492,
    "Y": 270,
    "Delta": null,
    "KeyCode": null
  },
  {
    "Type": "MouseMove",
    "Time": 7340,
    "X": 525,
    "Y": 246,
    "Delta": null,
    "KeyCode": null
  },
  {
    "Type": "MouseMove",
    "Time": 7354,
    "X": 555,
    "Y": 228,
    "Delta": null,
    "KeyCode": null
  },
  {
    "Type": "MouseMove",
    "Time": 7372,
    "X": 588,
    "Y": 210,
    "Delta": null,
    "KeyCode": null
  },
  {
    "Type": "MouseMove",
    "Time": 7386,
    "X": 621,
    "Y": 192,
    "Delta": null,
    "KeyCode": null
  },
  {
    "Type": "MouseMove",
    "Time": 7408,
    "X": 660,
    "Y": 174,
    "Delta": null,
    "KeyCode": null
  },
  {
    "Type": "MouseMove",
    "Time": 7426,
    "X": 678,
    "Y": 165,
    "Delta": null,
    "KeyCode": null
  },
  {
    "Type": "MouseMove",
    "Time": 7438,
    "X": 687,
    "Y": 159,
    "Delta": null,
    "KeyCode": null
  },
  {
    "Type": "MouseMove",
    "Time": 7438,
    "X": 690,
    "Y": 156,
    "Delta": null,
    "KeyCode": null
  },
  {
    "Type": "MouseMove",
    "Time": 7472,
    "X": 693,
    "Y": 153,
    "Delta": null,
    "KeyCode": null
  },
  {
    "Type": "MouseMove",
    "Time": 7504,
    "X": 693,
    "Y": 150,
    "Delta": null,
    "KeyCode": null
  },
  {
    "Type": "MouseMove",
    "Time": 7525,
    "X": 693,
    "Y": 147,
    "Delta": null,
    "KeyCode": null
  },
  {
    "Type": "MouseMove",
    "Time": 7542,
    "X": 693,
    "Y": 144,
    "Delta": null,
    "KeyCode": null
  },
  {
    "Type": "MouseMove",
    "Time": 7573,
    "X": 693,
    "Y": 141,
    "Delta": null,
    "KeyCode": null
  },
  {
    "Type": "MouseMove",
    "Time": 7614,
    "X": 696,
    "Y": 138,
    "Delta": null,
    "KeyCode": null
  },
  {
    "Type": "MouseMove",
    "Time": 7635,
    "X": 702,
    "Y": 129,
    "Delta": null,
    "KeyCode": null
  },
  {
    "Type": "MouseMove",
    "Time": 7657,
    "X": 705,
    "Y": 126,
    "Delta": null,
    "KeyCode": null
  },
  {
    "Type": "MouseMove",
    "Time": 7838,
    "X": 708,
    "Y": 126,
    "Delta": null,
    "KeyCode": null
  },
  {
    "Type": "MouseMove",
    "Time": 7886,
    "X": 711,
    "Y": 126,
    "Delta": null,
    "KeyCode": null
  },
  {
    "Type": "MouseMove",
    "Time": 7967,
    "X": 714,
    "Y": 126,
    "Delta": null,
    "KeyCode": null
  },
  {
    "Type": "KeyDown",
    "Time": 8048,
    "X": null,
    "Y": null,
    "Delta": null,
    "KeyCode": 49
  },
  {
    "Type": "KeyUp",
    "Time": 8095,
    "X": null,
    "Y": null,
    "Delta": null,
    "KeyCode": 49
  },
  {
    "Type": "MouseMove",
    "Time": 8154,
    "X": 714,
    "Y": 129,
    "Delta": null,
    "KeyCode": null
  },
  {
    "Type": "MouseMove",
    "Time": 8408,
    "X": 714,
    "Y": 132,
    "Delta": null,
    "KeyCode": null
  },
  {
    "Type": "MouseMove",
    "Time": 8426,
    "X": 717,
    "Y": 135,
    "Delta": null,
    "KeyCode": null
  },
  {
    "Type": "MouseMove",
    "Time": 8452,
    "X": 720,
    "Y": 138,
    "Delta": null,
    "KeyCode": null
  },
  {
    "Type": "MouseMove",
    "Time": 8471,
    "X": 723,
    "Y": 138,
    "Delta": null,
    "KeyCode": null
  },
  {
    "Type": "MouseMove",
    "Time": 8487,
    "X": 726,
    "Y": 141,
    "Delta": null,
    "KeyCode": null
  },
  {
    "Type": "MouseMove",
    "Time": 8509,
    "X": 729,
    "Y": 147,
    "Delta": null,
    "KeyCode": null
  },
  {
    "Type": "MouseMove",
    "Time": 8528,
    "X": 735,
    "Y": 153,
    "Delta": null,
    "KeyCode": null
  },
  {
    "Type": "MouseMove",
    "Time": 8549,
    "X": 738,
    "Y": 156,
    "Delta": null,
    "KeyCode": null
  },
  {
    "Type": "MouseMove",
    "Time": 8566,
    "X": 741,
    "Y": 159,
    "Delta": null,
    "KeyCode": null
  },
  {
    "Type": "MouseMove",
    "Time": 8597,
    "X": 747,
    "Y": 165,
    "Delta": null,
    "KeyCode": null
  },
  {
    "Type": "MouseMove",
    "Time": 8617,
    "X": 750,
    "Y": 171,
    "Delta": null,
    "KeyCode": null
  },
  {
    "Type": "MouseMove",
    "Time": 8639,
    "X": 756,
    "Y": 177,
    "Delta": null,
    "KeyCode": null
  },
  {
    "Type": "MouseMove",
    "Time": 8662,
    "X": 762,
    "Y": 183,
    "Delta": null,
    "KeyCode": null
  },
  {
    "Type": "MouseMove",
    "Time": 8683,
    "X": 771,
    "Y": 192,
    "Delta": null,
    "KeyCode": null
  },
  {
    "Type": "MouseMove",
    "Time": 8699,
    "X": 774,
    "Y": 195,
    "Delta": null,
    "KeyCode": null
  },
  {
    "Type": "MouseMove",
    "Time": 8716,
    "X": 786,
    "Y": 207,
    "Delta": null,
    "KeyCode": null
  },
  {
    "Type": "MouseMove",
    "Time": 8729,
    "X": 789,
    "Y": 210,
    "Delta": null,
    "KeyCode": null
  },
  {
    "Type": "MouseMove",
    "Time": 8751,
    "X": 798,
    "Y": 216,
    "Delta": null,
    "KeyCode": null
  },
  {
    "Type": "MouseMove",
    "Time": 8771,
    "X": 804,
    "Y": 222,
    "Delta": null,
    "KeyCode": null
  },
  {
    "Type": "MouseMove",
    "Time": 8788,
    "X": 810,
    "Y": 228,
    "Delta": null,
    "KeyCode": null
  },
  {
    "Type": "MouseMove",
    "Time": 8808,
    "X": 819,
    "Y": 231,
    "Delta": null,
    "KeyCode": null
  },
  {
    "Type": "MouseMove",
    "Time": 8825,
    "X": 825,
    "Y": 237,
    "Delta": null,
    "KeyCode": null
  },
  {
    "Type": "MouseMove",
    "Time": 8846,
    "X": 831,
    "Y": 243,
    "Delta": null,
    "KeyCode": null
  },
  {
    "Type": "MouseMove",
    "Time": 8856,
    "X": 834,
    "Y": 246,
    "Delta": null,
    "KeyCode": null
  },
  {
    "Type": "MouseMove",
    "Time": 8876,
    "X": 840,
    "Y": 255,
    "Delta": null,
    "KeyCode": null
  },
  {
    "Type": "MouseMove",
    "Time": 8876,
    "X": 843,
    "Y": 258,
    "Delta": null,
    "KeyCode": null
  },
  {
    "Type": "MouseMove",
    "Time": 8894,
    "X": 849,
    "Y": 267,
    "Delta": null,
    "KeyCode": null
  },
  {
    "Type": "MouseMove",
    "Time": 8917,
    "X": 855,
    "Y": 279,
    "Delta": null,
    "KeyCode": null
  },
  {
    "Type": "MouseMove",
    "Time": 8937,
    "X": 858,
    "Y": 282,
    "Delta": null,
    "KeyCode": null
  },
  {
    "Type": "MouseMove",
    "Time": 8938,
    "X": 861,
    "Y": 291,
    "Delta": null,
    "KeyCode": null
  },
  {
    "Type": "MouseMove",
    "Time": 8958,
    "X": 867,
    "Y": 306,
    "Delta": null,
    "KeyCode": null
  },
  {
    "Type": "MouseMove",
    "Time": 8979,
    "X": 870,
    "Y": 315,
    "Delta": null,
    "KeyCode": null
  },
  {
    "Type": "MouseMove",
    "Time": 8999,
    "X": 873,
    "Y": 324,
    "Delta": null,
    "KeyCode": null
  },
  {
    "Type": "MouseMove",
    "Time": 9022,
    "X": 876,
    "Y": 330,
    "Delta": null,
    "KeyCode": null
  },
  {
    "Type": "MouseMove",
    "Time": 9042,
    "X": 876,
    "Y": 336,
    "Delta": null,
    "KeyCode": null
  },
  {
    "Type": "MouseMove",
    "Time": 9052,
    "X": 876,
    "Y": 339,
    "Delta": null,
    "KeyCode": null
  },
  {
    "Type": "MouseMove",
    "Time": 9070,
    "X": 879,
    "Y": 345,
    "Delta": null,
    "KeyCode": null
  },
  {
    "Type": "MouseMove",
    "Time": 9080,
    "X": 882,
    "Y": 348,
    "Delta": null,
    "KeyCode": null
  },
  {
    "Type": "MouseMove",
    "Time": 9099,
    "X": 885,
    "Y": 354,
    "Delta": null,
    "KeyCode": null
  },
  {
    "Type": "MouseMove",
    "Time": 9116,
    "X": 885,
    "Y": 357,
    "Delta": null,
    "KeyCode": null
  },
  {
    "Type": "MouseMove",
    "Time": 9138,
    "X": 888,
    "Y": 366,
    "Delta": null,
    "KeyCode": null
  },
  {
    "Type": "MouseMove",
    "Time": 9160,
    "X": 894,
    "Y": 375,
    "Delta": null,
    "KeyCode": null
  },
  {
    "Type": "MouseMove",
    "Time": 9181,
    "X": 897,
    "Y": 381,
    "Delta": null,
    "KeyCode": null
  },
  {
    "Type": "MouseMove",
    "Time": 9182,
    "X": 900,
    "Y": 381,
    "Delta": null,
    "KeyCode": null
  },
  {
    "Type": "MouseMove",
    "Time": 9197,
    "X": 903,
    "Y": 384,
    "Delta": null,
    "KeyCode": null
  },
  {
    "Type": "MouseMove",
    "Time": 9208,
    "X": 906,
    "Y": 390,
    "Delta": null,
    "KeyCode": null
  },
  {
    "Type": "MouseMove",
    "Time": 9227,
    "X": 906,
    "Y": 393,
    "Delta": null,
    "KeyCode": null
  },
  {
    "Type": "MouseMove",
    "Time": 9246,
    "X": 909,
    "Y": 396,
    "Delta": null,
    "KeyCode": null
  },
  {
    "Type": "MouseMove",
    "Time": 9267,
    "X": 912,
    "Y": 402,
    "Delta": null,
    "KeyCode": null
  },
  {
    "Type": "MouseMove",
    "Time": 9289,
    "X": 915,
    "Y": 405,
    "Delta": null,
    "KeyCode": null
  },
  {
    "Type": "MouseMove",
    "Time": 9306,
    "X": 915,
    "Y": 408,
    "Delta": null,
    "KeyCode": null
  },
  {
    "Type": "MouseMove",
    "Time": 9348,
    "X": 918,
    "Y": 408,
    "Delta": null,
    "KeyCode": null
  },
  {
    "Type": "MouseMove",
    "Time": 9371,
    "X": 921,
    "Y": 411,
    "Delta": null,
    "KeyCode": null
  },
  {
    "Type": "MouseMove",
    "Time": 9392,
    "X": 921,
    "Y": 414,
    "Delta": null,
    "KeyCode": null
  },
  {
    "Type": "MouseMove",
    "Time": 9406,
    "X": 924,
    "Y": 417,
    "Delta": null,
    "KeyCode": null
  },
  {
    "Type": "MouseMove",
    "Time": 9426,
    "X": 924,
    "Y": 420,
    "Delta": null,
    "KeyCode": null
  },
  {
    "Type": "MouseMove",
    "Time": 9465,
    "X": 927,
    "Y": 423,
    "Delta": null,
    "KeyCode": null
  },
  {
    "Type": "MouseMove",
    "Time": 9489,
    "X": 930,
    "Y": 426,
    "Delta": null,
    "KeyCode": null
  },
  {
    "Type": "MouseMove",
    "Time": 9509,
    "X": 933,
    "Y": 429,
    "Delta": null,
    "KeyCode": null
  },
  {
    "Type": "MouseMove",
    "Time": 9550,
    "X": 933,
    "Y": 432,
    "Delta": null,
    "KeyCode": null
  },
  {
    "Type": "MouseMove",
    "Time": 9591,
    "X": 936,
    "Y": 432,
    "Delta": null,
    "KeyCode": null
  },
  {
    "Type": "MouseMove",
    "Time": 9605,
    "X": 936,
    "Y": 435,
    "Delta": null,
    "KeyCode": null
  },
  {
    "Type": "MouseMove",
    "Time": 9647,
    "X": 939,
    "Y": 435,
    "Delta": null,
    "KeyCode": null
  },
  {
    "Type": "MouseMove",
    "Time": 9668,
    "X": 939,
    "Y": 438,
    "Delta": null,
    "KeyCode": null
  },
  {
    "Type": "MouseMove",
    "Time": 9702,
    "X": 939,
    "Y": 441,
    "Delta": null,
    "KeyCode": null
  },
  {
    "Type": "MouseMove",
    "Time": 9771,
    "X": 942,
    "Y": 444,
    "Delta": null,
    "KeyCode": null
  },
  {
    "Type": "MouseMove",
    "Time": 9810,
    "X": 942,
    "Y": 447,
    "Delta": null,
    "KeyCode": null
  },
  {
    "Type": "MouseMove",
    "Time": 9870,
    "X": 942,
    "Y": 450,
    "Delta": null,
    "KeyCode": null
  },
  {
    "Type": "MouseMove",
    "Time": 9985,
    "X": 942,
    "Y": 453,
    "Delta": null,
    "KeyCode": null
  },
  {
    "Type": "MouseMove",
    "Time": 10012,
    "X": 942,
    "Y": 456,
    "Delta": null,
    "KeyCode": null
  },
  {
    "Type": "MouseMove",
    "Time": 10043,
    "X": 942,
    "Y": 459,
    "Delta": null,
    "KeyCode": null
  },
  {
    "Type": "MouseMove",
    "Time": 10058,
    "X": 942,
    "Y": 462,
    "Delta": null,
    "KeyCode": null
  },
  {
    "Type": "MouseMove",
    "Time": 10257,
    "X": 942,
    "Y": 465,
    "Delta": null,
    "KeyCode": null
  },
  {
    "Type": "DragStart",
    "Time": 10272,
    "X": 942,
    "Y": 465,
    "Delta": null,
    "KeyCode": null
  },
  {
    "Type": "DragEnd",
    "Time": 10391,
    "X": 942,
    "Y": 465,
    "Delta": null,
    "KeyCode": null
  },
  {
    "Type": "MouseMove",
    "Time": 10558,
    "X": 942,
    "Y": 462,
    "Delta": null,
    "KeyCode": null
  },
  {
    "Type": "MouseMove",
    "Time": 10576,
    "X": 933,
    "Y": 462,
    "Delta": null,
    "KeyCode": null
  },
  {
    "Type": "MouseMove",
    "Time": 10599,
    "X": 924,
    "Y": 456,
    "Delta": null,
    "KeyCode": null
  },
  {
    "Type": "MouseMove",
    "Time": 10610,
    "X": 921,
    "Y": 456,
    "Delta": null,
    "KeyCode": null
  },
  {
    "Type": "MouseMove",
    "Time": 10622,
    "X": 915,
    "Y": 456,
    "Delta": null,
    "KeyCode": null
  },
  {
    "Type": "MouseMove",
    "Time": 10642,
    "X": 912,
    "Y": 459,
    "Delta": null,
    "KeyCode": null
  },
  {
    "Type": "MouseMove",
    "Time": 10661,
    "X": 897,
    "Y": 456,
    "Delta": null,
    "KeyCode": null
  },
  {
    "Type": "MouseMove",
    "Time": 10676,
    "X": 879,
    "Y": 453,
    "Delta": null,
    "KeyCode": null
  },
  {
    "Type": "MouseMove",
    "Time": 10693,
    "X": 858,
    "Y": 450,
    "Delta": null,
    "KeyCode": null
  },
  {
    "Type": "MouseMove",
    "Time": 10708,
    "X": 840,
    "Y": 447,
    "Delta": null,
    "KeyCode": null
  },
  {
    "Type": "MouseMove",
    "Time": 10727,
    "X": 831,
    "Y": 444,
    "Delta": null,
    "KeyCode": null
  },
  {
    "Type": "MouseMove",
    "Time": 10750,
    "X": 816,
    "Y": 441,
    "Delta": null,
    "KeyCode": null
  },
  {
    "Type": "MouseMove",
    "Time": 10771,
    "X": 813,
    "Y": 438,
    "Delta": null,
    "KeyCode": null
  },
  {
    "Type": "MouseMove",
    "Time": 10787,
    "X": 804,
    "Y": 432,
    "Delta": null,
    "KeyCode": null
  },
  {
    "Type": "MouseMove",
    "Time": 10803,
    "X": 786,
    "Y": 429,
    "Delta": null,
    "KeyCode": null
  },
  {
    "Type": "MouseMove",
    "Time": 10819,
    "X": 768,
    "Y": 426,
    "Delta": null,
    "KeyCode": null
  },
  {
    "Type": "MouseMove",
    "Time": 10840,
    "X": 747,
    "Y": 423,
    "Delta": null,
    "KeyCode": null
  },
  {
    "Type": "MouseMove",
    "Time": 10863,
    "X": 729,
    "Y": 420,
    "Delta": null,
    "KeyCode": null
  },
  {
    "Type": "MouseMove",
    "Time": 10884,
    "X": 723,
    "Y": 417,
    "Delta": null,
    "KeyCode": null
  },
  {
    "Type": "MouseMove",
    "Time": 10886,
    "X": 717,
    "Y": 417,
    "Delta": null,
    "KeyCode": null
  },
  {
    "Type": "MouseMove",
    "Time": 10894,
    "X": 714,
    "Y": 414,
    "Delta": null,
    "KeyCode": null
  },
  {
    "Type": "MouseMove",
    "Time": 10910,
    "X": 708,
    "Y": 411,
    "Delta": null,
    "KeyCode": null
  },
  {
    "Type": "MouseMove",
    "Time": 10922,
    "X": 705,
    "Y": 411,
    "Delta": null,
    "KeyCode": null
  },
  {
    "Type": "MouseMove",
    "Time": 10933,
    "X": 702,
    "Y": 408,
    "Delta": null,
    "KeyCode": null
  },
  {
    "Type": "MouseMove",
    "Time": 10954,
    "X": 690,
    "Y": 402,
    "Delta": null,
    "KeyCode": null
  },
  {
    "Type": "MouseMove",
    "Time": 10972,
    "X": 681,
    "Y": 399,
    "Delta": null,
    "KeyCode": null
  },
  {
    "Type": "MouseMove",
    "Time": 10974,
    "X": 678,
    "Y": 396,
    "Delta": null,
    "KeyCode": null
  },
  {
    "Type": "MouseMove",
    "Time": 10986,
    "X": 675,
    "Y": 396,
    "Delta": null,
    "KeyCode": null
  },
  {
    "Type": "MouseMove",
    "Time": 10996,
    "X": 672,
    "Y": 393,
    "Delta": null,
    "KeyCode": null
  },
  {
    "Type": "MouseMove",
    "Time": 11017,
    "X": 660,
    "Y": 387,
    "Delta": null,
    "KeyCode": null
  },
  {
    "Type": "MouseMove",
    "Time": 11037,
    "X": 654,
    "Y": 381,
    "Delta": null,
    "KeyCode": null
  },
  {
    "Type": "MouseMove",
    "Time": 11038,
    "X": 648,
    "Y": 378,
    "Delta": null,
    "KeyCode": null
  },
  {
    "Type": "MouseMove",
    "Time": 11046,
    "X": 645,
    "Y": 378,
    "Delta": null,
    "KeyCode": null
  },
  {
    "Type": "MouseMove",
    "Time": 11063,
    "X": 642,
    "Y": 375,
    "Delta": null,
    "KeyCode": null
  },
  {
    "Type": "MouseMove",
    "Time": 11074,
    "X": 639,
    "Y": 372,
    "Delta": null,
    "KeyCode": null
  },
  {
    "Type": "MouseMove",
    "Time": 11095,
    "X": 636,
    "Y": 369,
    "Delta": null,
    "KeyCode": null
  },
  {
    "Type": "MouseMove",
    "Time": 11112,
    "X": 633,
    "Y": 366,
    "Delta": null,
    "KeyCode": null
  },
  {
    "Type": "MouseMove",
    "Time": 11120,
    "X": 630,
    "Y": 363,
    "Delta": null,
    "KeyCode": null
  },
  {
    "Type": "MouseMove",
    "Time": 11128,
    "X": 627,
    "Y": 360,
    "Delta": null,
    "KeyCode": null
  },
  {
    "Type": "MouseMove",
    "Time": 11136,
    "X": 624,
    "Y": 357,
    "Delta": null,
    "KeyCode": null
  },
  {
    "Type": "MouseMove",
    "Time": 11144,
    "X": 624,
    "Y": 354,
    "Delta": null,
    "KeyCode": null
  },
  {
    "Type": "MouseMove",
    "Time": 11152,
    "X": 621,
    "Y": 354,
    "Delta": null,
    "KeyCode": null
  },
  {
    "Type": "MouseMove",
    "Time": 11160,
    "X": 618,
    "Y": 351,
    "Delta": null,
    "KeyCode": null
  },
  {
    "Type": "MouseMove",
    "Time": 11184,
    "X": 618,
    "Y": 348,
    "Delta": null,
    "KeyCode": null
  },
  {
    "Type": "MouseMove",
    "Time": 11201,
    "X": 615,
    "Y": 345,
    "Delta": null,
    "KeyCode": null
  },
  {
    "Type": "MouseMove",
    "Time": 11216,
    "X": 615,
    "Y": 342,
    "Delta": null,
    "KeyCode": null
  },
  {
    "Type": "MouseMove",
    "Time": 11233,
    "X": 612,
    "Y": 342,
    "Delta": null,
    "KeyCode": null
  },
  {
    "Type": "MouseMove",
    "Time": 11264,
    "X": 609,
    "Y": 339,
    "Delta": null,
    "KeyCode": null
  },
  {
    "Type": "MouseMove",
    "Time": 11298,
    "X": 606,
    "Y": 336,
    "Delta": null,
    "KeyCode": null
  },
  {
    "Type": "MouseMove",
    "Time": 11337,
    "X": 603,
    "Y": 336,
    "Delta": null,
    "KeyCode": null
  },
  {
    "Type": "MouseMove",
    "Time": 11357,
    "X": 600,
    "Y": 333,
    "Delta": null,
    "KeyCode": null
  },
  {
    "Type": "MouseMove",
    "Time": 11457,
    "X": 597,
    "Y": 330,
    "Delta": null,
    "KeyCode": null
  },
  {
    "Type": "MouseMove",
    "Time": 11458,
    "X": 594,
    "Y": 330,
    "Delta": null,
    "KeyCode": null
  },
  {
    "Type": "MouseMove",
    "Time": 11466,
    "X": 591,
    "Y": 330,
    "Delta": null,
    "KeyCode": null
  },
  {
    "Type": "MouseMove",
    "Time": 11497,
    "X": 588,
    "Y": 330,
    "Delta": null,
    "KeyCode": null
  },
  {
    "Type": "MouseMove",
    "Time": 11517,
    "X": 588,
    "Y": 327,
    "Delta": null,
    "KeyCode": null
  },
  {
    "Type": "MouseMove",
    "Time": 11537,
    "X": 585,
    "Y": 327,
    "Delta": null,
    "KeyCode": null
  },
  {
    "Type": "MouseMove",
    "Time": 11546,
    "X": 582,
    "Y": 327,
    "Delta": null,
    "KeyCode": null
  },
  {
    "Type": "MouseMove",
    "Time": 11580,
    "X": 582,
    "Y": 324,
    "Delta": null,
    "KeyCode": null
  },
  {
    "Type": "MouseMove",
    "Time": 11591,
    "X": 579,
    "Y": 324,
    "Delta": null,
    "KeyCode": null
  },
  {
    "Type": "MouseMove",
    "Time": 11608,
    "X": 576,
    "Y": 324,
    "Delta": null,
    "KeyCode": null
  },
  {
    "Type": "MouseMove",
    "Time": 11629,
    "X": 570,
    "Y": 321,
    "Delta": null,
    "KeyCode": null
  },
  {
    "Type": "MouseMove",
    "Time": 11650,
    "X": 564,
    "Y": 318,
    "Delta": null,
    "KeyCode": null
  },
  {
    "Type": "MouseMove",
    "Time": 11651,
    "X": 561,
    "Y": 318,
    "Delta": null,
    "KeyCode": null
  },
  {
    "Type": "MouseMove",
    "Time": 11658,
    "X": 558,
    "Y": 318,
    "Delta": null,
    "KeyCode": null
  },
  {
    "Type": "MouseMove",
    "Time": 11674,
    "X": 555,
    "Y": 318,
    "Delta": null,
    "KeyCode": null
  },
  {
    "Type": "MouseMove",
    "Time": 11795,
    "X": 552,
    "Y": 318,
    "Delta": null,
    "KeyCode": null
  },
  {
    "Type": "MouseMove",
    "Time": 11921,
    "X": 549,
    "Y": 318,
    "Delta": null,
    "KeyCode": null
  },
  {
    "Type": "MouseMove",
    "Time": 12210,
    "X": 546,
    "Y": 318,
    "Delta": null,
    "KeyCode": null
  },
  {
    "Type": "MouseMove",
    "Time": 12407,
    "X": 543,
    "Y": 318,
    "Delta": null,
    "KeyCode": null
  },
  {
    "Type": "MouseMove",
    "Time": 12481,
    "X": 540,
    "Y": 318,
    "Delta": null,
    "KeyCode": null
  },
  {
    "Type": "MouseMove",
    "Time": 12504,
    "X": 537,
    "Y": 321,
    "Delta": null,
    "KeyCode": null
  },
  {
    "Type": "MouseMove",
    "Time": 12576,
    "X": 534,
    "Y": 321,
    "Delta": null,
    "KeyCode": null
  },
  {
    "Type": "MouseMove",
    "Time": 12650,
    "X": 531,
    "Y": 321,
    "Delta": null,
    "KeyCode": null
  },
  {
    "Type": "MouseMove",
    "Time": 12697,
    "X": 528,
    "Y": 321,
    "Delta": null,
    "KeyCode": null
  },
  {
    "Type": "DragStart",
    "Time": 12903,
    "X": 528,
    "Y": 321,
    "Delta": null,
    "KeyCode": null
  },
  {
    "Type": "DragEnd",
    "Time": 13014,
    "X": 528,
    "Y": 321,
    "Delta": null,
    "KeyCode": null
  },
  {
    "Type": "MouseMove",
    "Time": 13223,
    "X": 525,
    "Y": 324,
    "Delta": null,
    "KeyCode": null
  },
  {
    "Type": "MouseMove",
    "Time": 13268,
    "X": 522,
    "Y": 324,
    "Delta": null,
    "KeyCode": null
  },
  {
    "Type": "MouseMove",
    "Time": 13344,
    "X": 519,
    "Y": 324,
    "Delta": null,
    "KeyCode": null
  },
  {
    "Type": "MouseMove",
    "Time": 13361,
    "X": 516,
    "Y": 324,
    "Delta": null,
    "KeyCode": null
  },
  {
    "Type": "MouseMove",
    "Time": 13394,
    "X": 516,
    "Y": 327,
    "Delta": null,
    "KeyCode": null
  },
  {
    "Type": "MouseMove",
    "Time": 13413,
    "X": 513,
    "Y": 327,
    "Delta": null,
    "KeyCode": null
  },
  {
    "Type": "MouseMove",
    "Time": 13448,
    "X": 510,
    "Y": 327,
    "Delta": null,
    "KeyCode": null
  },
  {
    "Type": "MouseMove",
    "Time": 13487,
    "X": 510,
    "Y": 330,
    "Delta": null,
    "KeyCode": null
  },
  {
    "Type": "MouseMove",
    "Time": 13509,
    "X": 507,
    "Y": 330,
    "Delta": null,
    "KeyCode": null
  },
  {
    "Type": "MouseMove",
    "Time": 13628,
    "X": 504,
    "Y": 330,
    "Delta": null,
    "KeyCode": null
  },
  {
    "Type": "MouseMove",
    "Time": 13705,
    "X": 501,
    "Y": 333,
    "Delta": null,
    "KeyCode": null
  },
  {
    "Type": "MouseMove",
    "Time": 13727,
    "X": 498,
    "Y": 333,
    "Delta": null,
    "KeyCode": null
  },
  {
    "Type": "MouseMove",
    "Time": 13736,
    "X": 498,
    "Y": 336,
    "Delta": null,
    "KeyCode": null
  },
  {
    "Type": "MouseMove",
    "Time": 13765,
    "X": 495,
    "Y": 336,
    "Delta": null,
    "KeyCode": null
  },
  {
    "Type": "MouseMove",
    "Time": 13972,
    "X": 498,
    "Y": 336,
    "Delta": null,
    "KeyCode": null
  },
  {
    "Type": "MouseMove",
    "Time": 13993,
    "X": 501,
    "Y": 336,
    "Delta": null,
    "KeyCode": null
  },
  {
    "Type": "MouseMove",
    "Time": 14013,
    "X": 510,
    "Y": 333,
    "Delta": null,
    "KeyCode": null
  },
  {
    "Type": "MouseMove",
    "Time": 14025,
    "X": 516,
    "Y": 333,
    "Delta": null,
    "KeyCode": null
  },
  {
    "Type": "MouseMove",
    "Time": 14036,
    "X": 519,
    "Y": 330,
    "Delta": null,
    "KeyCode": null
  },
  {
    "Type": "MouseMove",
    "Time": 14055,
    "X": 525,
    "Y": 330,
    "Delta": null,
    "KeyCode": null
  },
  {
    "Type": "MouseMove",
    "Time": 14073,
    "X": 528,
    "Y": 327,
    "Delta": null,
    "KeyCode": null
  },
  {
    "Type": "MouseMove",
    "Time": 14088,
    "X": 537,
    "Y": 324,
    "Delta": null,
    "KeyCode": null
  },
  {
    "Type": "MouseMove",
    "Time": 14109,
    "X": 549,
    "Y": 321,
    "Delta": null,
    "KeyCode": null
  },
  {
    "Type": "MouseMove",
    "Time": 14130,
    "X": 558,
    "Y": 318,
    "Delta": null,
    "KeyCode": null
  },
  {
    "Type": "MouseMove",
    "Time": 14132,
    "X": 564,
    "Y": 318,
    "Delta": null,
    "KeyCode": null
  },
  {
    "Type": "MouseMove",
    "Time": 14140,
    "X": 567,
    "Y": 318,
    "Delta": null,
    "KeyCode": null
  },
  {
    "Type": "MouseMove",
    "Time": 14148,
    "X": 570,
    "Y": 315,
    "Delta": null,
    "KeyCode": null
  },
  {
    "Type": "MouseMove",
    "Time": 14164,
    "X": 573,
    "Y": 315,
    "Delta": null,
    "KeyCode": null
  },
  {
    "Type": "MouseMove",
    "Time": 14197,
    "X": 579,
    "Y": 312,
    "Delta": null,
    "KeyCode": null
  },
  {
    "Type": "MouseMove",
    "Time": 14216,
    "X": 585,
    "Y": 312,
    "Delta": null,
    "KeyCode": null
  },
  {
    "Type": "MouseMove",
    "Time": 14237,
    "X": 603,
    "Y": 306,
    "Delta": null,
    "KeyCode": null
  },
  {
    "Type": "MouseMove",
    "Time": 14261,
    "X": 624,
    "Y": 300,
    "Delta": null,
    "KeyCode": null
  },
  {
    "Type": "MouseMove",
    "Time": 14282,
    "X": 639,
    "Y": 297,
    "Delta": null,
    "KeyCode": null
  },
  {
    "Type": "MouseMove",
    "Time": 14305,
    "X": 654,
    "Y": 291,
    "Delta": null,
    "KeyCode": null
  },
  {
    "Type": "MouseMove",
    "Time": 14326,
    "X": 672,
    "Y": 288,
    "Delta": null,
    "KeyCode": null
  },
  {
    "Type": "MouseMove",
    "Time": 14346,
    "X": 684,
    "Y": 285,
    "Delta": null,
    "KeyCode": null
  },
  {
    "Type": "MouseMove",
    "Time": 14350,
    "X": 690,
    "Y": 285,
    "Delta": null,
    "KeyCode": null
  },
  {
    "Type": "MouseMove",
    "Time": 14358,
    "X": 696,
    "Y": 282,
    "Delta": null,
    "KeyCode": null
  },
  {
    "Type": "MouseMove",
    "Time": 14370,
    "X": 699,
    "Y": 282,
    "Delta": null,
    "KeyCode": null
  },
  {
    "Type": "MouseMove",
    "Time": 14380,
    "X": 702,
    "Y": 282,
    "Delta": null,
    "KeyCode": null
  },
  {
    "Type": "MouseMove",
    "Time": 14397,
    "X": 714,
    "Y": 282,
    "Delta": null,
    "KeyCode": null
  },
  {
    "Type": "MouseMove",
    "Time": 14411,
    "X": 720,
    "Y": 279,
    "Delta": null,
    "KeyCode": null
  },
  {
    "Type": "MouseMove",
    "Time": 14429,
    "X": 729,
    "Y": 276,
    "Delta": null,
    "KeyCode": null
  },
  {
    "Type": "MouseMove",
    "Time": 14450,
    "X": 741,
    "Y": 270,
    "Delta": null,
    "KeyCode": null
  },
  {
    "Type": "MouseMove",
    "Time": 14462,
    "X": 744,
    "Y": 270,
    "Delta": null,
    "KeyCode": null
  },
  {
    "Type": "MouseMove",
    "Time": 14462,
    "X": 750,
    "Y": 270,
    "Delta": null,
    "KeyCode": null
  },
  {
    "Type": "MouseMove",
    "Time": 14491,
    "X": 753,
    "Y": 270,
    "Delta": null,
    "KeyCode": null
  },
  {
    "Type": "MouseMove",
    "Time": 14506,
    "X": 756,
    "Y": 267,
    "Delta": null,
    "KeyCode": null
  },
  {
    "Type": "MouseMove",
    "Time": 14544,
    "X": 759,
    "Y": 267,
    "Delta": null,
    "KeyCode": null
  },
  {
    "Type": "MouseMove",
    "Time": 14559,
    "X": 762,
    "Y": 264,
    "Delta": null,
    "KeyCode": null
  },
  {
    "Type": "MouseMove",
    "Time": 14602,
    "X": 765,
    "Y": 264,
    "Delta": null,
    "KeyCode": null
  },
  {
    "Type": "MouseMove",
    "Time": 14626,
    "X": 768,
    "Y": 261,
    "Delta": null,
    "KeyCode": null
  },
  {
    "Type": "MouseMove",
    "Time": 14640,
    "X": 771,
    "Y": 261,
    "Delta": null,
    "KeyCode": null
  },
  {
    "Type": "MouseMove",
    "Time": 14660,
    "X": 771,
    "Y": 258,
    "Delta": null,
    "KeyCode": null
  },
  {
    "Type": "MouseMove",
    "Time": 14661,
    "X": 774,
    "Y": 258,
    "Delta": null,
    "KeyCode": null
  },
  {
    "Type": "MouseMove",
    "Time": 14707,
    "X": 777,
    "Y": 255,
    "Delta": null,
    "KeyCode": null
  },
  {
    "Type": "MouseMove",
    "Time": 14729,
    "X": 780,
    "Y": 255,
    "Delta": null,
    "KeyCode": null
  },
  {
    "Type": "MouseMove",
    "Time": 14751,
    "X": 780,
    "Y": 252,
    "Delta": null,
    "KeyCode": null
  },
  {
    "Type": "MouseMove",
    "Time": 14752,
    "X": 783,
    "Y": 252,
    "Delta": null,
    "KeyCode": null
  },
  {
    "Type": "MouseMove",
    "Time": 14761,
    "X": 786,
    "Y": 252,
    "Delta": null,
    "KeyCode": null
  },
  {
    "Type": "MouseMove",
    "Time": 14772,
    "X": 786,
    "Y": 249,
    "Delta": null,
    "KeyCode": null
  },
  {
    "Type": "MouseMove",
    "Time": 14804,
    "X": 789,
    "Y": 246,
    "Delta": null,
    "KeyCode": null
  },
  {
    "Type": "MouseMove",
    "Time": 14848,
    "X": 792,
    "Y": 246,
    "Delta": null,
    "KeyCode": null
  },
  {
    "Type": "MouseMove",
    "Time": 15042,
    "X": 792,
    "Y": 243,
    "Delta": null,
    "KeyCode": null
  },
  {
    "Type": "MouseMove",
    "Time": 15062,
    "X": 792,
    "Y": 240,
    "Delta": null,
    "KeyCode": null
  },
  {
    "Type": "MouseMove",
    "Time": 15083,
    "X": 786,
    "Y": 234,
    "Delta": null,
    "KeyCode": null
  },
  {
    "Type": "MouseMove",
    "Time": 15090,
    "X": 783,
    "Y": 231,
    "Delta": null,
    "KeyCode": null
  },
  {
    "Type": "MouseMove",
    "Time": 15098,
    "X": 780,
    "Y": 228,
    "Delta": null,
    "KeyCode": null
  },
  {
    "Type": "MouseMove",
    "Time": 15109,
    "X": 771,
    "Y": 225,
    "Delta": null,
    "KeyCode": null
  },
  {
    "Type": "MouseMove",
    "Time": 15120,
    "X": 768,
    "Y": 222,
    "Delta": null,
    "KeyCode": null
  },
  {
    "Type": "MouseMove",
    "Time": 15142,
    "X": 756,
    "Y": 216,
    "Delta": null,
    "KeyCode": null
  },
  {
    "Type": "MouseMove",
    "Time": 15163,
    "X": 753,
    "Y": 210,
    "Delta": null,
    "KeyCode": null
  },
  {
    "Type": "MouseMove",
    "Time": 15170,
    "X": 753,
    "Y": 204,
    "Delta": null,
    "KeyCode": null
  },
  {
    "Type": "MouseMove",
    "Time": 15178,
    "X": 750,
    "Y": 201,
    "Delta": null,
    "KeyCode": null
  },
  {
    "Type": "MouseMove",
    "Time": 15186,
    "X": 750,
    "Y": 195,
    "Delta": null,
    "KeyCode": null
  },
  {
    "Type": "MouseMove",
    "Time": 15194,
    "X": 750,
    "Y": 192,
    "Delta": null,
    "KeyCode": null
  },
  {
    "Type": "MouseMove",
    "Time": 15205,
    "X": 747,
    "Y": 186,
    "Delta": null,
    "KeyCode": null
  },
  {
    "Type": "MouseMove",
    "Time": 15214,
    "X": 747,
    "Y": 180,
    "Delta": null,
    "KeyCode": null
  },
  {
    "Type": "MouseMove",
    "Time": 15232,
    "X": 744,
    "Y": 177,
    "Delta": null,
    "KeyCode": null
  },
  {
    "Type": "MouseMove",
    "Time": 15268,
    "X": 741,
    "Y": 174,
    "Delta": null,
    "KeyCode": null
  },
  {
    "Type": "MouseMove",
    "Time": 15269,
    "X": 741,
    "Y": 171,
    "Delta": null,
    "KeyCode": null
  },
  {
    "Type": "MouseMove",
    "Time": 15291,
    "X": 741,
    "Y": 168,
    "Delta": null,
    "KeyCode": null
  },
  {
    "Type": "MouseMove",
    "Time": 15312,
    "X": 738,
    "Y": 165,
    "Delta": null,
    "KeyCode": null
  },
  {
    "Type": "MouseMove",
    "Time": 15333,
    "X": 735,
    "Y": 162,
    "Delta": null,
    "KeyCode": null
  },
  {
    "Type": "MouseMove",
    "Time": 15356,
    "X": 732,
    "Y": 159,
    "Delta": null,
    "KeyCode": null
  },
  {
    "Type": "MouseMove",
    "Time": 15376,
    "X": 729,
    "Y": 156,
    "Delta": null,
    "KeyCode": null
  },
  {
    "Type": "MouseMove",
    "Time": 15398,
    "X": 726,
    "Y": 156,
    "Delta": null,
    "KeyCode": null
  },
  {
    "Type": "MouseMove",
    "Time": 15421,
    "X": 723,
    "Y": 153,
    "Delta": null,
    "KeyCode": null
  },
  {
    "Type": "MouseMove",
    "Time": 15444,
    "X": 720,
    "Y": 153,
    "Delta": null,
    "KeyCode": null
  },
  {
    "Type": "MouseMove",
    "Time": 15466,
    "X": 717,
    "Y": 150,
    "Delta": null,
    "KeyCode": null
  },
  {
    "Type": "MouseMove",
    "Time": 15492,
    "X": 714,
    "Y": 147,
    "Delta": null,
    "KeyCode": null
  },
  {
    "Type": "MouseMove",
    "Time": 15678,
    "X": 714,
    "Y": 144,
    "Delta": null,
    "KeyCode": null
  },
  {
    "Type": "MouseMove",
    "Time": 15744,
    "X": 714,
    "Y": 141,
    "Delta": null,
    "KeyCode": null
  },
  {
    "Type": "KeyDown",
    "Time": 15874,
    "X": null,
    "Y": null,
    "Delta": null,
    "KeyCode": 49
  },
  {
    "Type": "KeyUp",
    "Time": 15907,
    "X": null,
    "Y": null,
    "Delta": null,
    "KeyCode": 49
  },
  {
    "Type": "MouseMove",
    "Time": 16010,
    "X": 714,
    "Y": 138,
    "Delta": null,
    "KeyCode": null
  },
  {
    "Type": "MouseMove",
    "Time": 16029,
    "X": 714,
    "Y": 135,
    "Delta": null,
    "KeyCode": null
  },
  {
    "Type": "MouseMove",
    "Time": 16051,
    "X": 714,
    "Y": 126,
    "Delta": null,
    "KeyCode": null
  },
  {
    "Type": "MouseMove",
    "Time": 16072,
    "X": 714,
    "Y": 117,
    "Delta": null,
    "KeyCode": null
  },
  {
    "Type": "MouseMove",
    "Time": 16092,
    "X": 714,
    "Y": 111,
    "Delta": null,
    "KeyCode": null
  },
  {
    "Type": "MouseMove",
    "Time": 16114,
    "X": 714,
    "Y": 105,
    "Delta": null,
    "KeyCode": null
  },
  {
    "Type": "MouseMove",
    "Time": 16137,
    "X": 714,
    "Y": 99,
    "Delta": null,
    "KeyCode": null
  },
  {
    "Type": "MouseMove",
    "Time": 16156,
    "X": 714,
    "Y": 90,
    "Delta": null,
    "KeyCode": null
  },
  {
    "Type": "MouseMove",
    "Time": 16172,
    "X": 717,
    "Y": 84,
    "Delta": null,
    "KeyCode": null
  },
  {
    "Type": "MouseMove",
    "Time": 16193,
    "X": 717,
    "Y": 78,
    "Delta": null,
    "KeyCode": null
  },
  {
    "Type": "MouseMove",
    "Time": 16213,
    "X": 720,
    "Y": 69,
    "Delta": null,
    "KeyCode": null
  },
  {
    "Type": "MouseMove",
    "Time": 16236,
    "X": 720,
    "Y": 60,
    "Delta": null,
    "KeyCode": null
  },
  {
    "Type": "MouseMove",
    "Time": 16258,
    "X": 720,
    "Y": 54,
    "Delta": null,
    "KeyCode": null
  },
  {
    "Type": "MouseMove",
    "Time": 16259,
    "X": 717,
    "Y": 51,
    "Delta": null,
    "KeyCode": null
  },
  {
    "Type": "MouseMove",
    "Time": 16279,
    "X": 717,
    "Y": 48,
    "Delta": null,
    "KeyCode": null
  },
  {
    "Type": "MouseMove",
    "Time": 16299,
    "X": 714,
    "Y": 39,
    "Delta": null,
    "KeyCode": null
  },
  {
    "Type": "MouseMove",
    "Time": 16321,
    "X": 714,
    "Y": 36,
    "Delta": null,
    "KeyCode": null
  },
  {
    "Type": "MouseMove",
    "Time": 16322,
    "X": 714,
    "Y": 33,
    "Delta": null,
    "KeyCode": null
  },
  {
    "Type": "MouseMove",
    "Time": 16330,
    "X": 714,
    "Y": 30,
    "Delta": null,
    "KeyCode": null
  },
  {
    "Type": "MouseMove",
    "Time": 16354,
    "X": 714,
    "Y": 27,
    "Delta": null,
    "KeyCode": null
  },
  {
    "Type": "MouseMove",
    "Time": 16375,
    "X": 714,
    "Y": 24,
    "Delta": null,
    "KeyCode": null
  },
  {
    "Type": "MouseMove",
    "Time": 16396,
    "X": 714,
    "Y": 21,
    "Delta": null,
    "KeyCode": null
  },
  {
    "Type": "MouseMove",
    "Time": 16437,
    "X": 714,
    "Y": 18,
    "Delta": null,
    "KeyCode": null
  },
  {
    "Type": "MouseMove",
    "Time": 16453,
    "X": 717,
    "Y": 18,
    "Delta": null,
    "KeyCode": null
  },
  {
    "Type": "MouseMove",
    "Time": 89817,
    "X": 327,
    "Y": 594,
    "Delta": null,
    "KeyCode": null
  },
  {
    "Type": "MouseMove",
    "Time": 89836,
    "X": 333,
    "Y": 591,
    "Delta": null,
    "KeyCode": null
  },
  {
    "Type": "MouseMove",
    "Time": 89854,
    "X": 351,
    "Y": 582,
    "Delta": null,
    "KeyCode": null
  },
  {
    "Type": "MouseMove",
    "Time": 89877,
    "X": 366,
    "Y": 576,
    "Delta": null,
    "KeyCode": null
  },
  {
    "Type": "MouseMove",
    "Time": 89899,
    "X": 393,
    "Y": 564,
    "Delta": null,
    "KeyCode": null
  },
  {
    "Type": "MouseMove",
    "Time": 89921,
    "X": 420,
    "Y": 552,
    "Delta": null,
    "KeyCode": null
  },
  {
    "Type": "MouseMove",
    "Time": 89943,
    "X": 426,
    "Y": 549,
    "Delta": null,
    "KeyCode": null
  },
  {
    "Type": "MouseMove",
    "Time": 89944,
    "X": 447,
    "Y": 537,
    "Delta": null,
    "KeyCode": null
  },
  {
    "Type": "MouseMove",
    "Time": 89962,
    "X": 495,
    "Y": 516,
    "Delta": null,
    "KeyCode": null
  },
  {
    "Type": "MouseMove",
    "Time": 89983,
    "X": 525,
    "Y": 501,
    "Delta": null,
    "KeyCode": null
  },
  {
    "Type": "MouseMove",
    "Time": 90004,
    "X": 579,
    "Y": 480,
    "Delta": null,
    "KeyCode": null
  },
  {
    "Type": "MouseMove",
    "Time": 90025,
    "X": 633,
    "Y": 456,
    "Delta": null,
    "KeyCode": null
  },
  {
    "Type": "MouseMove",
    "Time": 90047,
    "X": 669,
    "Y": 441,
    "Delta": null,
    "KeyCode": null
  },
  {
    "Type": "MouseMove",
    "Time": 90067,
    "X": 723,
    "Y": 411,
    "Delta": null,
    "KeyCode": null
  },
  {
    "Type": "MouseMove",
    "Time": 90089,
    "X": 765,
    "Y": 390,
    "Delta": null,
    "KeyCode": null
  },
  {
    "Type": "MouseMove",
    "Time": 90109,
    "X": 792,
    "Y": 375,
    "Delta": null,
    "KeyCode": null
  },
  {
    "Type": "MouseMove",
    "Time": 90130,
    "X": 819,
    "Y": 360,
    "Delta": null,
    "KeyCode": null
  },
  {
    "Type": "MouseMove",
    "Time": 90131,
    "X": 828,
    "Y": 354,
    "Delta": null,
    "KeyCode": null
  },
  {
    "Type": "MouseMove",
    "Time": 90151,
    "X": 849,
    "Y": 342,
    "Delta": null,
    "KeyCode": null
  },
  {
    "Type": "MouseMove",
    "Time": 90170,
    "X": 876,
    "Y": 324,
    "Delta": null,
    "KeyCode": null
  },
  {
    "Type": "MouseMove",
    "Time": 90191,
    "X": 885,
    "Y": 318,
    "Delta": null,
    "KeyCode": null
  },
  {
    "Type": "MouseMove",
    "Time": 90192,
    "X": 903,
    "Y": 306,
    "Delta": null,
    "KeyCode": null
  },
  {
    "Type": "MouseMove",
    "Time": 90212,
    "X": 918,
    "Y": 297,
    "Delta": null,
    "KeyCode": null
  },
  {
    "Type": "MouseMove",
    "Time": 90231,
    "X": 927,
    "Y": 288,
    "Delta": null,
    "KeyCode": null
  },
  {
    "Type": "MouseMove",
    "Time": 90250,
    "X": 936,
    "Y": 276,
    "Delta": null,
    "KeyCode": null
  },
  {
    "Type": "MouseMove",
    "Time": 90273,
    "X": 945,
    "Y": 270,
    "Delta": null,
    "KeyCode": null
  },
  {
    "Type": "MouseMove",
    "Time": 90294,
    "X": 957,
    "Y": 258,
    "Delta": null,
    "KeyCode": null
  },
  {
    "Type": "MouseMove",
    "Time": 90317,
    "X": 972,
    "Y": 243,
    "Delta": null,
    "KeyCode": null
  },
  {
    "Type": "MouseMove",
    "Time": 90340,
    "X": 984,
    "Y": 234,
    "Delta": null,
    "KeyCode": null
  },
  {
    "Type": "MouseMove",
    "Time": 90359,
    "X": 990,
    "Y": 228,
    "Delta": null,
    "KeyCode": null
  },
  {
    "Type": "MouseMove",
    "Time": 90378,
    "X": 1002,
    "Y": 216,
    "Delta": null,
    "KeyCode": null
  },
  {
    "Type": "MouseMove",
    "Time": 90399,
    "X": 1008,
    "Y": 213,
    "Delta": null,
    "KeyCode": null
  },
  {
    "Type": "MouseMove",
    "Time": 90421,
    "X": 1014,
    "Y": 210,
    "Delta": null,
    "KeyCode": null
  },
  {
    "Type": "MouseMove",
    "Time": 90443,
    "X": 1020,
    "Y": 207,
    "Delta": null,
    "KeyCode": null
  },
  {
    "Type": "MouseMove",
    "Time": 90464,
    "X": 1032,
    "Y": 198,
    "Delta": null,
    "KeyCode": null
  },
  {
    "Type": "MouseMove",
    "Time": 90485,
    "X": 1044,
    "Y": 192,
    "Delta": null,
    "KeyCode": null
  },
  {
    "Type": "MouseMove",
    "Time": 90505,
    "X": 1047,
    "Y": 189,
    "Delta": null,
    "KeyCode": null
  },
  {
    "Type": "MouseMove",
    "Time": 90566,
    "X": 1050,
    "Y": 189,
    "Delta": null,
    "KeyCode": null
  },
  {
    "Type": "MouseMove",
    "Time": 90585,
    "X": 1053,
    "Y": 186,
    "Delta": null,
    "KeyCode": null
  },
  {
    "Type": "MouseMove",
    "Time": 90601,
    "X": 1056,
    "Y": 183,
    "Delta": null,
    "KeyCode": null
  },
  {
    "Type": "MouseMove",
    "Time": 90621,
    "X": 1056,
    "Y": 180,
    "Delta": null,
    "KeyCode": null
  },
  {
    "Type": "MouseMove",
    "Time": 90644,
    "X": 1059,
    "Y": 177,
    "Delta": null,
    "KeyCode": null
  },
  {
    "Type": "MouseMove",
    "Time": 90669,
    "X": 1062,
    "Y": 174,
    "Delta": null,
    "KeyCode": null
  },
  {
    "Type": "MouseMove",
    "Time": 90681,
    "X": 1062,
    "Y": 171,
    "Delta": null,
    "KeyCode": null
  },
  {
    "Type": "MouseMove",
    "Time": 90701,
    "X": 1065,
    "Y": 168,
    "Delta": null,
    "KeyCode": null
  },
  {
    "Type": "MouseMove",
    "Time": 90716,
    "X": 1068,
    "Y": 165,
    "Delta": null,
    "KeyCode": null
  },
  {
    "Type": "MouseMove",
    "Time": 90776,
    "X": 1068,
    "Y": 162,
    "Delta": null,
    "KeyCode": null
  },
  {
    "Type": "MouseMove",
    "Time": 90843,
    "X": 1071,
    "Y": 162,
    "Delta": null,
    "KeyCode": null
  },
  {
    "Type": "MouseMove",
    "Time": 90868,
    "X": 1074,
    "Y": 162,
    "Delta": null,
    "KeyCode": null
  }
]