[
  {
    "Type": "KeyUp",
    "Time": 95,
    "X": null,
    "Y": null,
    "Delta": null,
    "KeyCode": 35
  },
  {
    "Type": "MouseMove",
    "Time": 343,
    "X": 576,
    "Y": 609,
    "Delta": null,
    "KeyCode": null
  },
  {
    "Type": "MouseMove",
    "Time": 348,
    "X": 576,
    "Y": 606,
    "Delta": null,
    "KeyCode": null
  },
  {
    "Type": "MouseMove",
    "Time": 374,
    "X": 567,
    "Y": 594,
    "Delta": null,
    "KeyCode": null
  },
  {
    "Type": "MouseMove",
    "Time": 397,
    "X": 558,
    "Y": 573,
    "Delta": null,
    "KeyCode": null
  },
  {
    "Type": "MouseMove",
    "Time": 423,
    "X": 543,
    "Y": 549,
    "Delta": null,
    "KeyCode": null
  },
  {
    "Type": "MouseMove",
    "Time": 446,
    "X": 531,
    "Y": 519,
    "Delta": null,
    "KeyCode": null
  },
  {
    "Type": "MouseMove",
    "Time": 470,
    "X": 522,
    "Y": 495,
    "Delta": null,
    "KeyCode": null
  },
  {
    "Type": "MouseMove",
    "Time": 493,
    "X": 510,
    "Y": 465,
    "Delta": null,
    "KeyCode": null
  },
  {
    "Type": "MouseMove",
    "Time": 518,
    "X": 501,
    "Y": 432,
    "Delta": null,
    "KeyCode": null
  },
  {
    "Type": "MouseMove",
    "Time": 542,
    "X": 495,
    "Y": 417,
    "Delta": null,
    "KeyCode": null
  },
  {
    "Type": "MouseMove",
    "Time": 543,
    "X": 489,
    "Y": 408,
    "Delta": null,
    "KeyCode": null
  },
  {
    "Type": "MouseMove",
    "Time": 566,
    "X": 480,
    "Y": 387,
    "Delta": null,
    "KeyCode": null
  },
  {
    "Type": "MouseMove",
    "Time": 591,
    "X": 474,
    "Y": 369,
    "Delta": null,
    "KeyCode": null
  },
  {
    "Type": "MouseMove",
    "Time": 598,
    "X": 474,
    "Y": 363,
    "Delta": null,
    "KeyCode": null
  },
  {
    "Type": "MouseMove",
    "Time": 622,
    "X": 474,
    "Y": 351,
    "Delta": null,
    "KeyCode": null
  },
  {
    "Type": "MouseMove",
    "Time": 644,
    "X": 474,
    "Y": 339,
    "Delta": null,
    "KeyCode": null
  },
  {
    "Type": "MouseMove",
    "Time": 669,
    "X": 471,
    "Y": 324,
    "Delta": null,
    "KeyCode": null
  },
  {
    "Type": "MouseMove",
    "Time": 693,
    "X": 471,
    "Y": 321,
    "Delta": null,
    "KeyCode": null
  },
  {
    "Type": "MouseMove",
    "Time": 695,
    "X": 468,
    "Y": 312,
    "Delta": null,
    "KeyCode": null
  },
  {
    "Type": "MouseMove",
    "Time": 714,
    "X": 465,
    "Y": 303,
    "Delta": null,
    "KeyCode": null
  },
  {
    "Type": "MouseMove",
    "Time": 738,
    "X": 465,
    "Y": 294,
    "Delta": null,
    "KeyCode": null
  },
  {
    "Type": "MouseMove",
    "Time": 761,
    "X": 462,
    "Y": 288,
    "Delta": null,
    "KeyCode": null
  },
  {
    "Type": "MouseMove",
    "Time": 788,
    "X": 462,
    "Y": 282,
    "Delta": null,
    "KeyCode": null
  },
  {
    "Type": "MouseMove",
    "Time": 812,
    "X": 459,
    "Y": 276,
    "Delta": null,
    "KeyCode": null
  },
  {
    "Type": "MouseMove",
    "Time": 813,
    "X": 459,
    "Y": 273,
    "Delta": null,
    "KeyCode": null
  },
  {
    "Type": "MouseMove",
    "Time": 843,
    "X": 459,
    "Y": 267,
    "Delta": null,
    "KeyCode": null
  },
  {
    "Type": "MouseMove",
    "Time": 848,
    "X": 459,
    "Y": 264,
    "Delta": null,
    "KeyCode": null
  },
  {
    "Type": "MouseMove",
    "Time": 873,
    "X": 459,
    "Y": 258,
    "Delta": null,
    "KeyCode": null
  },
  {
    "Type": "MouseMove",
    "Time": 880,
    "X": 459,
    "Y": 255,
    "Delta": null,
    "KeyCode": null
  },
  {
    "Type": "MouseMove",
    "Time": 906,
    "X": 456,
    "Y": 249,
    "Delta": null,
    "KeyCode": null
  },
  {
    "Type": "MouseMove",
    "Time": 929,
    "X": 456,
    "Y": 243,
    "Delta": null,
    "KeyCode": null
  },
  {
    "Type": "MouseMove",
    "Time": 944,
    "X": 456,
    "Y": 240,
    "Delta": null,
    "KeyCode": null
  },
  {
    "Type": "MouseMove",
    "Time": 965,
    "X": 456,
    "Y": 237,
    "Delta": null,
    "KeyCode": null
  },
  {
    "Type": "MouseMove",
    "Time": 967,
    "X": 456,
    "Y": 234,
    "Delta": null,
    "KeyCode": null
  },
  {
    "Type": "MouseMove",
    "Time": 999,
    "X": 456,
    "Y": 231,
    "Delta": null,
    "KeyCode": null
  },
  {
    "Type": "MouseMove",
    "Time": 1029,
    "X": 456,
    "Y": 228,
    "Delta": null,
    "KeyCode": null
  },
  {
    "Type": "MouseMove",
    "Time": 1054,
    "X": 453,
    "Y": 228,
    "Delta": null,
    "KeyCode": null
  },
  {
    "Type": "MouseMove",
    "Time": 1080,
    "X": 453,
    "Y": 225,
    "Delta": null,
    "KeyCode": null
  },
  {
    "Type": "MouseMove",
    "Time": 1108,
    "X": 453,
    "Y": 219,
    "Delta": null,
    "KeyCode": null
  },
  {
    "Type": "MouseMove",
    "Time": 1138,
    "X": 450,
    "Y": 216,
    "Delta": null,
    "KeyCode": null
  },
  {
    "Type": "MouseMove",
    "Time": 1163,
    "X": 450,
    "Y": 213,
    "Delta": null,
    "KeyCode": null
  },
  {
    "Type": "MouseMove",
    "Time": 1186,
    "X": 450,
    "Y": 210,
    "Delta": null,
    "KeyCode": null
  },
  {
    "Type": "MouseMove",
    "Time": 1209,
    "X": 447,
    "Y": 210,
    "Delta": null,
    "KeyCode": null
  },
  {
    "Type": "MouseMove",
    "Time": 1257,
    "X": 444,
    "Y": 210,
    "Delta": null,
    "KeyCode": null
  },
  {
    "Type": "MouseMove",
    "Time": 1282,
    "X": 432,
    "Y": 204,
    "Delta": null,
    "KeyCode": null
  },
  {
    "Type": "MouseMove",
    "Time": 1304,
    "X": 426,
    "Y": 204,
    "Delta": null,
    "KeyCode": null
  },
  {
    "Type": "MouseMove",
    "Time": 1305,
    "X": 420,
    "Y": 201,
    "Delta": null,
    "KeyCode": null
  },
  {
    "Type": "MouseMove",
    "Time": 1326,
    "X": 402,
    "Y": 198,
    "Delta": null,
    "KeyCode": null
  },
  {
    "Type": "MouseMove",
    "Time": 1350,
    "X": 390,
    "Y": 195,
    "Delta": null,
    "KeyCode": null
  },
  {
    "Type": "MouseMove",
    "Time": 1373,
    "X": 384,
    "Y": 192,
    "Delta": null,
    "KeyCode": null
  },
  {
    "Type": "MouseMove",
    "Time": 1378,
    "X": 381,
    "Y": 192,
    "Delta": null,
    "KeyCode": null
  },
  {
    "Type": "MouseMove",
    "Time": 1401,
    "X": 378,
    "Y": 189,
    "Delta": null,
    "KeyCode": null
  },
  {
    "Type": "MouseMove",
    "Time": 1423,
    "X": 372,
    "Y": 186,
    "Delta": null,
    "KeyCode": null
  },
  {
    "Type": "MouseMove",
    "Time": 1428,
    "X": 369,
    "Y": 186,
    "Delta": null,
    "KeyCode": null
  },
  {
    "Type": "MouseMove",
    "Time": 1455,
    "X": 363,
    "Y": 183,
    "Delta": null,
    "KeyCode": null
  },
  {
    "Type": "MouseMove",
    "Time": 1477,
    "X": 360,
    "Y": 180,
    "Delta": null,
    "KeyCode": null
  },
  {
    "Type": "MouseMove",
    "Time": 1500,
    "X": 354,
    "Y": 177,
    "Delta": null,
    "KeyCode": null
  },
  {
    "Type": "MouseMove",
    "Time": 1508,
    "X": 351,
    "Y": 174,
    "Delta": null,
    "KeyCode": null
  },
  {
    "Type": "MouseMove",
    "Time": 1536,
    "X": 342,
    "Y": 168,
    "Delta": null,
    "KeyCode": null
  },
  {
    "Type": "MouseMove",
    "Time": 1539,
    "X": 342,
    "Y": 165,
    "Delta": null,
    "KeyCode": null
  },
  {
    "Type": "MouseMove",
    "Time": 1568,
    "X": 333,
    "Y": 162,
    "Delta": null,
    "KeyCode": null
  },
  {
    "Type": "MouseMove",
    "Time": 1590,
    "X": 327,
    "Y": 159,
    "Delta": null,
    "KeyCode": null
  },
  {
    "Type": "MouseMove",
    "Time": 1618,
    "X": 324,
    "Y": 159,
    "Delta": null,
    "KeyCode": null
  },
  {
    "Type": "MouseMove",
    "Time": 1641,
    "X": 321,
    "Y": 156,
    "Delta": null,
    "KeyCode": null
  },
  {
    "Type": "MouseMove",
    "Time": 1667,
    "X": 318,
    "Y": 156,
    "Delta": null,
    "KeyCode": null
  },
  {
    "Type": "MouseMove",
    "Time": 1668,
    "X": 315,
    "Y": 156,
    "Delta": null,
    "KeyCode": null
  },
  {
    "Type": "MouseMove",
    "Time": 1698,
    "X": 309,
    "Y": 153,
    "Delta": null,
    "KeyCode": null
  },
  {
    "Type": "MouseMove",
    "Time": 1772,
    "X": 306,
    "Y": 153,
    "Delta": null,
    "KeyCode": null
  },
  {
    "Type": "MouseMove",
    "Time": 1973,
    "X": 306,
    "Y": 150,
    "Delta": null,
    "KeyCode": null
  },
  {
    "Type": "MouseMove",
    "Time": 1998,
    "X": 303,
    "Y": 150,
    "Delta": null,
    "KeyCode": null
  },
  {
    "Type": "DragStart",
    "Time": 2136,
    "X": 303,
    "Y": 150,
    "Delta": null,
    "KeyCode": null
  },
  {
    "Type": "DragEnd",
    "Time": 2215,
    "X": 303,
    "Y": 150,
    "Delta": null,
    "KeyCode": null
  },
  {
    "Type": "MouseMove",
    "Time": 2474,
    "X": 300,
    "Y": 153,
    "Delta": null,
    "KeyCode": null
  },
  {
    "Type": "MouseMove",
    "Time": 2475,
    "X": 300,
    "Y": 156,
    "Delta": null,
    "KeyCode": null
  },
  {
    "Type": "MouseMove",
    "Time": 2499,
    "X": 288,
    "Y": 168,
    "Delta": null,
    "KeyCode": null
  },
  {
    "Type": "MouseMove",
    "Time": 2506,
    "X": 285,
    "Y": 174,
    "Delta": null,
    "KeyCode": null
  },
  {
    "Type": "MouseMove",
    "Time": 2513,
    "X": 282,
    "Y": 180,
    "Delta": null,
    "KeyCode": null
  },
  {
    "Type": "MouseMove",
    "Time": 2521,
    "X": 276,
    "Y": 186,
    "Delta": null,
    "KeyCode": null
  },
  {
    "Type": "MouseMove",
    "Time": 2529,
    "X": 270,
    "Y": 192,
    "Delta": null,
    "KeyCode": null
  },
  {
    "Type": "MouseMove",
    "Time": 2558,
    "X": 252,
    "Y": 210,
    "Delta": null,
    "KeyCode": null
  },
  {
    "Type": "MouseMove",
    "Time": 2561,
    "X": 246,
    "Y": 216,
    "Delta": null,
    "KeyCode": null
  },
  {
    "Type": "MouseMove",
    "Time": 2591,
    "X": 237,
    "Y": 228,
    "Delta": null,
    "KeyCode": null
  },
  {
    "Type": "MouseMove",
    "Time": 2617,
    "X": 219,
    "Y": 249,
    "Delta": null,
    "KeyCode": null
  },
  {
    "Type": "MouseMove",
    "Time": 2640,
    "X": 204,
    "Y": 270,
    "Delta": null,
    "KeyCode": null
  },
  {
    "Type": "MouseMove",
    "Time": 2666,
    "X": 195,
    "Y": 282,
    "Delta": null,
    "KeyCode": null
  },
  {
    "Type": "MouseMove",
    "Time": 2689,
    "X": 189,
    "Y": 288,
    "Delta": null,
    "KeyCode": null
  },
  {
    "Type": "MouseMove",
    "Time": 2715,
    "X": 180,
    "Y": 300,
    "Delta": null,
    "KeyCode": null
  },
  {
    "Type": "MouseMove",
    "Time": 2738,
    "X": 177,
    "Y": 309,
    "Delta": null,
    "KeyCode": null
  },
  {
    "Type": "MouseMove",
    "Time": 2739,
    "X": 177,
    "Y": 312,
    "Delta": null,
    "KeyCode": null
  },
  {
    "Type": "MouseMove",
    "Time": 2765,
    "X": 174,
    "Y": 318,
    "Delta": null,
    "KeyCode": null
  },
  {
    "Type": "MouseMove",
    "Time": 2788,
    "X": 174,
    "Y": 321,
    "Delta": null,
    "KeyCode": null
  },
  {
    "Type": "MouseMove",
    "Time": 2810,
    "X": 174,
    "Y": 324,
    "Delta": null,
    "KeyCode": null
  },
  {
    "Type": "MouseMove",
    "Time": 2832,
    "X": 171,
    "Y": 327,
    "Delta": null,
    "KeyCode": null
  },
  {
    "Type": "MouseMove",
    "Time": 2835,
    "X": 168,
    "Y": 327,
    "Delta": null,
    "KeyCode": null
  },
  {
    "Type": "MouseMove",
    "Time": 2868,
    "X": 168,
    "Y": 333,
    "Delta": null,
    "KeyCode": null
  },
  {
    "Type": "MouseMove",
    "Time": 2896,
    "X": 165,
    "Y": 339,
    "Delta": null,
    "KeyCode": null
  },
  {
    "Type": "MouseMove",
    "Time": 2926,
    "X": 162,
    "Y": 345,
    "Delta": null,
    "KeyCode": null
  },
  {
    "Type": "MouseMove",
    "Time": 2934,
    "X": 162,
    "Y": 348,
    "Delta": null,
    "KeyCode": null
  },
  {
    "Type": "MouseMove",
    "Time": 2959,
    "X": 159,
    "Y": 351,
    "Delta": null,
    "KeyCode": null
  },
  {
    "Type": "MouseMove",
    "Time": 2980,
    "X": 156,
    "Y": 354,
    "Delta": null,
    "KeyCode": null
  },
  {
    "Type": "MouseMove",
    "Time": 3081,
    "X": 156,
    "Y": 357,
    "Delta": null,
    "KeyCode": null
  },
  {
    "Type": "MouseMove",
    "Time": 3132,
    "X": 153,
    "Y": 360,
    "Delta": null,
    "KeyCode": null
  },
  {
    "Type": "MouseMove",
    "Time": 3156,
    "X": 150,
    "Y": 366,
    "Delta": null,
    "KeyCode": null
  },
  {
    "Type": "MouseMove",
    "Time": 3179,
    "X": 147,
    "Y": 366,
    "Delta": null,
    "KeyCode": null
  },
  {
    "Type": "MouseMove",
    "Time": 3203,
    "X": 144,
    "Y": 369,
    "Delta": null,
    "KeyCode": null
  },
  {
    "Type": "MouseMove",
    "Time": 3226,
    "X": 144,
    "Y": 372,
    "Delta": null,
    "KeyCode": null
  },
  {
    "Type": "MouseMove",
    "Time": 3249,
    "X": 141,
    "Y": 375,
    "Delta": null,
    "KeyCode": null
  },
  {
    "Type": "MouseMove",
    "Time": 3273,
    "X": 141,
    "Y": 378,
    "Delta": null,
    "KeyCode": null
  },
  {
    "Type": "MouseMove",
    "Time": 3297,
    "X": 138,
    "Y": 378,
    "Delta": null,
    "KeyCode": null
  },
  {
    "Type": "MouseMove",
    "Time": 3520,
    "X": 138,
    "Y": 381,
    "Delta": null,
    "KeyCode": null
  },
  {
    "Type": "MouseMove",
    "Time": 3544,
    "X": 135,
    "Y": 384,
    "Delta": null,
    "KeyCode": null
  },
  {
    "Type": "MouseMove",
    "Time": 3567,
    "X": 129,
    "Y": 390,
    "Delta": null,
    "KeyCode": null
  },
  {
    "Type": "MouseMove",
    "Time": 3570,
    "X": 126,
    "Y": 390,
    "Delta": null,
    "KeyCode": null
  },
  {
    "Type": "MouseMove",
    "Time": 3595,
    "X": 123,
    "Y": 396,
    "Delta": null,
    "KeyCode": null
  },
  {
    "Type": "MouseMove",
    "Time": 3617,
    "X": 120,
    "Y": 396,
    "Delta": null,
    "KeyCode": null
  },
  {
    "Type": "MouseMove",
    "Time": 3639,
    "X": 120,
    "Y": 399,
    "Delta": null,
    "KeyCode": null
  },
  {
    "Type": "MouseMove",
    "Time": 3797,
    "X": 120,
    "Y": 402,
    "Delta": null,
    "KeyCode": null
  },
  {
    "Type": "MouseMove",
    "Time": 4191,
    "X": 120,
    "Y": 399,
    "Delta": null,
    "KeyCode": null
  },
  {
    "Type": "MouseMove",
    "Time": 4214,
    "X": 120,
    "Y": 396,
    "Delta": null,
    "KeyCode": null
  },
  {
    "Type": "MouseMove",
    "Time": 4261,
    "X": 120,
    "Y": 393,
    "Delta": null,
    "KeyCode": null
  },
  {
    "Type": "MouseMove",
    "Time": 4285,
    "X": 120,
    "Y": 390,
    "Delta": null,
    "KeyCode": null
  },
  {
    "Type": "MouseMove",
    "Time": 4485,
    "X": 120,
    "Y": 387,
    "Delta": null,
    "KeyCode": null
  },
  {
    "Type": "MouseMove",
    "Time": 4507,
    "X": 120,
    "Y": 384,
    "Delta": null,
    "KeyCode": null
  },
  {
    "Type": "DragStart",
    "Time": 4847,
    "X": 120,
    "Y": 384,
    "Delta": null,
    "KeyCode": null
  },
  {
    "Type": "DragEnd",
    "Time": 4937,
    "X": 120,
    "Y": 384,
    "Delta": null,
    "KeyCode": null
  },
  {
    "Type": "MouseMove",
    "Time": 5842,
    "X": 129,
    "Y": 384,
    "Delta": null,
    "KeyCode": null
  },
  {
    "Type": "MouseMove",
    "Time": 5850,
    "X": 138,
    "Y": 387,
    "Delta": null,
    "KeyCode": null
  },
  {
    "Type": "MouseMove",
    "Time": 5875,
    "X": 189,
    "Y": 390,
    "Delta": null,
    "KeyCode": null
  },
  {
    "Type": "MouseMove",
    "Time": 5882,
    "X": 207,
    "Y": 390,
    "Delta": null,
    "KeyCode": null
  },
  {
    "Type": "MouseMove",
    "Time": 5907,
    "X": 291,
    "Y": 393,
    "Delta": null,
    "KeyCode": null
  },
  {
    "Type": "MouseMove",
    "Time": 5930,
    "X": 387,
    "Y": 393,
    "Delta": null,
    "KeyCode": null
  },
  {
    "Type": "MouseMove",
    "Time": 5954,
    "X": 507,
    "Y": 393,
    "Delta": null,
    "KeyCode": null
  },
  {
    "Type": "MouseMove",
    "Time": 5962,
    "X": 546,
    "Y": 390,
    "Delta": null,
    "KeyCode": null
  },
  {
    "Type": "MouseMove",
    "Time": 5969,
    "X": 579,
    "Y": 390,
    "Delta": null,
    "KeyCode": null
  },
  {
    "Type": "MouseMove",
    "Time": 5999,
    "X": 657,
    "Y": 390,
    "Delta": null,
    "KeyCode": null
  },
  {
    "Type": "MouseMove",
    "Time": 6021,
    "X": 708,
    "Y": 393,
    "Delta": null,
    "KeyCode": null
  },
  {
    "Type": "MouseMove",
    "Time": 6026,
    "X": 720,
    "Y": 396,
    "Delta": null,
    "KeyCode": null
  },
  {
    "Type": "MouseMove",
    "Time": 6034,
    "X": 732,
    "Y": 396,
    "Delta": null,
    "KeyCode": null
  },
  {
    "Type": "MouseMove",
    "Time": 6061,
    "X": 741,
    "Y": 402,
    "Delta": null,
    "KeyCode": null
  },
  {
    "Type": "MouseMove",
    "Time": 6085,
    "X": 747,
    "Y": 405,
    "Delta": null,
    "KeyCode": null
  },
  {
    "Type": "MouseMove",
    "Time": 6092,
    "X": 750,
    "Y": 405,
    "Delta": null,
    "KeyCode": null
  },
  {
    "Type": "MouseMove",
    "Time": 6125,
    "X": 750,
    "Y": 408,
    "Delta": null,
    "KeyCode": null
  },
  {
    "Type": "MouseMove",
    "Time": 6157,
    "X": 759,
    "Y": 414,
    "Delta": null,
    "KeyCode": null
  },
  {
    "Type": "MouseMove",
    "Time": 6181,
    "X": 786,
    "Y": 420,
    "Delta": null,
    "KeyCode": null
  },
  {
    "Type": "MouseMove",
    "Time": 6205,
    "X": 810,
    "Y": 423,
    "Delta": null,
    "KeyCode": null
  },
  {
    "Type": "MouseMove",
    "Time": 6226,
    "X": 828,
    "Y": 423,
    "Delta": null,
    "KeyCode": null
  },
  {
    "Type": "MouseMove",
    "Time": 6253,
    "X": 846,
    "Y": 426,
    "Delta": null,
    "KeyCode": null
  },
  {
    "Type": "MouseMove",
    "Time": 6260,
    "X": 855,
    "Y": 426,
    "Delta": null,
    "KeyCode": null
  },
  {
    "Type": "MouseMove",
    "Time": 6286,
    "X": 876,
    "Y": 426,
    "Delta": null,
    "KeyCode": null
  },
  {
    "Type": "MouseMove",
    "Time": 6309,
    "X": 885,
    "Y": 426,
    "Delta": null,
    "KeyCode": null
  },
  {
    "Type": "MouseMove",
    "Time": 6384,
    "X": 894,
    "Y": 426,
    "Delta": null,
    "KeyCode": null
  },
  {
    "Type": "MouseMove",
    "Time": 6411,
    "X": 903,
    "Y": 426,
    "Delta": null,
    "KeyCode": null
  },
  {
    "Type": "MouseMove",
    "Time": 6470,
    "X": 903,
    "Y": 420,
    "Delta": null,
    "KeyCode": null
  },
  {
    "Type": "MouseMove",
    "Time": 6478,
    "X": 906,
    "Y": 420,
    "Delta": null,
    "KeyCode": null
  },
  {
    "Type": "DragStart",
    "Time": 6615,
    "X": 906,
    "Y": 420,
    "Delta": null,
    "KeyCode": null
  },
  {
    "Type": "DragEnd",
    "Time": 6681,
    "X": 906,
    "Y": 420,
    "Delta": null,
    "KeyCode": null
  },
  {
    "Type": "MouseMove",
    "Time": 6904,
    "X": 903,
    "Y": 420,
    "Delta": null,
    "KeyCode": null
  },
  {
    "Type": "MouseMove",
    "Time": 6961,
    "X": 900,
    "Y": 420,
    "Delta": null,
    "KeyCode": null
  },
  {
    "Type": "MouseMove",
    "Time": 7029,
    "X": 897,
    "Y": 423,
    "Delta": null,
    "KeyCode": null
  },
  {
    "Type": "MouseMove",
    "Time": 7051,
    "X": 894,
    "Y": 426,
    "Delta": null,
    "KeyCode": null
  },
  {
    "Type": "DragStart",
    "Time": 7144,
    "X": 894,
    "Y": 426,
    "Delta": null,
    "KeyCode": null
  },
  {
    "Type": "DragEnd",
    "Time": 7209,
    "X": 894,
    "Y": 426,
    "Delta": null,
    "KeyCode": null
  },
  {
    "Type": "MouseMove",
    "Time": 7646,
    "X": 894,
    "Y": 429,
    "Delta": null,
    "KeyCode": null
  },
  {
    "Type": "DragStart",
    "Time": 8256,
    "X": 894,
    "Y": 429,
    "Delta": null,
    "KeyCode": null
  },
  {
    "Type": "DragEnd",
    "Time": 8331,
    "X": 894,
    "Y": 429,
    "Delta": null,
    "KeyCode": null
  },
  {
    "Type": "DragStart",
    "Time": 8721,
    "X": 894,
    "Y": 429,
    "Delta": null,
    "KeyCode": null
  },
  {
    "Type": "DragEnd",
    "Time": 8791,
    "X": 894,
    "Y": 429,
    "Delta": null,
    "KeyCode": null
  },
  {
    "Type": "MouseMove",
    "Time": 11755,
    "X": 891,
    "Y": 429,
    "Delta": null,
    "KeyCode": null
  },
  {
    "Type": "MouseMove",
    "Time": 11791,
    "X": 888,
    "Y": 429,
    "Delta": null,
    "KeyCode": null
  },
  {
    "Type": "MouseMove",
    "Time": 11961,
    "X": 876,
    "Y": 426,
    "Delta": null,
    "KeyCode": null
  },
  {
    "Type": "MouseMove",
    "Time": 11983,
    "X": 849,
    "Y": 420,
    "Delta": null,
    "KeyCode": null
  },
  {
    "Type": "MouseMove",
    "Time": 11988,
    "X": 840,
    "Y": 420,
    "Delta": null,
    "KeyCode": null
  },
  {
    "Type": "MouseMove",
    "Time": 12013,
    "X": 792,
    "Y": 414,
    "Delta": null,
    "KeyCode": null
  },
  {
    "Type": "MouseMove",
    "Time": 12037,
    "X": 750,
    "Y": 414,
    "Delta": null,
    "KeyCode": null
  },
  {
    "Type": "MouseMove",
    "Time": 12061,
    "X": 723,
    "Y": 414,
    "Delta": null,
    "KeyCode": null
  },
  {
    "Type": "MouseMove",
    "Time": 12086,
    "X": 699,
    "Y": 411,
    "Delta": null,
    "KeyCode": null
  },
  {
    "Type": "MouseMove",
    "Time": 12110,
    "X": 678,
    "Y": 408,
    "Delta": null,
    "KeyCode": null
  },
  {
    "Type": "MouseMove",
    "Time": 12116,
    "X": 669,
    "Y": 405,
    "Delta": null,
    "KeyCode": null
  },
  {
    "Type": "MouseMove",
    "Time": 12138,
    "X": 660,
    "Y": 405,
    "Delta": null,
    "KeyCode": null
  },
  {
    "Type": "MouseMove",
    "Time": 12160,
    "X": 651,
    "Y": 402,
    "Delta": null,
    "KeyCode": null
  },
  {
    "Type": "MouseMove",
    "Time": 12185,
    "X": 642,
    "Y": 396,
    "Delta": null,
    "KeyCode": null
  },
  {
    "Type": "MouseMove",
    "Time": 12209,
    "X": 630,
    "Y": 393,
    "Delta": null,
    "KeyCode": null
  },
  {
    "Type": "MouseMove",
    "Time": 12211,
    "X": 624,
    "Y": 390,
    "Delta": null,
    "KeyCode": null
  },
  {
    "Type": "MouseMove",
    "Time": 12236,
    "X": 621,
    "Y": 390,
    "Delta": null,
    "KeyCode": null
  },
  {
    "Type": "MouseMove",
    "Time": 12266,
    "X": 615,
    "Y": 387,
    "Delta": null,
    "KeyCode": null
  },
  {
    "Type": "MouseMove",
    "Time": 12290,
    "X": 612,
    "Y": 384,
    "Delta": null,
    "KeyCode": null
  },
  {
    "Type": "MouseMove",
    "Time": 12313,
    "X": 612,
    "Y": 381,
    "Delta": null,
    "KeyCode": null
  },
  {
    "Type": "MouseMove",
    "Time": 12341,
    "X": 609,
    "Y": 381,
    "Delta": null,
    "KeyCode": null
  },
  {
    "Type": "MouseMove",
    "Time": 12374,
    "X": 606,
    "Y": 378,
    "Delta": null,
    "KeyCode": null
  },
  {
    "Type": "MouseMove",
    "Time": 12398,
    "X": 600,
    "Y": 375,
    "Delta": null,
    "KeyCode": null
  },
  {
    "Type": "MouseMove",
    "Time": 12423,
    "X": 594,
    "Y": 372,
    "Delta": null,
    "KeyCode": null
  },
  {
    "Type": "MouseMove",
    "Time": 12448,
    "X": 594,
    "Y": 369,
    "Delta": null,
    "KeyCode": null
  },
  {
    "Type": "MouseMove",
    "Time": 12471,
    "X": 591,
    "Y": 366,
    "Delta": null,
    "KeyCode": null
  },
  {
    "Type": "MouseMove",
    "Time": 12495,
    "X": 588,
    "Y": 363,
    "Delta": null,
    "KeyCode": null
  },
  {
    "Type": "MouseMove",
    "Time": 12502,
    "X": 588,
    "Y": 360,
    "Delta": null,
    "KeyCode": null
  },
  {
    "Type": "MouseMove",
    "Time": 12509,
    "X": 585,
    "Y": 360,
    "Delta": null,
    "KeyCode": null
  },
  {
    "Type": "MouseMove",
    "Time": 12556,
    "X": 582,
    "Y": 357,
    "Delta": null,
    "KeyCode": null
  },
  {
    "Type": "MouseMove",
    "Time": 12826,
    "X": 585,
    "Y": 357,
    "Delta": null,
    "KeyCode": null
  },
  {
    "Type": "MouseMove",
    "Time": 12849,
    "X": 591,
    "Y": 363,
    "Delta": null,
    "KeyCode": null
  },
  {
    "Type": "MouseMove",
    "Time": 12873,
    "X": 603,
    "Y": 381,
    "Delta": null,
    "KeyCode": null
  },
  {
    "Type": "MouseMove",
    "Time": 12897,
    "X": 624,
    "Y": 408,
    "Delta": null,
    "KeyCode": null
  },
  {
    "Type": "MouseMove",
    "Time": 12920,
    "X": 651,
    "Y": 435,
    "Delta": null,
    "KeyCode": null
  },
  {
    "Type": "MouseMove",
    "Time": 12942,
    "X": 666,
    "Y": 453,
    "Delta": null,
    "KeyCode": null
  },
  {
    "Type": "MouseMove",
    "Time": 12945,
    "X": 669,
    "Y": 459,
    "Delta": null,
    "KeyCode": null
  },
  {
    "Type": "MouseMove",
    "Time": 12953,
    "X": 675,
    "Y": 465,
    "Delta": null,
    "KeyCode": null
  },
  {
    "Type": "MouseMove",
    "Time": 12982,
    "X": 690,
    "Y": 483,
    "Delta": null,
    "KeyCode": null
  },
  {
    "Type": "MouseMove",
    "Time": 12986,
    "X": 693,
    "Y": 486,
    "Delta": null,
    "KeyCode": null
  },
  {
    "Type": "MouseMove",
    "Time": 13012,
    "X": 702,
    "Y": 498,
    "Delta": null,
    "KeyCode": null
  },
  {
    "Type": "MouseMove",
    "Time": 13017,
    "X": 702,
    "Y": 501,
    "Delta": null,
    "KeyCode": null
  },
  {
    "Type": "MouseMove",
    "Time": 13044,
    "X": 708,
    "Y": 504,
    "Delta": null,
    "KeyCode": null
  },
  {
    "Type": "MouseMove",
    "Time": 13050,
    "X": 711,
    "Y": 507,
    "Delta": null,
    "KeyCode": null
  },
  {
    "Type": "MouseMove",
    "Time": 13075,
    "X": 717,
    "Y": 516,
    "Delta": null,
    "KeyCode": null
  },
  {
    "Type": "MouseMove",
    "Time": 13082,
    "X": 720,
    "Y": 516,
    "Delta": null,
    "KeyCode": null
  },
  {
    "Type": "MouseMove",
    "Time": 13108,
    "X": 723,
    "Y": 522,
    "Delta": null,
    "KeyCode": null
  },
  {
    "Type": "MouseMove",
    "Time": 13153,
    "X": 726,
    "Y": 528,
    "Delta": null,
    "KeyCode": null
  },
  {
    "Type": "MouseMove",
    "Time": 13155,
    "X": 729,
    "Y": 528,
    "Delta": null,
    "KeyCode": null
  },
  {
    "Type": "MouseMove",
    "Time": 13164,
    "X": 732,
    "Y": 531,
    "Delta": null,
    "KeyCode": null
  },
  {
    "Type": "MouseMove",
    "Time": 13188,
    "X": 735,
    "Y": 534,
    "Delta": null,
    "KeyCode": null
  },
  {
    "Type": "MouseMove",
    "Time": 13211,
    "X": 735,
    "Y": 537,
    "Delta": null,
    "KeyCode": null
  },
  {
    "Type": "MouseMove",
    "Time": 13235,
    "X": 738,
    "Y": 537,
    "Delta": null,
    "KeyCode": null
  },
  {
    "Type": "MouseMove",
    "Time": 13244,
    "X": 738,
    "Y": 540,
    "Delta": null,
    "KeyCode": null
  },
  {
    "Type": "MouseMove",
    "Time": 13293,
    "X": 744,
    "Y": 546,
    "Delta": null,
    "KeyCode": null
  },
  {
    "Type": "MouseMove",
    "Time": 13328,
    "X": 747,
    "Y": 549,
    "Delta": null,
    "KeyCode": null
  },
  {
    "Type": "MouseMove",
    "Time": 13366,
    "X": 750,
    "Y": 552,
    "Delta": null,
    "KeyCode": null
  },
  {
    "Type": "MouseMove",
    "Time": 13391,
    "X": 756,
    "Y": 552,
    "Delta": null,
    "KeyCode": null
  },
  {
    "Type": "DragStart",
    "Time": 13653,
    "X": 756,
    "Y": 552,
    "Delta": null,
    "KeyCode": null
  },
  {
    "Type": "DragEnd",
    "Time": 13712,
    "X": 756,
    "Y": 552,
    "Delta": null,
    "KeyCode": null
  },
  {
    "Type": "MouseMove",
    "Time": 13738,
    "X": 762,
    "Y": 552,
    "Delta": null,
    "KeyCode": null
  },
  {
    "Type": "MouseMove",
    "Time": 13739,
    "X": 768,
    "Y": 552,
    "Delta": null,
    "KeyCode": null
  },
  {
    "Type": "MouseMove",
    "Time": 13748,
    "X": 771,
    "Y": 552,
    "Delta": null,
    "KeyCode": null
  },
  {
    "Type": "MouseMove",
    "Time": 13756,
    "X": 777,
    "Y": 552,
    "Delta": null,
    "KeyCode": null
  },
  {
    "Type": "MouseMove",
    "Time": 13764,
    "X": 783,
    "Y": 552,
    "Delta": null,
    "KeyCode": null
  },
  {
    "Type": "MouseMove",
    "Time": 13792,
    "X": 798,
    "Y": 552,
    "Delta": null,
    "KeyCode": null
  },
  {
    "Type": "MouseMove",
    "Time": 13816,
    "X": 813,
    "Y": 549,
    "Delta": null,
    "KeyCode": null
  },
  {
    "Type": "MouseMove",
    "Time": 13838,
    "X": 828,
    "Y": 549,
    "Delta": null,
    "KeyCode": null
  },
  {
    "Type": "MouseMove",
    "Time": 13868,
    "X": 831,
    "Y": 549,
    "Delta": null,
    "KeyCode": null
  },
  {
    "Type": "MouseMove",
    "Time": 13893,
    "X": 834,
    "Y": 549,
    "Delta": null,
    "KeyCode": null
  },
  {
    "Type": "MouseMove",
    "Time": 14031,
    "X": 837,
    "Y": 549,
    "Delta": null,
    "KeyCode": null
  },
  {
    "Type": "MouseMove",
    "Time": 14063,
    "X": 840,
    "Y": 549,
    "Delta": null,
    "KeyCode": null
  },
  {
    "Type": "MouseMove",
    "Time": 14086,
    "X": 843,
    "Y": 549,
    "Delta": null,
    "KeyCode": null
  },
  {
    "Type": "DragStart",
    "Time": 14233,
    "X": 843,
    "Y": 549,
    "Delta": null,
    "KeyCode": null
  },
  {
    "Type": "DragEnd",
    "Time": 14319,
    "X": 843,
    "Y": 549,
    "Delta": null,
    "KeyCode": null
  },
  {
    "Type": "MouseMove",
    "Time": 14467,
    "X": 846,
    "Y": 546,
    "Delta": null,
    "KeyCode": null
  },
  {
    "Type": "MouseMove",
    "Time": 14468,
    "X": 846,
    "Y": 540,
    "Delta": null,
    "KeyCode": null
  },
  {
    "Type": "MouseMove",
    "Time": 14495,
    "X": 855,
    "Y": 528,
    "Delta": null,
    "KeyCode": null
  },
  {
    "Type": "MouseMove",
    "Time": 14499,
    "X": 858,
    "Y": 522,
    "Delta": null,
    "KeyCode": null
  },
  {
    "Type": "MouseMove",
    "Time": 14508,
    "X": 864,
    "Y": 516,
    "Delta": null,
    "KeyCode": null
  },
  {
    "Type": "MouseMove",
    "Time": 14515,
    "X": 867,
    "Y": 510,
    "Delta": null,
    "KeyCode": null
  },
  {
    "Type": "MouseMove",
    "Time": 14523,
    "X": 876,
    "Y": 501,
    "Delta": null,
    "KeyCode": null
  },
  {
    "Type": "MouseMove",
    "Time": 14532,
    "X": 882,
    "Y": 495,
    "Delta": null,
    "KeyCode": null
  },
  {
    "Type": "MouseMove",
    "Time": 14557,
    "X": 900,
    "Y": 477,
    "Delta": null,
    "KeyCode": null
  },
  {
    "Type": "MouseMove",
    "Time": 14583,
    "X": 915,
    "Y": 462,
    "Delta": null,
    "KeyCode": null
  },
  {
    "Type": "MouseMove",
    "Time": 14590,
    "X": 918,
    "Y": 453,
    "Delta": null,
    "KeyCode": null
  },
  {
    "Type": "MouseMove",
    "Time": 14616,
    "X": 921,
    "Y": 444,
    "Delta": null,
    "KeyCode": null
  },
  {
    "Type": "MouseMove",
    "Time": 14638,
    "X": 921,
    "Y": 441,
    "Delta": null,
    "KeyCode": null
  },
  {
    "Type": "MouseMove",
    "Time": 14661,
    "X": 921,
    "Y": 438,
    "Delta": null,
    "KeyCode": null
  },
  {
    "Type": "MouseMove",
    "Time": 14716,
    "X": 921,
    "Y": 435,
    "Delta": null,
    "KeyCode": null
  },
  {
    "Type": "MouseMove",
    "Time": 14738,
    "X": 918,
    "Y": 432,
    "Delta": null,
    "KeyCode": null
  },
  {
    "Type": "MouseMove",
    "Time": 14760,
    "X": 909,
    "Y": 432,
    "Delta": null,
    "KeyCode": null
  },
  {
    "Type": "MouseMove",
    "Time": 14784,
    "X": 903,
    "Y": 432,
    "Delta": null,
    "KeyCode": null
  },
  {
    "Type": "MouseMove",
    "Time": 14830,
    "X": 900,
    "Y": 426,
    "Delta": null,
    "KeyCode": null
  },
  {
    "Type": "MouseMove",
    "Time": 14878,
    "X": 900,
    "Y": 423,
    "Delta": null,
    "KeyCode": null
  },
  {
    "Type": "MouseMove",
    "Time": 14902,
    "X": 900,
    "Y": 420,
    "Delta": null,
    "KeyCode": null
  },
  {
    "Type": "DragStart",
    "Time": 14972,
    "X": 900,
    "Y": 420,
    "Delta": null,
    "KeyCode": null
  },
  {
    "Type": "DragEnd",
    "Time": 15088,
    "X": 900,
    "Y": 420,
    "Delta": null,
    "KeyCode": null
  },
  {
    "Type": "DragStart",
    "Time": 15159,
    "X": 900,
    "Y": 420,
    "Delta": null,
    "KeyCode": null
  },
  {
    "Type": "DragEnd",
    "Time": 15245,
    "X": 900,
    "Y": 420,
    "Delta": null,
    "KeyCode": null
  },
  {
    "Type": "MouseMove",
    "Time": 15578,
    "X": 888,
    "Y": 417,
    "Delta": null,
    "KeyCode": null
  },
  {
    "Type": "MouseMove",
    "Time": 15602,
    "X": 858,
    "Y": 411,
    "Delta": null,
    "KeyCode": null
  },
  {
    "Type": "MouseMove",
    "Time": 15625,
    "X": 813,
    "Y": 408,
    "Delta": null,
    "KeyCode": null
  },
  {
    "Type": "MouseMove",
    "Time": 15646,
    "X": 762,
    "Y": 402,
    "Delta": null,
    "KeyCode": null
  },
  {
    "Type": "MouseMove",
    "Time": 15671,
    "X": 705,
    "Y": 393,
    "Delta": null,
    "KeyCode": null
  },
  {
    "Type": "MouseMove",
    "Time": 15694,
    "X": 660,
    "Y": 387,
    "Delta": null,
    "KeyCode": null
  },
  {
    "Type": "MouseMove",
    "Time": 15700,
    "X": 648,
    "Y": 381,
    "Delta": null,
    "KeyCode": null
  },
  {
    "Type": "MouseMove",
    "Time": 15708,
    "X": 636,
    "Y": 378,
    "Delta": null,
    "KeyCode": null
  },
  {
    "Type": "MouseMove",
    "Time": 15735,
    "X": 609,
    "Y": 372,
    "Delta": null,
    "KeyCode": null
  },
  {
    "Type": "MouseMove",
    "Time": 15759,
    "X": 588,
    "Y": 360,
    "Delta": null,
    "KeyCode": null
  },
  {
    "Type": "MouseMove",
    "Time": 15783,
    "X": 576,
    "Y": 354,
    "Delta": null,
    "KeyCode": null
  },
  {
    "Type": "MouseMove",
    "Time": 15806,
    "X": 567,
    "Y": 348,
    "Delta": null,
    "KeyCode": null
  },
  {
    "Type": "MouseMove",
    "Time": 15807,
    "X": 564,
    "Y": 348,
    "Delta": null,
    "KeyCode": null
  },
  {
    "Type": "MouseMove",
    "Time": 15831,
    "X": 555,
    "Y": 342,
    "Delta": null,
    "KeyCode": null
  },
  {
    "Type": "MouseMove",
    "Time": 15855,
    "X": 552,
    "Y": 339,
    "Delta": null,
    "KeyCode": null
  },
  {
    "Type": "MouseMove",
    "Time": 15878,
    "X": 549,
    "Y": 336,
    "Delta": null,
    "KeyCode": null
  },
  {
    "Type": "MouseMove",
    "Time": 15886,
    "X": 546,
    "Y": 336,
    "Delta": null,
    "KeyCode": null
  },
  {
    "Type": "MouseMove",
    "Time": 16021,
    "X": 546,
    "Y": 333,
    "Delta": null,
    "KeyCode": null
  },
  {
    "Type": "MouseMove",
    "Time": 16021,
    "X": 549,
    "Y": 333,
    "Delta": null,
    "KeyCode": null
  },
  {
    "Type": "MouseMove",
    "Time": 16053,
    "X": 552,
    "Y": 333,
    "Delta": null,
    "KeyCode": null
  },
  {
    "Type": "MouseMove",
    "Time": 16077,
    "X": 555,
    "Y": 330,
    "Delta": null,
    "KeyCode": null
  },
  {
    "Type": "MouseMove",
    "Time": 16100,
    "X": 558,
    "Y": 330,
    "Delta": null,
    "KeyCode": null
  },
  {
    "Type": "MouseMove",
    "Time": 16148,
    "X": 561,
    "Y": 330,
    "Delta": null,
    "KeyCode": null
  },
  {
    "Type": "MouseMove",
    "Time": 16171,
    "X": 564,
    "Y": 330,
    "Delta": null,
    "KeyCode": null
  },
  {
    "Type": "MouseMove",
    "Time": 16344,
    "X": 567,
    "Y": 330,
    "Delta": null,
    "KeyCode": null
  },
  {
    "Type": "MouseMove",
    "Time": 16396,
    "X": 570,
    "Y": 330,
    "Delta": null,
    "KeyCode": null
  },
  {
    "Type": "MouseMove",
    "Time": 16420,
    "X": 570,
    "Y": 333,
    "Delta": null,
    "KeyCode": null
  },
  {
    "Type": "MouseMove",
    "Time": 16608,
    "X": 567,
    "Y": 336,
    "Delta": null,
    "KeyCode": null
  },
  {
    "Type": "MouseMove",
    "Time": 16609,
    "X": 564,
    "Y": 336,
    "Delta": null,
    "KeyCode": null
  },
  {
    "Type": "MouseMove",
    "Time": 16637,
    "X": 564,
    "Y": 339,
    "Delta": null,
    "KeyCode": null
  },
  {
    "Type": "MouseMove",
    "Time": 16641,
    "X": 561,
    "Y": 339,
    "Delta": null,
    "KeyCode": null
  },
  {
    "Type": "DragStart",
    "Time": 16935,
    "X": 561,
    "Y": 339,
    "Delta": null,
    "KeyCode": null
  },
  {
    "Type": "DragEnd",
    "Time": 16971,
    "X": 561,
    "Y": 339,
    "Delta": null,
    "KeyCode": null
  },
  {
    "Type": "MouseMove",
    "Time": 18706,
    "X": 561,
    "Y": 336,
    "Delta": null,
    "KeyCode": null
  },
  {
    "Type": "MouseMove",
    "Time": 18776,
    "X": 558,
    "Y": 336,
    "Delta": null,
    "KeyCode": null
  },
  {
    "Type": "MouseMove",
    "Time": 18806,
    "X": 549,
    "Y": 336,
    "Delta": null,
    "KeyCode": null
  },
  {
    "Type": "MouseMove",
    "Time": 18810,
    "X": 546,
    "Y": 336,
    "Delta": null,
    "KeyCode": null
  },
  {
    "Type": "MouseMove",
    "Time": 18838,
    "X": 537,
    "Y": 333,
    "Delta": null,
    "KeyCode": null
  },
  {
    "Type": "MouseMove",
    "Time": 18842,
    "X": 534,
    "Y": 333,
    "Delta": null,
    "KeyCode": null
  },
  {
    "Type": "MouseMove",
    "Time": 18867,
    "X": 522,
    "Y": 333,
    "Delta": null,
    "KeyCode": null
  },
  {
    "Type": "MouseMove",
    "Time": 18893,
    "X": 507,
    "Y": 330,
    "Delta": null,
    "KeyCode": null
  },
  {
    "Type": "MouseMove",
    "Time": 18917,
    "X": 486,
    "Y": 330,
    "Delta": null,
    "KeyCode": null
  },
  {
    "Type": "MouseMove",
    "Time": 18940,
    "X": 462,
    "Y": 330,
    "Delta": null,
    "KeyCode": null
  },
  {
    "Type": "MouseMove",
    "Time": 18966,
    "X": 435,
    "Y": 333,
    "Delta": null,
    "KeyCode": null
  },
  {
    "Type": "MouseMove",
    "Time": 18988,
    "X": 405,
    "Y": 333,
    "Delta": null,
    "KeyCode": null
  },
  {
    "Type": "MouseMove",
    "Time": 18996,
    "X": 396,
    "Y": 336,
    "Delta": null,
    "KeyCode": null
  },
  {
    "Type": "MouseMove",
    "Time": 19004,
    "X": 387,
    "Y": 336,
    "Delta": null,
    "KeyCode": null
  },
  {
    "Type": "MouseMove",
    "Time": 19030,
    "X": 360,
    "Y": 336,
    "Delta": null,
    "KeyCode": null
  },
  {
    "Type": "MouseMove",
    "Time": 19054,
    "X": 336,
    "Y": 339,
    "Delta": null,
    "KeyCode": null
  },
  {
    "Type": "MouseMove",
    "Time": 19076,
    "X": 324,
    "Y": 339,
    "Delta": null,
    "KeyCode": null
  },
  {
    "Type": "MouseMove",
    "Time": 19076,
    "X": 318,
    "Y": 339,
    "Delta": null,
    "KeyCode": null
  },
  {
    "Type": "MouseMove",
    "Time": 19106,
    "X": 309,
    "Y": 339,
    "Delta": null,
    "KeyCode": null
  },
  {
    "Type": "MouseMove",
    "Time": 19107,
    "X": 297,
    "Y": 339,
    "Delta": null,
    "KeyCode": null
  },
  {
    "Type": "MouseMove",
    "Time": 19129,
    "X": 282,
    "Y": 339,
    "Delta": null,
    "KeyCode": null
  },
  {
    "Type": "MouseMove",
    "Time": 19132,
    "X": 276,
    "Y": 342,
    "Delta": null,
    "KeyCode": null
  },
  {
    "Type": "MouseMove",
    "Time": 19139,
    "X": 273,
    "Y": 342,
    "Delta": null,
    "KeyCode": null
  },
  {
    "Type": "MouseMove",
    "Time": 19148,
    "X": 267,
    "Y": 342,
    "Delta": null,
    "KeyCode": null
  },
  {
    "Type": "MouseMove",
    "Time": 19155,
    "X": 264,
    "Y": 342,
    "Delta": null,
    "KeyCode": null
  },
  {
    "Type": "MouseMove",
    "Time": 19181,
    "X": 252,
    "Y": 342,
    "Delta": null,
    "KeyCode": null
  },
  {
    "Type": "MouseMove",
    "Time": 19213,
    "X": 243,
    "Y": 342,
    "Delta": null,
    "KeyCode": null
  },
  {
    "Type": "MouseMove",
    "Time": 19236,
    "X": 240,
    "Y": 342,
    "Delta": null,
    "KeyCode": null
  },
  {
    "Type": "MouseMove",
    "Time": 19237,
    "X": 237,
    "Y": 342,
    "Delta": null,
    "KeyCode": null
  },
  {
    "Type": "MouseMove",
    "Time": 19282,
    "X": 234,
    "Y": 342,
    "Delta": null,
    "KeyCode": null
  },
  {
    "Type": "MouseMove",
    "Time": 19358,
    "X": 231,
    "Y": 342,
    "Delta": null,
    "KeyCode": null
  },
  {
    "Type": "MouseMove",
    "Time": 19714,
    "X": 228,
    "Y": 342,
    "Delta": null,
    "KeyCode": null
  },
  {
    "Type": "MouseMove",
    "Time": 19791,
    "X": 228,
    "Y": 339,
    "Delta": null,
    "KeyCode": null
  },
  {
    "Type": "MouseMove",
    "Time": 19981,
    "X": 225,
    "Y": 339,
    "Delta": null,
    "KeyCode": null
  },
  {
    "Type": "MouseMove",
    "Time": 20004,
    "X": 219,
    "Y": 342,
    "Delta": null,
    "KeyCode": null
  },
  {
    "Type": "MouseMove",
    "Time": 20027,
    "X": 216,
    "Y": 342,
    "Delta": null,
    "KeyCode": null
  },
  {
    "Type": "MouseMove",
    "Time": 20049,
    "X": 213,
    "Y": 345,
    "Delta": null,
    "KeyCode": null
  },
  {
    "Type": "MouseMove",
    "Time": 20072,
    "X": 210,
    "Y": 345,
    "Delta": null,
    "KeyCode": null
  },
  {
    "Type": "MouseMove",
    "Time": 20321,
    "X": 207,
    "Y": 348,
    "Delta": null,
    "KeyCode": null
  },
  {
    "Type": "MouseMove",
    "Time": 20345,
    "X": 204,
    "Y": 351,
    "Delta": null,
    "KeyCode": null
  },
  {
    "Type": "DragStart",
    "Time": 20619,
    "X": 204,
    "Y": 351,
    "Delta": null,
    "KeyCode": null
  },
  {
    "Type": "DragEnd",
    "Time": 20711,
    "X": 204,
    "Y": 351,
    "Delta": null,
    "KeyCode": null
  },
  {
    "Type": "MouseMove",
    "Time": 21387,
    "X": 204,
    "Y": 348,
    "Delta": null,
    "KeyCode": null
  },
  {
    "Type": "MouseMove",
    "Time": 21388,
    "X": 207,
    "Y": 348,
    "Delta": null,
    "KeyCode": null
  },
  {
    "Type": "MouseMove",
    "Time": 21396,
    "X": 210,
    "Y": 342,
    "Delta": null,
    "KeyCode": null
  },
  {
    "Type": "MouseMove",
    "Time": 21420,
    "X": 234,
    "Y": 330,
    "Delta": null,
    "KeyCode": null
  },
  {
    "Type": "MouseMove",
    "Time": 21444,
    "X": 264,
    "Y": 315,
    "Delta": null,
    "KeyCode": null
  },
  {
    "Type": "MouseMove",
    "Time": 21468,
    "X": 288,
    "Y": 303,
    "Delta": null,
    "KeyCode": null
  },
  {
    "Type": "MouseMove",
    "Time": 21497,
    "X": 339,
    "Y": 285,
    "Delta": null,
    "KeyCode": null
  },
  {
    "Type": "MouseMove",
    "Time": 21520,
    "X": 402,
    "Y": 264,
    "Delta": null,
    "KeyCode": null
  },
  {
    "Type": "MouseMove",
    "Time": 21546,
    "X": 462,
    "Y": 240,
    "Delta": null,
    "KeyCode": null
  },
  {
    "Type": "MouseMove",
    "Time": 21568,
    "X": 507,
    "Y": 216,
    "Delta": null,
    "KeyCode": null
  },
  {
    "Type": "MouseMove",
    "Time": 21590,
    "X": 549,
    "Y": 195,
    "Delta": null,
    "KeyCode": null
  },
  {
    "Type": "MouseMove",
    "Time": 21612,
    "X": 570,
    "Y": 183,
    "Delta": null,
    "KeyCode": null
  },
  {
    "Type": "MouseMove",
    "Time": 21614,
    "X": 576,
    "Y": 180,
    "Delta": null,
    "KeyCode": null
  },
  {
    "Type": "MouseMove",
    "Time": 21638,
    "X": 603,
    "Y": 162,
    "Delta": null,
    "KeyCode": null
  },
  {
    "Type": "MouseMove",
    "Time": 21661,
    "X": 612,
    "Y": 156,
    "Delta": null,
    "KeyCode": null
  },
  {
    "Type": "MouseMove",
    "Time": 21686,
    "X": 630,
    "Y": 138,
    "Delta": null,
    "KeyCode": null
  },
  {
    "Type": "MouseMove",
    "Time": 21711,
    "X": 645,
    "Y": 123,
    "Delta": null,
    "KeyCode": null
  },
  {
    "Type": "MouseMove",
    "Time": 21737,
    "X": 654,
    "Y": 114,
    "Delta": null,
    "KeyCode": null
  },
  {
    "Type": "MouseMove",
    "Time": 21760,
    "X": 663,
    "Y": 99,
    "Delta": null,
    "KeyCode": null
  },
  {
    "Type": "MouseMove",
    "Time": 21782,
    "X": 666,
    "Y": 93,
    "Delta": null,
    "KeyCode": null
  },
  {
    "Type": "MouseMove",
    "Time": 21809,
    "X": 669,
    "Y": 87,
    "Delta": null,
    "KeyCode": null
  },
  {
    "Type": "MouseMove",
    "Time": 21833,
    "X": 672,
    "Y": 84,
    "Delta": null,
    "KeyCode": null
  },
  {
    "Type": "MouseMove",
    "Time": 21856,
    "X": 678,
    "Y": 75,
    "Delta": null,
    "KeyCode": null
  },
  {
    "Type": "MouseMove",
    "Time": 21879,
    "X": 681,
    "Y": 69,
    "Delta": null,
    "KeyCode": null
  },
  {
    "Type": "MouseMove",
    "Time": 21904,
    "X": 684,
    "Y": 63,
    "Delta": null,
    "KeyCode": null
  },
  {
    "Type": "MouseMove",
    "Time": 21912,
    "X": 687,
    "Y": 60,
    "Delta": null,
    "KeyCode": null
  },
  {
    "Type": "MouseMove",
    "Time": 21918,
    "X": 690,
    "Y": 57,
    "Delta": null,
    "KeyCode": null
  },
  {
    "Type": "MouseMove",
    "Time": 21944,
    "X": 702,
    "Y": 45,
    "Delta": null,
    "KeyCode": null
  },
  {
    "Type": "MouseMove",
    "Time": 21966,
    "X": 711,
    "Y": 36,
    "Delta": null,
    "KeyCode": null
  },
  {
    "Type": "MouseMove",
    "Time": 21967,
    "X": 714,
    "Y": 33,
    "Delta": null,
    "KeyCode": null
  },
  {
    "Type": "MouseMove",
    "Time": 21976,
    "X": 717,
    "Y": 30,
    "Delta": null,
    "KeyCode": null
  },
  {
    "Type": "MouseMove",
    "Time": 22005,
    "X": 720,
    "Y": 24,
    "Delta": null,
    "KeyCode": null
  },
  {
    "Type": "MouseMove",
    "Time": 22037,
    "X": 720,
    "Y": 21,
    "Delta": null,
    "KeyCode": null
  },
  {
    "Type": "MouseMove",
    "Time": 22059,
    "X": 720,
    "Y": 18,
    "Delta": null,
    "KeyCode": null
  },
  {
    "Type": "MouseMove",
    "Time": 49011,
    "X": 252,
    "Y": 594,
    "Delta": null,
    "KeyCode": null
  },
  {
    "Type": "MouseMove",
    "Time": 49040,
    "X": 264,
    "Y": 588,
    "Delta": null,
    "KeyCode": null
  },
  {
    "Type": "MouseMove",
    "Time": 49042,
    "X": 267,
    "Y": 588,
    "Delta": null,
    "KeyCode": null
  },
  {
    "Type": "MouseMove",
    "Time": 49068,
    "X": 294,
    "Y": 576,
    "Delta": null,
    "KeyCode": null
  },
  {
    "Type": "MouseMove",
    "Time": 49074,
    "X": 303,
    "Y": 573,
    "Delta": null,
    "KeyCode": null
  },
  {
    "Type": "MouseMove",
    "Time": 49098,
    "X": 333,
    "Y": 564,
    "Delta": null,
    "KeyCode": null
  },
  {
    "Type": "MouseMove",
    "Time": 49122,
    "X": 360,
    "Y": 552,
    "Delta": null,
    "KeyCode": null
  },
  {
    "Type": "MouseMove",
    "Time": 49122,
    "X": 372,
    "Y": 546,
    "Delta": null,
    "KeyCode": null
  },
  {
    "Type": "MouseMove",
    "Time": 49146,
    "X": 405,
    "Y": 531,
    "Delta": null,
    "KeyCode": null
  },
  {
    "Type": "MouseMove",
    "Time": 49169,
    "X": 420,
    "Y": 528,
    "Delta": null,
    "KeyCode": null
  },
  {
    "Type": "MouseMove",
    "Time": 49170,
    "X": 450,
    "Y": 516,
    "Delta": null,
    "KeyCode": null
  },
  {
    "Type": "MouseMove",
    "Time": 49193,
    "X": 465,
    "Y": 513,
    "Delta": null,
    "KeyCode": null
  },
  {
    "Type": "MouseMove",
    "Time": 49194,
    "X": 501,
    "Y": 507,
    "Delta": null,
    "KeyCode": null
  },
  {
    "Type": "MouseMove",
    "Time": 49218,
    "X": 567,
    "Y": 486,
    "Delta": null,
    "KeyCode": null
  },
  {
    "Type": "MouseMove",
    "Time": 49240,
    "X": 597,
    "Y": 480,
    "Delta": null,
    "KeyCode": null
  },
  {
    "Type": "MouseMove",
    "Time": 49241,
    "X": 624,
    "Y": 474,
    "Delta": null,
    "KeyCode": null
  },
  {
    "Type": "MouseMove",
    "Time": 49273,
    "X": 681,
    "Y": 462,
    "Delta": null,
    "KeyCode": null
  },
  {
    "Type": "MouseMove",
    "Time": 49295,
    "X": 732,
    "Y": 453,
    "Delta": null,
    "KeyCode": null
  },
  {
    "Type": "MouseMove",
    "Time": 49298,
    "X": 747,
    "Y": 450,
    "Delta": null,
    "KeyCode": null
  },
  {
    "Type": "MouseMove",
    "Time": 49308,
    "X": 759,
    "Y": 450,
    "Delta": null,
    "KeyCode": null
  },
  {
    "Type": "MouseMove",
    "Time": 49332,
    "X": 789,
    "Y": 447,
    "Delta": null,
    "KeyCode": null
  },
  {
    "Type": "MouseMove",
    "Time": 49340,
    "X": 795,
    "Y": 444,
    "Delta": null,
    "KeyCode": null
  },
  {
    "Type": "MouseMove",
    "Time": 49366,
    "X": 801,
    "Y": 444,
    "Delta": null,
    "KeyCode": null
  },
  {
    "Type": "MouseMove",
    "Time": 49372,
    "X": 804,
    "Y": 444,
    "Delta": null,
    "KeyCode": null
  },
  {
    "Type": "MouseMove",
    "Time": 49480,
    "X": 810,
    "Y": 444,
    "Delta": null,
    "KeyCode": null
  },
  {
    "Type": "MouseMove",
    "Time": 49504,
    "X": 822,
    "Y": 441,
    "Delta": null,
    "KeyCode": null
  },
  {
    "Type": "MouseMove",
    "Time": 49529,
    "X": 831,
    "Y": 438,
    "Delta": null,
    "KeyCode": null
  },
  {
    "Type": "MouseMove",
    "Time": 49551,
    "X": 837,
    "Y": 438,
    "Delta": null,
    "KeyCode": null
  },
  {
    "Type": "MouseMove",
    "Time": 49576,
    "X": 840,
    "Y": 438,
    "Delta": null,
    "KeyCode": null
  },
  {
    "Type": "MouseMove",
    "Time": 49599,
    "X": 846,
    "Y": 438,
    "Delta": null,
    "KeyCode": null
  },
  {
    "Type": "MouseMove",
    "Time": 49623,
    "X": 855,
    "Y": 435,
    "Delta": null,
    "KeyCode": null
  },
  {
    "Type": "MouseMove",
    "Time": 49645,
    "X": 861,
    "Y": 432,
    "Delta": null,
    "KeyCode": null
  },
  {
    "Type": "MouseMove",
    "Time": 49646,
    "X": 867,
    "Y": 432,
    "Delta": null,
    "KeyCode": null
  },
  {
    "Type": "MouseMove",
    "Time": 49654,
    "X": 870,
    "Y": 429,
    "Delta": null,
    "KeyCode": null
  },
  {
    "Type": "MouseMove",
    "Time": 49677,
    "X": 876,
    "Y": 429,
    "Delta": null,
    "KeyCode": null
  },
  {
    "Type": "MouseMove",
    "Time": 49758,
    "X": 876,
    "Y": 426,
    "Delta": null,
    "KeyCode": null
  },
  {
    "Type": "MouseMove",
    "Time": 49766,
    "X": 879,
    "Y": 426,
    "Delta": null,
    "KeyCode": null
  },
  {
    "Type": "MouseMove",
    "Time": 49806,
    "X": 882,
    "Y": 426,
    "Delta": null,
    "KeyCode": null
  },
  {
    "Type": "MouseMove",
    "Time": 49846,
    "X": 885,
    "Y": 426,
    "Delta": null,
    "KeyCode": null
  },
  {
    "Type": "MouseMove",
    "Time": 49868,
    "X": 888,
    "Y": 423,
    "Delta": null,
    "KeyCode": null
  },
  {
    "Type": "MouseMove",
    "Time": 49869,
    "X": 891,
    "Y": 423,
    "Delta": null,
    "KeyCode": null
  },
  {
    "Type": "MouseMove",
    "Time": 49886,
    "X": 894,
    "Y": 423,
    "Delta": null,
    "KeyCode": null
  },
  {
    "Type": "DragStart",
    "Time": 49952,
    "X": 894,
    "Y": 423,
    "Delta": null,
    "KeyCode": null
  },
  {
    "Type": "DragEnd",
    "Time": 50012,
    "X": 894,
    "Y": 423,
    "Delta": null,
    "KeyCode": null
  },
  {
    "Type": "MouseMove",
    "Time": 50207,
    "X": 894,
    "Y": 420,
    "Delta": null,
    "KeyCode": null
  },
  {
    "Type": "MouseMove",
    "Time": 50232,
    "X": 894,
    "Y": 414,
    "Delta": null,
    "KeyCode": null
  },
  {
    "Type": "MouseMove",
    "Time": 50233,
    "X": 894,
    "Y": 411,
    "Delta": null,
    "KeyCode": null
  },
  {
    "Type": "MouseMove",
    "Time": 50259,
    "X": 897,
    "Y": 405,
    "Delta": null,
    "KeyCode": null
  },
  {
    "Type": "MouseMove",
    "Time": 50266,
    "X": 897,
    "Y": 402,
    "Delta": null,
    "KeyCode": null
  },
  {
    "Type": "MouseMove",
    "Time": 50291,
    "X": 897,
    "Y": 396,
    "Delta": null,
    "KeyCode": null
  },
  {
    "Type": "MouseMove",
    "Time": 50298,
    "X": 897,
    "Y": 393,
    "Delta": null,
    "KeyCode": null
  },
  {
    "Type": "MouseMove",
    "Time": 50323,
    "X": 897,
    "Y": 390,
    "Delta": null,
    "KeyCode": null
  },
  {
    "Type": "MouseMove",
    "Time": 50370,
    "X": 897,
    "Y": 387,
    "Delta": null,
    "KeyCode": null
  },
  {
    "Type": "MouseMove",
    "Time": 50401,
    "X": 900,
    "Y": 381,
    "Delta": null,
    "KeyCode": null
  },
  {
    "Type": "MouseMove",
    "Time": 50402,
    "X": 900,
    "Y": 378,
    "Delta": null,
    "KeyCode": null
  },
  {
    "Type": "MouseMove",
    "Time": 50429,
    "X": 900,
    "Y": 372,
    "Delta": null,
    "KeyCode": null
  },
  {
    "Type": "MouseMove",
    "Time": 50461,
    "X": 900,
    "Y": 363,
    "Delta": null,
    "KeyCode": null
  },
  {
    "Type": "MouseMove",
    "Time": 50468,
    "X": 900,
    "Y": 360,
    "Delta": null,
    "KeyCode": null
  },
  {
    "Type": "MouseMove",
    "Time": 50493,
    "X": 900,
    "Y": 354,
    "Delta": null,
    "KeyCode": null
  },
  {
    "Type": "MouseMove",
    "Time": 50516,
    "X": 900,
    "Y": 348,
    "Delta": null,
    "KeyCode": null
  },
  {
    "Type": "MouseMove",
    "Time": 50540,
    "X": 900,
    "Y": 342,
    "Delta": null,
    "KeyCode": null
  },
  {
    "Type": "MouseMove",
    "Time": 50563,
    "X": 900,
    "Y": 339,
    "Delta": null,
    "KeyCode": null
  },
  {
    "Type": "MouseMove",
    "Time": 50564,
    "X": 900,
    "Y": 336,
    "Delta": null,
    "KeyCode": null
  },
  {
    "Type": "MouseMove",
    "Time": 50580,
    "X": 900,
    "Y": 333,
    "Delta": null,
    "KeyCode": null
  },
  {
    "Type": "MouseMove",
    "Time": 50603,
    "X": 900,
    "Y": 330,
    "Delta": null,
    "KeyCode": null
  },
  {
    "Type": "MouseMove",
    "Time": 51137,
    "X": 903,
    "Y": 327,
    "Delta": null,
    "KeyCode": null
  },
  {
    "Type": "MouseMove",
    "Time": 51144,
    "X": 906,
    "Y": 327,
    "Delta": null,
    "KeyCode": null
  },
  {
    "Type": "MouseMove",
    "Time": 51169,
    "X": 909,
    "Y": 327,
    "Delta": null,
    "KeyCode": null
  },
  {
    "Type": "MouseMove",
    "Time": 51247,
    "X": 912,
    "Y": 324,
    "Delta": null,
    "KeyCode": null
  },
  {
    "Type": "MouseMove",
    "Time": 51279,
    "X": 915,
    "Y": 321,
    "Delta": null,
    "KeyCode": null
  },
  {
    "Type": "MouseMove",
    "Time": 51288,
    "X": 918,
    "Y": 321,
    "Delta": null,
    "KeyCode": null
  },
  {
    "Type": "MouseMove",
    "Time": 51310,
    "X": 918,
    "Y": 318,
    "Delta": null,
    "KeyCode": null
  },
  {
    "Type": "MouseMove",
    "Time": 51340,
    "X": 924,
    "Y": 312,
    "Delta": null,
    "KeyCode": null
  },
  {
    "Type": "MouseMove",
    "Time": 51344,
    "X": 927,
    "Y": 309,
    "Delta": null,
    "KeyCode": null
  },
  {
    "Type": "MouseMove",
    "Time": 51371,
    "X": 930,
    "Y": 303,
    "Delta": null,
    "KeyCode": null
  },
  {
    "Type": "MouseMove",
    "Time": 51396,
    "X": 930,
    "Y": 300,
    "Delta": null,
    "KeyCode": null
  },
  {
    "Type": "MouseMove",
    "Time": 51549,
    "X": 933,
    "Y": 300,
    "Delta": null,
    "KeyCode": null
  },
  {
    "Type": "MouseMove",
    "Time": 51573,
    "X": 936,
    "Y": 294,
    "Delta": null,
    "KeyCode": null
  },
  {
    "Type": "MouseMove",
    "Time": 51629,
    "X": 936,
    "Y": 291,
    "Delta": null,
    "KeyCode": null
  },
  {
    "Type": "MouseMove",
    "Time": 51676,
    "X": 936,
    "Y": 288,
    "Delta": null,
    "KeyCode": null
  },
  {
    "Type": "MouseMove",
    "Time": 51706,
    "X": 939,
    "Y": 288,
    "Delta": null,
    "KeyCode": null
  },
  {
    "Type": "DragStart",
    "Time": 51707,
    "X": 939,
    "Y": 288,
    "Delta": null,
    "KeyCode": null
  },
  {
    "Type": "DragEnd",
    "Time": 51769,
    "X": 939,
    "Y": 288,
    "Delta": null,
    "KeyCode": null
  },
  {
    "Type": "MouseMove",
    "Time": 51958,
    "X": 936,
    "Y": 285,
    "Delta": null,
    "KeyCode": null
  },
  {
    "Type": "MouseMove",
    "Time": 51992,
    "X": 936,
    "Y": 282,
    "Delta": null,
    "KeyCode": null
  },
  {
    "Type": "MouseMove",
    "Time": 52021,
    "X": 933,
    "Y": 276,
    "Delta": null,
    "KeyCode": null
  },
  {
    "Type": "MouseMove",
    "Time": 52046,
    "X": 930,
    "Y": 273,
    "Delta": null,
    "KeyCode": null
  },
  {
    "Type": "MouseMove",
    "Time": 52070,
    "X": 927,
    "Y": 264,
    "Delta": null,
    "KeyCode": null
  },
  {
    "Type": "MouseMove",
    "Time": 52093,
    "X": 924,
    "Y": 261,
    "Delta": null,
    "KeyCode": null
  },
  {
    "Type": "MouseMove",
    "Time": 52094,
    "X": 921,
    "Y": 258,
    "Delta": null,
    "KeyCode": null
  },
  {
    "Type": "MouseMove",
    "Time": 52118,
    "X": 918,
    "Y": 255,
    "Delta": null,
    "KeyCode": null
  },
  {
    "Type": "MouseMove",
    "Time": 52118,
    "X": 918,
    "Y": 249,
    "Delta": null,
    "KeyCode": null
  },
  {
    "Type": "MouseMove",
    "Time": 52140,
    "X": 915,
    "Y": 246,
    "Delta": null,
    "KeyCode": null
  },
  {
    "Type": "MouseMove",
    "Time": 52164,
    "X": 909,
    "Y": 240,
    "Delta": null,
    "KeyCode": null
  },
  {
    "Type": "MouseMove",
    "Time": 52188,
    "X": 903,
    "Y": 234,
    "Delta": null,
    "KeyCode": null
  },
  {
    "Type": "MouseMove",
    "Time": 52211,
    "X": 897,
    "Y": 228,
    "Delta": null,
    "KeyCode": null
  },
  {
    "Type": "MouseMove",
    "Time": 52235,
    "X": 891,
    "Y": 222,
    "Delta": null,
    "KeyCode": null
  },
  {
    "Type": "MouseMove",
    "Time": 52258,
    "X": 885,
    "Y": 216,
    "Delta": null,
    "KeyCode": null
  },
  {
    "Type": "MouseMove",
    "Time": 52264,
    "X": 885,
    "Y": 213,
    "Delta": null,
    "KeyCode": null
  },
  {
    "Type": "MouseMove",
    "Time": 52288,
    "X": 879,
    "Y": 207,
    "Delta": null,
    "KeyCode": null
  },
  {
    "Type": "MouseMove",
    "Time": 52296,
    "X": 876,
    "Y": 204,
    "Delta": null,
    "KeyCode": null
  },
  {
    "Type": "MouseMove",
    "Time": 52318,
    "X": 870,
    "Y": 198,
    "Delta": null,
    "KeyCode": null
  },
  {
    "Type": "MouseMove",
    "Time": 52319,
    "X": 867,
    "Y": 195,
    "Delta": null,
    "KeyCode": null
  },
  {
    "Type": "MouseMove",
    "Time": 52328,
    "X": 864,
    "Y": 192,
    "Delta": null,
    "KeyCode": null
  },
  {
    "Type": "MouseMove",
    "Time": 52353,
    "X": 858,
    "Y": 186,
    "Delta": null,
    "KeyCode": null
  },
  {
    "Type": "MouseMove",
    "Time": 52381,
    "X": 852,
    "Y": 180,
    "Delta": null,
    "KeyCode": null
  },
  {
    "Type": "MouseMove",
    "Time": 52383,
    "X": 849,
    "Y": 177,
    "Delta": null,
    "KeyCode": null
  },
  {
    "Type": "MouseMove",
    "Time": 52415,
    "X": 846,
    "Y": 174,
    "Delta": null,
    "KeyCode": null
  },
  {
    "Type": "MouseMove",
    "Time": 52466,
    "X": 843,
    "Y": 171,
    "Delta": null,
    "KeyCode": null
  },
  {
    "Type": "MouseMove",
    "Time": 52522,
    "X": 843,
    "Y": 168,
    "Delta": null,
    "KeyCode": null
  },
  {
    "Type": "MouseMove",
    "Time": 52561,
    "X": 843,
    "Y": 165,
    "Delta": null,
    "KeyCode": null
  },
  {
    "Type": "MouseMove",
    "Time": 52585,
    "X": 843,
    "Y": 162,
    "Delta": null,
    "KeyCode": null
  },
  {
    "Type": "MouseMove",
    "Time": 52611,
    "X": 843,
    "Y": 159,
    "Delta": null,
    "KeyCode": null
  },
  {
    "Type": "MouseMove",
    "Time": 52637,
    "X": 843,
    "Y": 156,
    "Delta": null,
    "KeyCode": null
  },
  {
    "Type": "MouseMove",
    "Time": 52738,
    "X": 843,
    "Y": 153,
    "Delta": null,
    "KeyCode": null
  },
  {
    "Type": "MouseMove",
    "Time": 52766,
    "X": 843,
    "Y": 150,
    "Delta": null,
    "KeyCode": null
  },
  {
    "Type": "MouseMove",
    "Time": 52791,
    "X": 840,
    "Y": 150,
    "Delta": null,
    "KeyCode": null
  },
  {
    "Type": "MouseMove",
    "Time": 52818,
    "X": 837,
    "Y": 150,
    "Delta": null,
    "KeyCode": null
  },
  {
    "Type": "MouseMove",
    "Time": 52842,
    "X": 834,
    "Y": 150,
    "Delta": null,
    "KeyCode": null
  },
  {
    "Type": "MouseMove",
    "Time": 52842,
    "X": 831,
    "Y": 147,
    "Delta": null,
    "KeyCode": null
  },
  {
    "Type": "MouseMove",
    "Time": 52876,
    "X": 825,
    "Y": 144,
    "Delta": null,
    "KeyCode": null
  },
  {
    "Type": "MouseMove",
    "Time": 52906,
    "X": 822,
    "Y": 144,
    "Delta": null,
    "KeyCode": null
  },
  {
    "Type": "MouseMove",
    "Time": 52932,
    "X": 819,
    "Y": 141,
    "Delta": null,
    "KeyCode": null
  },
  {
    "Type": "MouseMove",
    "Time": 52958,
    "X": 816,
    "Y": 141,
    "Delta": null,
    "KeyCode": null
  },
  {
    "Type": "MouseMove",
    "Time": 52984,
    "X": 813,
    "Y": 141,
    "Delta": null,
    "KeyCode": null
  },
  {
    "Type": "MouseMove",
    "Time": 53063,
    "X": 810,
    "Y": 141,
    "Delta": null,
    "KeyCode": null
  },
  {
    "Type": "MouseMove",
    "Time": 53117,
    "X": 807,
    "Y": 141,
    "Delta": null,
    "KeyCode": null
  },
  {
    "Type": "MouseMove",
    "Time": 53190,
    "X": 804,
    "Y": 141,
    "Delta": null,
    "KeyCode": null
  },
  {
    "Type": "MouseMove",
    "Time": 53344,
    "X": 807,
    "Y": 144,
    "Delta": null,
    "KeyCode": null
  },
  {
    "Type": "MouseMove",
    "Time": 53366,
    "X": 810,
    "Y": 144,
    "Delta": null,
    "KeyCode": null
  },
  {
    "Type": "MouseMove",
    "Time": 53392,
    "X": 813,
    "Y": 144,
    "Delta": null,
    "KeyCode": null
  },
  {
    "Type": "MouseMove",
    "Time": 53423,
    "X": 816,
    "Y": 144,
    "Delta": null,
    "KeyCode": null
  },
  {
    "Type": "MouseMove",
    "Time": 53455,
    "X": 819,
    "Y": 144,
    "Delta": null,
    "KeyCode": null
  },
  {
    "Type": "MouseMove",
    "Time": 53486,
    "X": 822,
    "Y": 144,
    "Delta": null,
    "KeyCode": null
  },
  {
    "Type": "MouseMove",
    "Time": 53512,
    "X": 828,
    "Y": 144,
    "Delta": null,
    "KeyCode": null
  },
  {
    "Type": "MouseMove",
    "Time": 53535,
    "X": 831,
    "Y": 144,
    "Delta": null,
    "KeyCode": null
  },
  {
    "Type": "MouseMove",
    "Time": 53582,
    "X": 834,
    "Y": 144,
    "Delta": null,
    "KeyCode": null
  },
  {
    "Type": "MouseMove",
    "Time": 53735,
    "X": 834,
    "Y": 147,
    "Delta": null,
    "KeyCode": null
  },
  {
    "Type": "MouseMove",
    "Time": 53745,
    "X": 834,
    "Y": 150,
    "Delta": null,
    "KeyCode": null
  },
  {
    "Type": "MouseMove",
    "Time": 53753,
    "X": 834,
    "Y": 153,
    "Delta": null,
    "KeyCode": null
  },
  {
    "Type": "MouseMove",
    "Time": 53783,
    "X": 834,
    "Y": 156,
    "Delta": null,
    "KeyCode": null
  },
  {
    "Type": "MouseMove",
    "Time": 53814,
    "X": 834,
    "Y": 162,
    "Delta": null,
    "KeyCode": null
  },
  {
    "Type": "MouseMove",
    "Time": 53909,
    "X": 834,
    "Y": 165,
    "Delta": null,
    "KeyCode": null
  },
  {
    "Type": "MouseMove",
    "Time": 53932,
    "X": 831,
    "Y": 165,
    "Delta": null,
    "KeyCode": null
  },
  {
    "Type": "MouseMove",
    "Time": 53956,
    "X": 831,
    "Y": 168,
    "Delta": null,
    "KeyCode": null
  },
  {
    "Type": "MouseMove",
    "Time": 53979,
    "X": 831,
    "Y": 171,
    "Delta": null,
    "KeyCode": null
  },
  {
    "Type": "MouseMove",
    "Time": 54004,
    "X": 831,
    "Y": 174,
    "Delta": null,
    "KeyCode": null
  },
  {
    "Type": "MouseMove",
    "Time": 54272,
    "X": 834,
    "Y": 174,
    "Delta": null,
    "KeyCode": null
  },
  {
    "Type": "DragStart",
    "Time": 54487,
    "X": 834,
    "Y": 174,
    "Delta": null,
    "KeyCode": null
  },
  {
    "Type": "DragEnd",
    "Time": 54565,
    "X": 834,
    "Y": 174,
    "Delta": null,
    "KeyCode": null
  },
  {
    "Type": "MouseMove",
    "Time": 54589,
    "X": 837,
    "Y": 174,
    "Delta": null,
    "KeyCode": null
  },
  {
    "Type": "MouseMove",
    "Time": 54640,
    "X": 840,
    "Y": 174,
    "Delta": null,
    "KeyCode": null
  },
  {
    "Type": "MouseMove",
    "Time": 54671,
    "X": 858,
    "Y": 189,
    "Delta": null,
    "KeyCode": null
  },
  {
    "Type": "MouseMove",
    "Time": 54695,
    "X": 882,
    "Y": 222,
    "Delta": null,
    "KeyCode": null
  },
  {
    "Type": "MouseMove",
    "Time": 54717,
    "X": 894,
    "Y": 264,
    "Delta": null,
    "KeyCode": null
  },
  {
    "Type": "MouseMove",
    "Time": 54719,
    "X": 894,
    "Y": 285,
    "Delta": null,
    "KeyCode": null
  },
  {
    "Type": "MouseMove",
    "Time": 54745,
    "X": 897,
    "Y": 321,
    "Delta": null,
    "KeyCode": null
  },
  {
    "Type": "MouseMove",
    "Time": 54767,
    "X": 900,
    "Y": 342,
    "Delta": null,
    "KeyCode": null
  },
  {
    "Type": "MouseMove",
    "Time": 54790,
    "X": 900,
    "Y": 384,
    "Delta": null,
    "KeyCode": null
  },
  {
    "Type": "MouseMove",
    "Time": 54791,
    "X": 900,
    "Y": 390,
    "Delta": null,
    "KeyCode": null
  },
  {
    "Type": "MouseMove",
    "Time": 54800,
    "X": 900,
    "Y": 399,
    "Delta": null,
    "KeyCode": null
  },
  {
    "Type": "MouseMove",
    "Time": 54808,
    "X": 900,
    "Y": 405,
    "Delta": null,
    "KeyCode": null
  },
  {
    "Type": "MouseMove",
    "Time": 54816,
    "X": 897,
    "Y": 411,
    "Delta": null,
    "KeyCode": null
  },
  {
    "Type": "MouseMove",
    "Time": 54841,
    "X": 891,
    "Y": 417,
    "Delta": null,
    "KeyCode": null
  },
  {
    "Type": "MouseMove",
    "Time": 54865,
    "X": 891,
    "Y": 420,
    "Delta": null,
    "KeyCode": null
  },
  {
    "Type": "MouseMove",
    "Time": 54888,
    "X": 894,
    "Y": 423,
    "Delta": null,
    "KeyCode": null
  },
  {
    "Type": "MouseMove",
    "Time": 54912,
    "X": 897,
    "Y": 429,
    "Delta": null,
    "KeyCode": null
  },
  {
    "Type": "MouseMove",
    "Time": 54935,
    "X": 897,
    "Y": 438,
    "Delta": null,
    "KeyCode": null
  },
  {
    "Type": "MouseMove",
    "Time": 54938,
    "X": 894,
    "Y": 441,
    "Delta": null,
    "KeyCode": null
  },
  {
    "Type": "MouseMove",
    "Time": 54969,
    "X": 891,
    "Y": 444,
    "Delta": null,
    "KeyCode": null
  },
  {
    "Type": "MouseMove",
    "Time": 55001,
    "X": 888,
    "Y": 444,
    "Delta": null,
    "KeyCode": null
  },
  {
    "Type": "MouseMove",
    "Time": 55029,
    "X": 894,
    "Y": 441,
    "Delta": null,
    "KeyCode": null
  },
  {
    "Type": "MouseMove",
    "Time": 55052,
    "X": 897,
    "Y": 435,
    "Delta": null,
    "KeyCode": null
  },
  {
    "Type": "MouseMove",
    "Time": 55076,
    "X": 897,
    "Y": 432,
    "Delta": null,
    "KeyCode": null
  },
  {
    "Type": "DragStart",
    "Time": 55241,
    "X": 897,
    "Y": 432,
    "Delta": null,
    "KeyCode": null
  },
  {
    "Type": "DragEnd",
    "Time": 55291,
    "X": 897,
    "Y": 432,
    "Delta": null,
    "KeyCode": null
  },
  {
    "Type": "MouseMove",
    "Time": 55495,
    "X": 903,
    "Y": 426,
    "Delta": null,
    "KeyCode": null
  },
  {
    "Type": "MouseMove",
    "Time": 55502,
    "X": 903,
    "Y": 423,
    "Delta": null,
    "KeyCode": null
  },
  {
    "Type": "MouseMove",
    "Time": 55509,
    "X": 906,
    "Y": 420,
    "Delta": null,
    "KeyCode": null
  },
  {
    "Type": "MouseMove",
    "Time": 55537,
    "X": 915,
    "Y": 411,
    "Delta": null,
    "KeyCode": null
  },
  {
    "Type": "MouseMove",
    "Time": 55542,
    "X": 918,
    "Y": 408,
    "Delta": null,
    "KeyCode": null
  },
  {
    "Type": "MouseMove",
    "Time": 55570,
    "X": 927,
    "Y": 396,
    "Delta": null,
    "KeyCode": null
  },
  {
    "Type": "MouseMove",
    "Time": 55574,
    "X": 930,
    "Y": 390,
    "Delta": null,
    "KeyCode": null
  },
  {
    "Type": "MouseMove",
    "Time": 55599,
    "X": 933,
    "Y": 381,
    "Delta": null,
    "KeyCode": null
  },
  {
    "Type": "MouseMove",
    "Time": 55623,
    "X": 939,
    "Y": 369,
    "Delta": null,
    "KeyCode": null
  },
  {
    "Type": "MouseMove",
    "Time": 55646,
    "X": 948,
    "Y": 357,
    "Delta": null,
    "KeyCode": null
  },
  {
    "Type": "MouseMove",
    "Time": 55668,
    "X": 951,
    "Y": 351,
    "Delta": null,
    "KeyCode": null
  },
  {
    "Type": "MouseMove",
    "Time": 55694,
    "X": 957,
    "Y": 342,
    "Delta": null,
    "KeyCode": null
  },
  {
    "Type": "MouseMove",
    "Time": 55694,
    "X": 957,
    "Y": 339,
    "Delta": null,
    "KeyCode": null
  },
  {
    "Type": "MouseMove",
    "Time": 55702,
    "X": 957,
    "Y": 333,
    "Delta": null,
    "KeyCode": null
  },
  {
    "Type": "MouseMove",
    "Time": 55726,
    "X": 960,
    "Y": 327,
    "Delta": null,
    "KeyCode": null
  },
  {
    "Type": "MouseMove",
    "Time": 55751,
    "X": 966,
    "Y": 318,
    "Delta": null,
    "KeyCode": null
  },
  {
    "Type": "MouseMove",
    "Time": 55773,
    "X": 975,
    "Y": 312,
    "Delta": null,
    "KeyCode": null
  },
  {
    "Type": "MouseMove",
    "Time": 55775,
    "X": 975,
    "Y": 309,
    "Delta": null,
    "KeyCode": null
  },
  {
    "Type": "MouseMove",
    "Time": 55805,
    "X": 978,
    "Y": 309,
    "Delta": null,
    "KeyCode": null
  },
  {
    "Type": "MouseMove",
    "Time": 55829,
    "X": 978,
    "Y": 303,
    "Delta": null,
    "KeyCode": null
  },
  {
    "Type": "MouseMove",
    "Time": 55850,
    "X": 981,
    "Y": 294,
    "Delta": null,
    "KeyCode": null
  },
  {
    "Type": "MouseMove",
    "Time": 55856,
    "X": 984,
    "Y": 294,
    "Delta": null,
    "KeyCode": null
  },
  {
    "Type": "MouseMove",
    "Time": 55891,
    "X": 984,
    "Y": 288,
    "Delta": null,
    "KeyCode": null
  },
  {
    "Type": "MouseMove",
    "Time": 55937,
    "X": 984,
    "Y": 285,
    "Delta": null,
    "KeyCode": null
  },
  {
    "Type": "MouseMove",
    "Time": 55997,
    "X": 984,
    "Y": 282,
    "Delta": null,
    "KeyCode": null
  },
  {
    "Type": "DragStart",
    "Time": 56086,
    "X": 984,
    "Y": 282,
    "Delta": null,
    "KeyCode": null
  },
  {
    "Type": "DragEnd",
    "Time": 56139,
    "X": 984,
    "Y": 282,
    "Delta": null,
    "KeyCode": null
  },
  {
    "Type": "MouseMove",
    "Time": 56278,
    "X": 984,
    "Y": 285,
    "Delta": null,
    "KeyCode": null
  },
  {
    "Type": "MouseMove",
    "Time": 56300,
    "X": 981,
    "Y": 288,
    "Delta": null,
    "KeyCode": null
  },
  {
    "Type": "MouseMove",
    "Time": 56313,
    "X": 981,
    "Y": 291,
    "Delta": null,
    "KeyCode": null
  },
  {
    "Type": "MouseMove",
    "Time": 56341,
    "X": 981,
    "Y": 294,
    "Delta": null,
    "KeyCode": null
  },
  {
    "Type": "MouseMove",
    "Time": 56348,
    "X": 978,
    "Y": 294,
    "Delta": null,
    "KeyCode": null
  },
  {
    "Type": "MouseMove",
    "Time": 56372,
    "X": 978,
    "Y": 300,
    "Delta": null,
    "KeyCode": null
  },
  {
    "Type": "MouseMove",
    "Time": 56396,
    "X": 975,
    "Y": 303,
    "Delta": null,
    "KeyCode": null
  },
  {
    "Type": "MouseMove",
    "Time": 56419,
    "X": 972,
    "Y": 306,
    "Delta": null,
    "KeyCode": null
  },
  {
    "Type": "MouseMove",
    "Time": 56420,
    "X": 972,
    "Y": 309,
    "Delta": null,
    "KeyCode": null
  },
  {
    "Type": "MouseMove",
    "Time": 56428,
    "X": 972,
    "Y": 312,
    "Delta": null,
    "KeyCode": null
  },
  {
    "Type": "MouseMove",
    "Time": 56451,
    "X": 969,
    "Y": 318,
    "Delta": null,
    "KeyCode": null
  },
  {
    "Type": "MouseMove",
    "Time": 56476,
    "X": 966,
    "Y": 330,
    "Delta": null,
    "KeyCode": null
  },
  {
    "Type": "MouseMove",
    "Time": 56500,
    "X": 960,
    "Y": 339,
    "Delta": null,
    "KeyCode": null
  },
  {
    "Type": "MouseMove",
    "Time": 56501,
    "X": 957,
    "Y": 342,
    "Delta": null,
    "KeyCode": null
  },
  {
    "Type": "MouseMove",
    "Time": 56523,
    "X": 954,
    "Y": 351,
    "Delta": null,
    "KeyCode": null
  },
  {
    "Type": "MouseMove",
    "Time": 56524,
    "X": 951,
    "Y": 354,
    "Delta": null,
    "KeyCode": null
  },
  {
    "Type": "MouseMove",
    "Time": 56532,
    "X": 948,
    "Y": 357,
    "Delta": null,
    "KeyCode": null
  },
  {
    "Type": "MouseMove",
    "Time": 56540,
    "X": 945,
    "Y": 360,
    "Delta": null,
    "KeyCode": null
  },
  {
    "Type": "MouseMove",
    "Time": 56548,
    "X": 945,
    "Y": 363,
    "Delta": null,
    "KeyCode": null
  },
  {
    "Type": "MouseMove",
    "Time": 56579,
    "X": 936,
    "Y": 372,
    "Delta": null,
    "KeyCode": null
  },
  {
    "Type": "MouseMove",
    "Time": 56601,
    "X": 933,
    "Y": 381,
    "Delta": null,
    "KeyCode": null
  },
  {
    "Type": "MouseMove",
    "Time": 56606,
    "X": 930,
    "Y": 384,
    "Delta": null,
    "KeyCode": null
  },
  {
    "Type": "MouseMove",
    "Time": 56613,
    "X": 930,
    "Y": 387,
    "Delta": null,
    "KeyCode": null
  },
  {
    "Type": "MouseMove",
    "Time": 56622,
    "X": 927,
    "Y": 390,
    "Delta": null,
    "KeyCode": null
  },
  {
    "Type": "MouseMove",
    "Time": 56630,
    "X": 924,
    "Y": 390,
    "Delta": null,
    "KeyCode": null
  },
  {
    "Type": "MouseMove",
    "Time": 56658,
    "X": 918,
    "Y": 396,
    "Delta": null,
    "KeyCode": null
  },
  {
    "Type": "MouseMove",
    "Time": 56682,
    "X": 915,
    "Y": 402,
    "Delta": null,
    "KeyCode": null
  },
  {
    "Type": "MouseMove",
    "Time": 56694,
    "X": 915,
    "Y": 405,
    "Delta": null,
    "KeyCode": null
  },
  {
    "Type": "MouseMove",
    "Time": 56702,
    "X": 912,
    "Y": 405,
    "Delta": null,
    "KeyCode": null
  },
  {
    "Type": "MouseMove",
    "Time": 56737,
    "X": 912,
    "Y": 408,
    "Delta": null,
    "KeyCode": null
  },
  {
    "Type": "MouseMove",
    "Time": 56742,
    "X": 909,
    "Y": 408,
    "Delta": null,
    "KeyCode": null
  },
  {
    "Type": "MouseMove",
    "Time": 56767,
    "X": 906,
    "Y": 414,
    "Delta": null,
    "KeyCode": null
  },
  {
    "Type": "MouseMove",
    "Time": 56798,
    "X": 903,
    "Y": 420,
    "Delta": null,
    "KeyCode": null
  },
  {
    "Type": "MouseMove",
    "Time": 56827,
    "X": 900,
    "Y": 423,
    "Delta": null,
    "KeyCode": null
  },
  {
    "Type": "MouseMove",
    "Time": 56850,
    "X": 897,
    "Y": 426,
    "Delta": null,
    "KeyCode": null
  },
  {
    "Type": "MouseMove",
    "Time": 56873,
    "X": 894,
    "Y": 429,
    "Delta": null,
    "KeyCode": null
  },
  {
    "Type": "MouseMove",
    "Time": 57104,
    "X": 894,
    "Y": 426,
    "Delta": null,
    "KeyCode": null
  },
  {
    "Type": "MouseMove",
    "Time": 57112,
    "X": 897,
    "Y": 426,
    "Delta": null,
    "KeyCode": null
  },
  {
    "Type": "DragStart",
    "Time": 57208,
    "X": 897,
    "Y": 426,
    "Delta": null,
    "KeyCode": null
  },
  {
    "Type": "DragEnd",
    "Time": 57263,
    "X": 897,
    "Y": 426,
    "Delta": null,
    "KeyCode": null
  },
  {
    "Type": "MouseMove",
    "Time": 57549,
    "X": 900,
    "Y": 426,
    "Delta": null,
    "KeyCode": null
  },
  {
    "Type": "MouseMove",
    "Time": 57643,
    "X": 903,
    "Y": 423,
    "Delta": null,
    "KeyCode": null
  },
  {
    "Type": "MouseMove",
    "Time": 57688,
    "X": 906,
    "Y": 420,
    "Delta": null,
    "KeyCode": null
  },
  {
    "Type": "MouseMove",
    "Time": 57711,
    "X": 909,
    "Y": 417,
    "Delta": null,
    "KeyCode": null
  },
  {
    "Type": "MouseMove",
    "Time": 57716,
    "X": 912,
    "Y": 414,
    "Delta": null,
    "KeyCode": null
  },
  {
    "Type": "MouseMove",
    "Time": 57726,
    "X": 912,
    "Y": 411,
    "Delta": null,
    "KeyCode": null
  },
  {
    "Type": "MouseMove",
    "Time": 57731,
    "X": 915,
    "Y": 408,
    "Delta": null,
    "KeyCode": null
  },
  {
    "Type": "MouseMove",
    "Time": 57762,
    "X": 921,
    "Y": 399,
    "Delta": null,
    "KeyCode": null
  },
  {
    "Type": "MouseMove",
    "Time": 57785,
    "X": 927,
    "Y": 387,
    "Delta": null,
    "KeyCode": null
  },
  {
    "Type": "MouseMove",
    "Time": 57789,
    "X": 930,
    "Y": 384,
    "Delta": null,
    "KeyCode": null
  },
  {
    "Type": "MouseMove",
    "Time": 57798,
    "X": 930,
    "Y": 381,
    "Delta": null,
    "KeyCode": null
  },
  {
    "Type": "MouseMove",
    "Time": 57825,
    "X": 933,
    "Y": 372,
    "Delta": null,
    "KeyCode": null
  },
  {
    "Type": "MouseMove",
    "Time": 57855,
    "X": 936,
    "Y": 366,
    "Delta": null,
    "KeyCode": null
  },
  {
    "Type": "MouseMove",
    "Time": 57884,
    "X": 936,
    "Y": 360,
    "Delta": null,
    "KeyCode": null
  },
  {
    "Type": "MouseMove",
    "Time": 57915,
    "X": 936,
    "Y": 354,
    "Delta": null,
    "KeyCode": null
  },
  {
    "Type": "MouseMove",
    "Time": 57917,
    "X": 939,
    "Y": 354,
    "Delta": null,
    "KeyCode": null
  },
  {
    "Type": "MouseMove",
    "Time": 57947,
    "X": 939,
    "Y": 348,
    "Delta": null,
    "KeyCode": null
  },
  {
    "Type": "MouseMove",
    "Time": 57979,
    "X": 939,
    "Y": 345,
    "Delta": null,
    "KeyCode": null
  },
  {
    "Type": "MouseMove",
    "Time": 57982,
    "X": 939,
    "Y": 342,
    "Delta": null,
    "KeyCode": null
  },
  {
    "Type": "MouseMove",
    "Time": 58008,
    "X": 942,
    "Y": 339,
    "Delta": null,
    "KeyCode": null
  },
  {
    "Type": "MouseMove",
    "Time": 58032,
    "X": 942,
    "Y": 336,
    "Delta": null,
    "KeyCode": null
  },
  {
    "Type": "MouseMove",
    "Time": 58058,
    "X": 942,
    "Y": 333,
    "Delta": null,
    "KeyCode": null
  },
  {
    "Type": "MouseMove",
    "Time": 58081,
    "X": 942,
    "Y": 330,
    "Delta": null,
    "KeyCode": null
  },
  {
    "Type": "MouseMove",
    "Time": 58105,
    "X": 942,
    "Y": 327,
    "Delta": null,
    "KeyCode": null
  },
  {
    "Type": "MouseMove",
    "Time": 59013,
    "X": 945,
    "Y": 327,
    "Delta": null,
    "KeyCode": null
  },
  {
    "Type": "MouseMove",
    "Time": 59035,
    "X": 948,
    "Y": 327,
    "Delta": null,
    "KeyCode": null
  },
  {
    "Type": "MouseMove",
    "Time": 59066,
    "X": 960,
    "Y": 327,
    "Delta": null,
    "KeyCode": null
  },
  {
    "Type": "MouseMove",
    "Time": 59069,
    "X": 966,
    "Y": 324,
    "Delta": null,
    "KeyCode": null
  },
  {
    "Type": "MouseMove",
    "Time": 59096,
    "X": 978,
    "Y": 324,
    "Delta": null,
    "KeyCode": null
  },
  {
    "Type": "DragStart",
    "Time": 59365,
    "X": 978,
    "Y": 324,
    "Delta": null,
    "KeyCode": null
  },
  {
    "Type": "DragEnd",
    "Time": 59447,
    "X": 978,
    "Y": 324,
    "Delta": null,
    "KeyCode": null
  },
  {
    "Type": "MouseMove",
    "Time": 59492,
    "X": 981,
    "Y": 324,
    "Delta": null,
    "KeyCode": null
  },
  {
    "Type": "MouseMove",
    "Time": 59604,
    "X": 978,
    "Y": 327,
    "Delta": null,
    "KeyCode": null
  },
  {
    "Type": "MouseMove",
    "Time": 59610,
    "X": 975,
    "Y": 330,
    "Delta": null,
    "KeyCode": null
  },
  {
    "Type": "MouseMove",
    "Time": 59637,
    "X": 972,
    "Y": 336,
    "Delta": null,
    "KeyCode": null
  },
  {
    "Type": "MouseMove",
    "Time": 59662,
    "X": 966,
    "Y": 342,
    "Delta": null,
    "KeyCode": null
  },
  {
    "Type": "MouseMove",
    "Time": 59685,
    "X": 948,
    "Y": 354,
    "Delta": null,
    "KeyCode": null
  },
  {
    "Type": "MouseMove",
    "Time": 59690,
    "X": 939,
    "Y": 357,
    "Delta": null,
    "KeyCode": null
  },
  {
    "Type": "MouseMove",
    "Time": 59714,
    "X": 921,
    "Y": 366,
    "Delta": null,
    "KeyCode": null
  },
  {
    "Type": "MouseMove",
    "Time": 59714,
    "X": 912,
    "Y": 369,
    "Delta": null,
    "KeyCode": null
  },
  {
    "Type": "MouseMove",
    "Time": 59744,
    "X": 876,
    "Y": 378,
    "Delta": null,
    "KeyCode": null
  },
  {
    "Type": "MouseMove",
    "Time": 59747,
    "X": 864,
    "Y": 381,
    "Delta": null,
    "KeyCode": null
  },
  {
    "Type": "MouseMove",
    "Time": 59776,
    "X": 822,
    "Y": 390,
    "Delta": null,
    "KeyCode": null
  },
  {
    "Type": "MouseMove",
    "Time": 59800,
    "X": 777,
    "Y": 402,
    "Delta": null,
    "KeyCode": null
  },
  {
    "Type": "MouseMove",
    "Time": 59824,
    "X": 720,
    "Y": 408,
    "Delta": null,
    "KeyCode": null
  },
  {
    "Type": "MouseMove",
    "Time": 59828,
    "X": 705,
    "Y": 411,
    "Delta": null,
    "KeyCode": null
  },
  {
    "Type": "MouseMove",
    "Time": 59859,
    "X": 651,
    "Y": 414,
    "Delta": null,
    "KeyCode": null
  },
  {
    "Type": "MouseMove",
    "Time": 59860,
    "X": 639,
    "Y": 414,
    "Delta": null,
    "KeyCode": null
  },
  {
    "Type": "MouseMove",
    "Time": 59890,
    "X": 603,
    "Y": 417,
    "Delta": null,
    "KeyCode": null
  },
  {
    "Type": "MouseMove",
    "Time": 59915,
    "X": 594,
    "Y": 417,
    "Delta": null,
    "KeyCode": null
  },
  {
    "Type": "MouseMove",
    "Time": 60028,
    "X": 594,
    "Y": 411,
    "Delta": null,
    "KeyCode": null
  },
  {
    "Type": "MouseMove",
    "Time": 60051,
    "X": 594,
    "Y": 408,
    "Delta": null,
    "KeyCode": null
  },
  {
    "Type": "MouseMove",
    "Time": 60052,
    "X": 594,
    "Y": 405,
    "Delta": null,
    "KeyCode": null
  },
  {
    "Type": "MouseMove",
    "Time": 60078,
    "X": 594,
    "Y": 402,
    "Delta": null,
    "KeyCode": null
  },
  {
    "Type": "MouseMove",
    "Time": 60080,
    "X": 594,
    "Y": 399,
    "Delta": null,
    "KeyCode": null
  },
  {
    "Type": "MouseMove",
    "Time": 60104,
    "X": 594,
    "Y": 396,
    "Delta": null,
    "KeyCode": null
  },
  {
    "Type": "MouseMove",
    "Time": 60132,
    "X": 597,
    "Y": 390,
    "Delta": null,
    "KeyCode": null
  },
  {
    "Type": "MouseMove",
    "Time": 60133,
    "X": 600,
    "Y": 390,
    "Delta": null,
    "KeyCode": null
  },
  {
    "Type": "MouseMove",
    "Time": 60142,
    "X": 600,
    "Y": 387,
    "Delta": null,
    "KeyCode": null
  },
  {
    "Type": "MouseMove",
    "Time": 60176,
    "X": 603,
    "Y": 384,
    "Delta": null,
    "KeyCode": null
  },
  {
    "Type": "MouseMove",
    "Time": 60182,
    "X": 606,
    "Y": 384,
    "Delta": null,
    "KeyCode": null
  },
  {
    "Type": "MouseMove",
    "Time": 60264,
    "X": 606,
    "Y": 381,
    "Delta": null,
    "KeyCode": null
  },
  {
    "Type": "MouseMove",
    "Time": 60278,
    "X": 609,
    "Y": 381,
    "Delta": null,
    "KeyCode": null
  },
  {
    "Type": "MouseMove",
    "Time": 60305,
    "X": 612,
    "Y": 375,
    "Delta": null,
    "KeyCode": null
  },
  {
    "Type": "MouseMove",
    "Time": 60334,
    "X": 612,
    "Y": 372,
    "Delta": null,
    "KeyCode": null
  },
  {
    "Type": "MouseMove",
    "Time": 60362,
    "X": 615,
    "Y": 372,
    "Delta": null,
    "KeyCode": null
  },
  {
    "Type": "MouseMove",
    "Time": 60720,
    "X": 612,
    "Y": 372,
    "Delta": null,
    "KeyCode": null
  },
  {
    "Type": "MouseMove",
    "Time": 60730,
    "X": 612,
    "Y": 369,
    "Delta": null,
    "KeyCode": null
  },
  {
    "Type": "DragStart",
    "Time": 60852,
    "X": 612,
    "Y": 369,
    "Delta": null,
    "KeyCode": null
  },
  {
    "Type": "DragEnd",
    "Time": 60923,
    "X": 612,
    "Y": 369,
    "Delta": null,
    "KeyCode": null
  },
  {
    "Type": "MouseMove",
    "Time": 61202,
    "X": 612,
    "Y": 372,
    "Delta": null,
    "KeyCode": null
  },
  {
    "Type": "MouseMove",
    "Time": 61298,
    "X": 612,
    "Y": 375,
    "Delta": null,
    "KeyCode": null
  },
  {
    "Type": "DragStart",
    "Time": 63467,
    "X": 612,
    "Y": 375,
    "Delta": null,
    "KeyCode": null
  },
  {
    "Type": "DragEnd",
    "Time": 63561,
    "X": 612,
    "Y": 375,
    "Delta": null,
    "KeyCode": null
  },
  {
    "Type": "MouseMove",
    "Time": 63798,
    "X": 612,
    "Y": 378,
    "Delta": null,
    "KeyCode": null
  },
  {
    "Type": "MouseMove",
    "Time": 63822,
    "X": 612,
    "Y": 384,
    "Delta": null,
    "KeyCode": null
  },
  {
    "Type": "MouseMove",
    "Time": 63824,
    "X": 612,
    "Y": 390,
    "Delta": null,
    "KeyCode": null
  },
  {
    "Type": "MouseMove",
    "Time": 63832,
    "X": 612,
    "Y": 393,
    "Delta": null,
    "KeyCode": null
  },
  {
    "Type": "MouseMove",
    "Time": 63840,
    "X": 612,
    "Y": 396,
    "Delta": null,
    "KeyCode": null
  },
  {
    "Type": "MouseMove",
    "Time": 63848,
    "X": 612,
    "Y": 399,
    "Delta": null,
    "KeyCode": null
  },
  {
    "Type": "MouseMove",
    "Time": 63856,
    "X": 612,
    "Y": 402,
    "Delta": null,
    "KeyCode": null
  },
  {
    "Type": "MouseMove",
    "Time": 63882,
    "X": 612,
    "Y": 408,
    "Delta": null,
    "KeyCode": null
  },
  {
    "Type": "MouseMove",
    "Time": 64036,
    "X": 606,
    "Y": 408,
    "Delta": null,
    "KeyCode": null
  },
  {
    "Type": "MouseMove",
    "Time": 64067,
    "X": 603,
    "Y": 408,
    "Delta": null,
    "KeyCode": null
  },
  {
    "Type": "MouseMove",
    "Time": 64396,
    "X": 603,
    "Y": 411,
    "Delta": null,
    "KeyCode": null
  },
  {
    "Type": "MouseMove",
    "Time": 64421,
    "X": 603,
    "Y": 417,
    "Delta": null,
    "KeyCode": null
  },
  {
    "Type": "MouseMove",
    "Time": 64445,
    "X": 603,
    "Y": 423,
    "Delta": null,
    "KeyCode": null
  },
  {
    "Type": "MouseMove",
    "Time": 64468,
    "X": 606,
    "Y": 432,
    "Delta": null,
    "KeyCode": null
  },
  {
    "Type": "MouseMove",
    "Time": 64490,
    "X": 606,
    "Y": 435,
    "Delta": null,
    "KeyCode": null
  },
  {
    "Type": "MouseMove",
    "Time": 64491,
    "X": 606,
    "Y": 438,
    "Delta": null,
    "KeyCode": null
  },
  {
    "Type": "MouseMove",
    "Time": 64508,
    "X": 606,
    "Y": 441,
    "Delta": null,
    "KeyCode": null
  },
  {
    "Type": "MouseMove",
    "Time": 64532,
    "X": 606,
    "Y": 444,
    "Delta": null,
    "KeyCode": null
  },
  {
    "Type": "MouseMove",
    "Time": 64555,
    "X": 606,
    "Y": 450,
    "Delta": null,
    "KeyCode": null
  },
  {
    "Type": "MouseMove",
    "Time": 64577,
    "X": 606,
    "Y": 456,
    "Delta": null,
    "KeyCode": null
  },
  {
    "Type": "MouseMove",
    "Time": 64602,
    "X": 606,
    "Y": 462,
    "Delta": null,
    "KeyCode": null
  },
  {
    "Type": "MouseMove",
    "Time": 64625,
    "X": 609,
    "Y": 468,
    "Delta": null,
    "KeyCode": null
  },
  {
    "Type": "MouseMove",
    "Time": 64628,
    "X": 609,
    "Y": 471,
    "Delta": null,
    "KeyCode": null
  },
  {
    "Type": "MouseMove",
    "Time": 64656,
    "X": 609,
    "Y": 480,
    "Delta": null,
    "KeyCode": null
  },
  {
    "Type": "MouseMove",
    "Time": 64679,
    "X": 609,
    "Y": 495,
    "Delta": null,
    "KeyCode": null
  },
  {
    "Type": "MouseMove",
    "Time": 64703,
    "X": 609,
    "Y": 507,
    "Delta": null,
    "KeyCode": null
  },
  {
    "Type": "MouseMove",
    "Time": 64727,
    "X": 609,
    "Y": 519,
    "Delta": null,
    "KeyCode": null
  },
  {
    "Type": "MouseMove",
    "Time": 64752,
    "X": 606,
    "Y": 528,
    "Delta": null,
    "KeyCode": null
  },
  {
    "Type": "MouseMove",
    "Time": 64776,
    "X": 606,
    "Y": 537,
    "Delta": null,
    "KeyCode": null
  },
  {
    "Type": "MouseMove",
    "Time": 64800,
    "X": 606,
    "Y": 546,
    "Delta": null,
    "KeyCode": null
  },
  {
    "Type": "MouseMove",
    "Time": 64826,
    "X": 606,
    "Y": 555,
    "Delta": null,
    "KeyCode": null
  },
  {
    "Type": "MouseMove",
    "Time": 64853,
    "X": 606,
    "Y": 564,
    "Delta": null,
    "KeyCode": null
  },
  {
    "Type": "MouseMove",
    "Time": 64854,
    "X": 603,
    "Y": 567,
    "Delta": null,
    "KeyCode": null
  },
  {
    "Type": "MouseMove",
    "Time": 64882,
    "X": 603,
    "Y": 573,
    "Delta": null,
    "KeyCode": null
  },
  {
    "Type": "MouseMove",
    "Time": 64887,
    "X": 603,
    "Y": 576,
    "Delta": null,
    "KeyCode": null
  },
  {
    "Type": "MouseMove",
    "Time": 64912,
    "X": 603,
    "Y": 579,
    "Delta": null,
    "KeyCode": null
  },
  {
    "Type": "MouseMove",
    "Time": 64935,
    "X": 603,
    "Y": 582,
    "Delta": null,
    "KeyCode": null
  },
  {
    "Type": "MouseMove",
    "Time": 64935,
    "X": 603,
    "Y": 585,
    "Delta": null,
    "KeyCode": null
  },
  {
    "Type": "MouseMove",
    "Time": 64959,
    "X": 600,
    "Y": 591,
    "Delta": null,
    "KeyCode": null
  },
  {
    "Type": "MouseMove",
    "Time": 64988,
    "X": 600,
    "Y": 594,
    "Delta": null,
    "KeyCode": null
  },
  {
    "Type": "MouseMove",
    "Time": 64992,
    "X": 600,
    "Y": 597,
    "Delta": null,
    "KeyCode": null
  },
  {
    "Type": "MouseMove",
    "Time": 65020,
    "X": 600,
    "Y": 603,
    "Delta": null,
    "KeyCode": null
  },
  {
    "Type": "MouseMove",
    "Time": 65052,
    "X": 600,
    "Y": 606,
    "Delta": null,
    "KeyCode": null
  },
  {
    "Type": "MouseMove",
    "Time": 65075,
    "X": 597,
    "Y": 606,
    "Delta": null,
    "KeyCode": null
  }
]